Workbook
Name Sections: [2]Filters!$A$2:$A$4

Sheet Corn Processors
A1: num` | B1: CA Co ID | C1: CA Facility ID | D1: EPM prev | E1: EPM | F1: Status | G1: Ownership | H1: Name | I1: State | J1: City | K1: Zip Code | L1: County | M1: PADD | N1: Latitude | O1: Longitude | P1: Year Build | Q1: Technology | R1: Multi-Plant | S1: Efficient Producer | T1: High Pro | U1: CHP | V1: Special Tech | W1: Wind Turbine | X1: White Fox | Y1: Waste heat | Z1: DCO Enhancement | AA1: ICM P10 | AB1: Feedstock | AC1: RINs | AD1: Basis Source | AE1: OPEX | AF1: Air Permit Current | AG1: RIN 2007 | AH1: Report | AI1: State ID | AJ1: Ethanol Capacity | AK1: Ethanol Production | AL1: Corn Grind | AM1: Grain Storage | AN1: Days Storage | AO1: DDGS | AP1: Dryer Types | AQ1: DCO Yield Cat | AR1: DCO Yield (lb/bu) | AS1: DCO Production | AT1: Announced Pipeline | AU1: C02 Pipeline -Direct | AV1: C02 Pipeline -3rd Party | AW1: CI Drop with Pipele | AX1: Sponsor | AY1: CI Drop Potenital | AZ1: CCS Gal (Mln) | BA1: CCS Tons (Mln) | BB1: Corn Acres 2023 | BC1: Public Financials | BD1: Website | BE1: Rail Lines | BF1: Unit Trains (Ethanol) | BG1: Truck ONLY | BH1: Other | BI1: Chinese DDGS Importer | BJ1: RFA Membership | BK1: Index | BL1: Transactions
A2: 1 | B2: 5049 | C2: 70144 | D2: 3546 | E2: 3546 | F2: =IF(A2>0,"Active","Retired") -> Active | G2: Absolute Energy | H2: Absolute Energy | I2: IA | J2: St. Ansgar | K2: 50472 | L2: Mitchell | M2: 2 | N2: 43.49951 | O2: -92.91709 | P2: 2007 | Q2: ICM | R2: =COUNTIF(G:G,"="&G2) -> 1 | S2: EP3 | AB2: Corn | AC2: D6 | AD2: Website | AE2: =IF(BK2=1,"Low","High") -> High | AF2: 150 | AG2: 110 | AH2: 06-A-601 | AJ2: =VLOOKUP(E2,'[1]Ethanol Plant Listing 2025'!$B$3:$E$220,4,FALSE) -> 130 | AK2: =+AJ2*[1]Yield!$K$4 -> 123.5 | AL2: =AK2/VLOOKUP(Q2,[1]Yield!$E$5:$F$14,2,FALSE) -> 41.864407 | AO2: =ROUND((+AL2*13.1*1000000)/2000,-3) -> 274000 | AP2: Rotary Dryer | AQ2: =IF(G2="POET Biorefining",G2,IF(T2="FQPT HI Pro",T2,IF(Z2="ICM FOT",Z2,IF(Q2="ICM",Q2,IF(Q2="ADM",Q2,"None"))))) -> ICM | AR2: =VLOOKUP(AQ2,[1]Yield!$A$5:$B$10,2,FALSE) -> 0.9 | AS2: =(AL2)*AR2 -> 37.677966 | AT2: Likely | AV2: SCS | AX2: =IFERROR(VLOOKUP(E2,[1]Sheet3!$C$2:$E$68,2,FALSE),"None") -> Summit Carbon Solutions | AY2: =IFERROR(VLOOKUP(AX2,[1]Sheet3!$H$3:$I$5,2,FALSE),0) -> 31 | AZ2: =AJ2 -> 130 | BA2: =+AJ2*6.85*0.48/2 -> 213.72 | BB2: =SUMIFS('[1]Corn 2023'!V:V,'[1]Corn 2023'!B:B,"=2023",'[1]Corn 2023'!L:L,"="&'Corn Processors'!L2) -> 151500 | BD2: https://absenergy.org/ | BE2: CP/CN | BF2: Yes | BI2: Importer | BJ2: Member | BK2: =IF(M2=2,10,5)+IF(Q2="ICM",10,5)+IF(X2="Y",10,5) -> 25
A3: 2 | D3: 2856 | E3: 3547 | F3: =IF(A3>0,"Active","Retired") -> Active | G3: ACE Ethanol | H3: =VLOOKUP(E3,'[1]EPA Ethanol Capacity 2024'!$B$5:$C$235,2,FALSE) -> Ace Ethanol LLC | I3: WI | J3: Stanley | K3: 54768 | L3: Chippewa | M3: 2 | N3: 44.9589 | O3: -90.9608 | P3: 2001 | Q3: Delta-T | R3: =COUNTIF(G:G,"="&G3) -> 2 | X3: White Fox ICE | Z3: Fluid Quip | AB3: Corn | AC3: D6/D3 | AD3: Website | AE3: =IF(BK3=1,"Low","High") -> High | AG3: ` | AJ3: =VLOOKUP(E3,'[1]Ethanol Plant Listing 2025'!$B$3:$E$220,4,FALSE) -> 52 | AK3: =+AJ3*[1]Yield!$K$4 -> 49.4 | AL3: =AK3/VLOOKUP(Q3,[1]Yield!$E$5:$F$14,2,FALSE) -> 17.152778 | AO3: =ROUND((+AL3*13.1*1000000)/2000,-3) -> 112000 | AP3: Ring Dryer | AQ3: =IF(G3="POET Biorefining",G3,IF(T3="FQPT HI Pro",T3,IF(Z3="ICM FOT",Z3,IF(Q3="ICM",Q3,IF(Q3="ADM",Q3,"None"))))) -> None | AR3: =VLOOKUP(AQ3,[1]Yield!$A$5:$B$10,2,FALSE) -> 0.815 | AS3: =(AL3)*AR3 -> 13.979514 | AT3: Unlikely | AY3: =IFERROR(VLOOKUP(AX3,[1]Sheet3!$H$3:$I$5,2,FALSE),0) -> 0 | AZ3: =AJ3 -> 52 | BA3: =+AJ3*6.85*0.48/2 -> 85.488 | BB3: =SUMIFS('[1]Corn 2023'!V:V,'[1]Corn 2023'!B:B,"=2023",'[1]Corn 2023'!L:L,"="&'Corn Processors'!L3) -> 0 | BD3: https://www.aceethanol.com/ | BE3: CN | BF3: No | BI3: Importer | BJ3: Member | BK3: =IF(M3=2,10,5)+IF(Q3="ICM",10,5)+IF(X3="Y",10,5) -> 20
A4: 3 | D4: 2857 | E4: 3548 | F4: =IF(A4>0,"Active","Retired") -> Active | G4: Pearl City Elevator | H4: =VLOOKUP(E4,'[1]EPA Ethanol Capacity 2024'!$B$5:$C$235,2,FALSE) -> Adkins Energy LLC | I4: IL | J4: Lena | K4: 61048 | L4: Stephenson | M4: 2 | N4: 42.3586 | O4: -89.80342 | P4: 2002 | Q4: ICM | R4: =COUNTIF(G:G,"="&G4) -> 1 | S4: EP3 | U4: CHP | AB4: Corn | AC4: D6 | AD4: https://pce-coops.com/resources/cashbids/ | AE4: =IF(BK4=1,"Low","High") -> High | AJ4: =VLOOKUP(E4,'[1]Ethanol Plant Listing 2025'!$B$3:$E$220,4,FALSE) -> 60 | AK4: =+AJ4*[1]Yield!$K$4 -> 57 | AL4: =AK4/VLOOKUP(Q4,[1]Yield!$E$5:$F$14,2,FALSE) -> 19.322034 | AO4: =ROUND((+AL4*13.1*1000000)/2000,-3) -> 127000 | AP4: Rotary Dryer | AQ4: =IF(G4="POET Biorefining",G4,IF(T4="FQPT HI Pro",T4,IF(Z4="ICM FOT",Z4,IF(Q4="ICM",Q4,IF(Q4="ADM",Q4,"None"))))) -> ICM | AR4: =VLOOKUP(AQ4,[1]Yield!$A$5:$B$10,2,FALSE) -> 0.9 | AS4: =(AL4)*AR4 -> 17.389831 | AT4: Likely | AY4: =IFERROR(VLOOKUP(AX4,[1]Sheet3!$H$3:$I$5,2,FALSE),0) -> 0 | AZ4: =AJ4 -> 60 | BA4: =+AJ4*6.85*0.48/2 -> 98.64 | BB4: =SUMIFS('[1]Corn 2023'!V:V,'[1]Corn 2023'!B:B,"=2023",'[1]Corn 2023'!L:L,"="&'Corn Processors'!L4) -> 0 | BD4: https://www.adkinsenergy.com/ | BE4: CN | BF4: No | BJ4: Member | BK4: =IF(M4=2,10,5)+IF(Q4="ICM",10,5)+IF(X4="Y",10,5) -> 25
A5: 4 | B5: 3566 | C5: 70234 | D5: 3135 | E5: 3549 | F5: =IF(A5<300,"Active","Retired") -> Active | G5: Aemetis | H5: =VLOOKUP(E5,'[1]EPA Ethanol Capacity 2024'!$B$5:$C$235,2,FALSE) -> Aemetis Advanced Fuels Keys Inc | I5: CA | J5: Keyes | K5: 95307 | L5: Stanislaus | M5: 5 | N5: 37.553007 | O5: -120.91648 | P5: 2006 | Q5: Delta-T | R5: =COUNTIF(G:G,"="&G5) -> 1 | AB5: Corn/Milo | AC5: D6/D5 | AD5: Website | AE5: =IF(BK5=1,"Low","High") -> High | AJ5: =VLOOKUP(E5,'[1]Ethanol Plant Listing 2025'!$B$3:$E$220,4,FALSE) -> 70 | AK5: =+AJ5*[1]Yield!$K$4 -> 66.5 | AL5: =AK5/VLOOKUP(Q5,[1]Yield!$E$5:$F$14,2,FALSE) -> 23.090278 | AO5: =ROUND((+AL5*13.1*1000000)/2000,-3) -> 151000 | AP5: Ring Dryer | AQ5: =IF(G5="POET Biorefining",G5,IF(T5="FQPT HI Pro",T5,IF(Z5="ICM FOT",Z5,IF(Q5="ICM",Q5,IF(Q5="ADM",Q5,"None"))))) -> None | AR5: =VLOOKUP(AQ5,[1]Yield!$A$5:$B$10,2,FALSE) -> 0.815 | AS5: =(AL5)*AR5 -> 18.818576 | AT5: Likely | AY5: =IFERROR(VLOOKUP(AX5,[1]Sheet3!$H$3:$I$5,2,FALSE),0) -> 0 | AZ5: =AJ5 -> 70 | BA5: =+AJ5*6.85*0.48/2 -> 115.08 | BB5: =SUMIFS('[1]Corn 2023'!V:V,'[1]Corn 2023'!B:B,"=2023",'[1]Corn 2023'!L:L,"="&'Corn Processors'!L5) -> 0 | BD5: https://www.aemetis.com/ | BE5: UP | BF5: No | BJ5: Member | BK5: =IF(M5=2,10,5)+IF(Q5="ICM",10,5)+IF(X5="Y",10,5) -> 15
A6: 5 | B6: 4825 | C6: 70087 | D6: 3136 | E6: 3550 | F6: =IF(A6<300,"Active","Retired") -> Active | G6: Al–Corn Clean Fuel | H6: =VLOOKUP(E6,'[1]EPA Ethanol Capacity 2024'!$B$5:$C$235,2,FALSE) -> Al-Corn Clean Fuel | I6: MN | J6: Claremont | K6: 55924 | L6: Dodge | M6: 2 | N6: 44.049412 | O6: -93.017379 | P6: 1996 | Q6: ICM | R6: =COUNTIF(G:G,"="&G6) -> 1 | S6: EP3 | AB6: Corn | AC6: D6 | AD6: Website | AE6: =IF(BK6=1,"Low","High") -> High | AJ6: =VLOOKUP(E6,'[1]Ethanol Plant Listing 2025'!$B$3:$E$220,4,FALSE) -> 130 | AK6: =+AJ6*[1]Yield!$K$4 -> 123.5 | AL6: =AK6/VLOOKUP(Q6,[1]Yield!$E$5:$F$14,2,FALSE) -> 41.864407 | AO6: =ROUND((+AL6*13.1*1000000)/2000,-3) -> 274000 | AP6: Rotary Dryer | AQ6: =IF(G6="POET Biorefining",G6,IF(T6="FQPT HI Pro",T6,IF(Z6="ICM FOT",Z6,IF(Q6="ICM",Q6,IF(Q6="ADM",Q6,"None"))))) -> ICM | AR6: =VLOOKUP(AQ6,[1]Yield!$A$5:$B$10,2,FALSE) -> 0.9 | AS6: =(AL6)*AR6 -> 37.677966 | AT6: Unlikely | AY6: =IFERROR(VLOOKUP(AX6,[1]Sheet3!$H$3:$I$5,2,FALSE),0) -> 0 | AZ6: =AJ6 -> 130 | BA6: =+AJ6*6.85*0.48/2 -> 213.72 | BB6: =SUMIFS('[1]Corn 2023'!V:V,'[1]Corn 2023'!B:B,"=2023",'[1]Corn 2023'!L:L,"="&'Corn Processors'!L6) -> 0 | BD6: http://www.al-corn.com/ | BE6: CP | BF6: Yes | BJ6: Member | BK6: =IF(M6=2,10,5)+IF(Q6="ICM",10,5)+IF(X6="Y",10,5) -> 25
A7: 6 | D7: 3137 | E7: 3551 | F7: =IF(A7<300,"Active","Retired") -> Active | G7: Alto | H7: =VLOOKUP(E7,'[1]EPA Ethanol Capacity 2024'!$B$5:$C$235,2,FALSE) -> Alto Columbia LLC | I7: OR | J7: Boardman | K7: 97818 | L7: Morrow | M7: 5 | N7: 45.855921 | O7: -119.65608 | P7: 2007 | Q7: Delta-T | R7: =COUNTIF(G:G,"="&G7) -> 5 | AB7: Corn | AC7: D6/D5 | AD7: Website | AE7: =IF(BK7=1,"Low","High") -> High | AJ7: =VLOOKUP(E7,'[1]Ethanol Plant Listing 2025'!$B$3:$E$220,4,FALSE) -> 40 | AK7: =+AJ7*[1]Yield!$K$4 -> 38 | AL7: =AK7/VLOOKUP(Q7,[1]Yield!$E$5:$F$14,2,FALSE) -> 13.194444 | AO7: =ROUND((+AL7*13.1*1000000)/2000,-3) -> 86000 | AP7: Ring Dryer | AQ7: =IF(G7="POET Biorefining",G7,IF(T7="FQPT HI Pro",T7,IF(Z7="ICM FOT",Z7,IF(Q7="ICM",Q7,IF(Q7="ADM",Q7,"None"))))) -> None | AR7: =VLOOKUP(AQ7,[1]Yield!$A$5:$B$10,2,FALSE) -> 0.815 | AS7: =(AL7)*AR7 -> 10.753472 | AT7: Likely | AY7: =IFERROR(VLOOKUP(AX7,[1]Sheet3!$H$3:$I$5,2,FALSE),0) -> 0 | AZ7: =AJ7 -> 40 | BA7: =+AJ7*6.85*0.48/2 -> 65.76 | BB7: =SUMIFS('[1]Corn 2023'!V:V,'[1]Corn 2023'!B:B,"=2023",'[1]Corn 2023'!L:L,"="&'Corn Processors'!L7) -> 0 | BC7: Y | BD7: https://www.altoingredients.com/ | BE7: UP | BF7: Yes | BK7: =IF(M7=2,10,5)+IF(Q7="ICM",10,5)+IF(X7="Y",10,5) -> 15
A8: 7 | D8: 3138 | E8: 3552 | F8: =IF(A8<300,"Active","Retired") -> Active | G8: Alto | H8: =VLOOKUP(E8,'[1]EPA Ethanol Capacity 2024'!$B$5:$C$235,2,FALSE) -> Alto Magic Valley Ethanol | I8: ID | J8: Burley | K8: 83318 | L8: Cassia | M8: 4 | N8: 42.521324 | O8: -113.81569 | P8: 2008 | Q8: Delta-T | R8: =COUNTIF(G:G,"="&G8) -> 5 | T8: Harvesting Tech HI PRO | AB8: Corn | AC8: D6 | AD8: Website | AE8: =IF(BK8=1,"Low","High") -> High | AJ8: =VLOOKUP(E8,'[1]Ethanol Plant Listing 2025'!$B$3:$E$220,4,FALSE) -> 60 | AK8: =+AJ8*[1]Yield!$K$4 -> 57 | AL8: =AK8/VLOOKUP(Q8,[1]Yield!$E$5:$F$14,2,FALSE) -> 19.791667 | AO8: =ROUND((+AL8*13.1*1000000)/2000,-3) -> 130000 | AP8: Ring Dryer | AQ8: =IF(G8="POET Biorefining",G8,IF(T8="FQPT HI Pro",T8,IF(Z8="ICM FOT",Z8,IF(Q8="ICM",Q8,IF(Q8="ADM",Q8,"None"))))) -> None | AR8: =VLOOKUP(AQ8,[1]Yield!$A$5:$B$10,2,FALSE) -> 0.815 | AS8: =(AL8)*AR8 -> 16.130208 | AT8: Likely | AY8: =IFERROR(VLOOKUP(AX8,[1]Sheet3!$H$3:$I$5,2,FALSE),0) -> 0 | AZ8: =AJ8 -> 60 | BA8: =+AJ8*6.85*0.48/2 -> 98.64 | BB8: =SUMIFS('[1]Corn 2023'!V:V,'[1]Corn 2023'!B:B,"=2023",'[1]Corn 2023'!L:L,"="&'Corn Processors'!L8) -> 0 | BC8: Y | BD8: https://www.altoingredients.com/ | BE8: UP | BF8: No | BK8: =IF(M8=2,10,5)+IF(Q8="ICM",10,5)+IF(X8="Y",10,5) -> 15
A9: 8 | D9: 3139 | E9: 3553 | F9: =IF(A9<300,"Active","Retired") -> Active | G9: Alto | H9: =VLOOKUP(E9,'[1]EPA Ethanol Capacity 2024'!$B$5:$C$235,2,FALSE) -> Alto ICP LLC | I9: IL | J9: Pekin | K9: 61554 | L9: Tazewell | M9: 2 | N9: 40.555 | O9: -89.6698 | P9: 0 | Q9: Vogelbusch | R9: =COUNTIF(G:G,"="&G9) -> 5 | AB9: Corn | AC9: D6 | AD9: https://www.altoingredients.com/corn-pricing/ | AE9: =IF(BK9=1,"Low","High") -> High | AJ9: =VLOOKUP(E9,'[1]Ethanol Plant Listing 2025'!$B$3:$E$220,4,FALSE) -> 82 | AK9: =+AJ9*[1]Yield!$K$4 -> 77.9 | AL9: =AK9/VLOOKUP(Q9,[1]Yield!$E$5:$F$14,2,FALSE) -> 26.862069 | AO9: =ROUND((+AL9*13.1*1000000)/2000,-3) -> 176000 | AQ9: =IF(G9="POET Biorefining",G9,IF(T9="FQPT HI Pro",T9,IF(Z9="ICM FOT",Z9,IF(Q9="ICM",Q9,IF(Q9="ADM",Q9,"None"))))) -> None | AR9: =VLOOKUP(AQ9,[1]Yield!$A$5:$B$10,2,FALSE) -> 0.815 | AS9: =(AL9)*AR9 -> 21.892586 | AT9: Likely | AY9: =IFERROR(VLOOKUP(AX9,[1]Sheet3!$H$3:$I$5,2,FALSE),0) -> 0 | AZ9: =AJ9 -> 82 | BA9: =+AJ9*6.85*0.48/2 -> 134.808 | BB9: =SUMIFS('[1]Corn 2023'!V:V,'[1]Corn 2023'!B:B,"=2023",'[1]Corn 2023'!L:L,"="&'Corn Processors'!L9) -> 0 | BC9: Y | BD9: https://www.altoingredients.com/ | BE9: IMRR/BNSF | BF9: Yes | BH9: Barge | BK9: =IF(M9=2,10,5)+IF(Q9="ICM",10,5)+IF(X9="Y",10,5) -> 20 | BL9: 6/27/2017 PEIX purchases ICP for $61M
A10: 9 | D10: 3140 | E10: 3554 | F10: =IF(A10<300,"Active","Retired") -> Active | G10: Alto | H10: =VLOOKUP(E10,'[1]EPA Ethanol Capacity 2024'!$B$5:$C$235,2,FALSE) -> Alto Pekin LLC Dry Mill | I10: IL | J10: Pekin | K10: 61554 | L10: Tazewell | M10: 2 | N10: 40.555063 | O10: -89.663302 | P10: 2007 | Q10: ICM | R10: =COUNTIF(G:G,"="&G10) -> 5 | AB10: Corn | AC10: D6 | AD10: https://www.altoingredients.com/corn-pricing/ | AE10: =IF(BK10=1,"Low","High") -> High | AJ10: =VLOOKUP(E10,'[1]Ethanol Plant Listing 2025'!$B$3:$E$220,4,FALSE) -> 63 | AK10: =+AJ10*[1]Yield!$K$4 -> 59.85 | AL10: =AK10/VLOOKUP(Q10,[1]Yield!$E$5:$F$14,2,FALSE) -> 20.288136 | AO10: =ROUND((+AL10*13.1*1000000)/2000,-3) -> 133000 | AP10: Rotary Dryer | AQ10: =IF(G10="POET Biorefining",G10,IF(T10="FQPT HI Pro",T10,IF(Z10="ICM FOT",Z10,IF(Q10="ICM",Q10,IF(Q10="ADM",Q10,"None"))))) -> ICM | AR10: =VLOOKUP(AQ10,[1]Yield!$A$5:$B$10,2,FALSE) -> 0.9 | AS10: =(AL10)*AR10 -> 18.259322 | AT10: Likely | AU10: Direct | AY10: =IFERROR(VLOOKUP(AX10,[1]Sheet3!$H$3:$I$5,2,FALSE),0) -> 0 | AZ10: =AJ10 -> 63 | BA10: =+AJ10*6.85*0.48/2 -> 103.572 | BB10: =SUMIFS('[1]Corn 2023'!V:V,'[1]Corn 2023'!B:B,"=2023",'[1]Corn 2023'!L:L,"="&'Corn Processors'!L10) -> 0 | BC10: Y | BD10: https://www.altoingredients.com/ | BE10: IMRR/BNSF | BF10: Yes | BH10: Barge | BK10: =IF(M10=2,10,5)+IF(Q10="ICM",10,5)+IF(X10="Y",10,5) -> 25 | BL10: 12/2014 PEIX purchases Aventine for $380M (315M gals)
A11: 10 | D11: 3141 | E11: 3555 | F11: =IF(A11<300,"Active","Retired") -> Active | G11: Alto | H11: =VLOOKUP(E11,'[1]EPA Ethanol Capacity 2024'!$B$5:$C$235,2,FALSE) -> Alto Pekin LLC Wet Mill | I11: IL | J11: Pekin | K11: 61554 | L11: Tazewell | M11: 2 | N11: 40.5534 | O11: -89.6631 | P11: 1981 | Q11: Wet Mill | R11: =COUNTIF(G:G,"="&G11) -> 5 | AB11: Corn | AC11: D6 | AD11: https://www.altoingredients.com/corn-pricing/ | AE11: =IF(BK11=1,"Low","High") -> High | AJ11: =VLOOKUP(E11,'[1]Ethanol Plant Listing 2025'!$B$3:$E$220,4,FALSE) -> 100 | AK11: =+AJ11*[1]Yield!$K$4 -> 95 | AL11: =AK11/VLOOKUP(Q11,[1]Yield!$E$5:$F$14,2,FALSE) -> 34.545455 | AO11: =ROUND((+AL11*13.1*1000000)/2000,-3) -> 226000 | AQ11: =IF(G11="POET Biorefining",G11,IF(T11="FQPT HI Pro",T11,IF(Z11="ICM FOT",Z11,IF(Q11="ICM",Q11,IF(Q11="ADM",Q11,"None"))))) -> None | AR11: =VLOOKUP(AQ11,[1]Yield!$A$5:$B$10,2,FALSE) -> 0.815 | AS11: =(AL11)*AR11 -> 28.154545 | AT11: Likely | AU11: Direct | AY11: =IFERROR(VLOOKUP(AX11,[1]Sheet3!$H$3:$I$5,2,FALSE),0) -> 0 | AZ11: =AJ11 -> 100 | BA11: =+AJ11*6.85*0.48/2 -> 164.4 | BB11: =SUMIFS('[1]Corn 2023'!V:V,'[1]Corn 2023'!B:B,"=2023",'[1]Corn 2023'!L:L,"="&'Corn Processors'!L11) -> 0 | BC11: Y | BD11: https://www.altoingredients.com/ | BE11: UP/BNSF/CN/NS/IAIS | BF11: Yes | BH11: Barge | BK11: =IF(M11=2,10,5)+IF(Q11="ICM",10,5)+IF(X11="Y",10,5) -> 20 | BL11: 12/2014 PEIX purchases Aventine for $380M (315M gals)
A12: 11 | E12: 3556 | F12: =IF(A12<300,"Active","Retired") -> Active | G12: Summit Sustainable Ingredients | H12: =VLOOKUP(E12,'[1]EPA Ethanol Capacity 2024'!$B$5:$C$235,2,FALSE) -> Amber Wave | I12: KS | J12: Phillipsburg | K12: 67661 | L12: Phillips | M12: 2 | N12: 38.363339 | O12: -97.783411 | P12: 2023 | Q12: Wheat | R12: =COUNTIF(G:G,"="&G12) -> 1 | AB12: Other Grains | AC12: D6 | AD12: Website | AE12: =IF(BK12=1,"Low","High") -> High | AJ12: =VLOOKUP(E12,'[1]Ethanol Plant Listing 2025'!$B$3:$E$220,4,FALSE) -> 50 | AK12: =+AJ12*[1]Yield!$K$4 -> 47.5 | AL12: =AK12/VLOOKUP(Q12,[1]Yield!$E$5:$F$14,2,FALSE) -> 17.592593 | AO12: =ROUND((+AL12*13.1*1000000)/2000,-3) -> 115000 | AQ12: =IF(G12="POET Biorefining",G12,IF(T12="FQPT HI Pro",T12,IF(Z12="ICM FOT",Z12,IF(Q12="ICM",Q12,IF(Q12="ADM",Q12,IF(Q12="Waste Stream",Q12,IF(Q12="Wheat","Wheat","None"))))))) -> Wheat | AR12: =VLOOKUP(AQ12,[1]Yield!$A$5:$B$15,2,FALSE) -> 0.2 | AS12: =(AL12)*AR12 -> 3.5185185 | AT12: Likely | AY12: =IFERROR(VLOOKUP(AX12,[1]Sheet3!$H$3:$I$5,2,FALSE),0) -> 0 | AZ12: =AJ12 -> 50 | BA12: =+AJ12*6.85*0.48/2 -> 82.2 | BB12: =SUMIFS('[1]Corn 2023'!V:V,'[1]Corn 2023'!B:B,"=2023",'[1]Corn 2023'!L:L,"="&'Corn Processors'!L12) -> 0 | BD12: https://amberwaveusa.com/ | BE12: UP | BF12: No | BK12: =IF(M12=2,10,5)+IF(Q12="ICM",10,5)+IF(X12="Y",10,5) -> 20
A13: 12 | D13: 3142 | E13: 3557 | F13: =IF(A13<300,"Active","Retired") -> Active | G13: ADM | H13: =VLOOKUP(E13,'[1]EPA Ethanol Capacity 2024'!$B$5:$C$235,2,FALSE) -> VCP Corn Processing | I13: IA | J13: Cedar Rapids | K13: 52404 | L13: Linn | M13: 2 | N13: 41.929 | O13: -91.6885 | P13: 2008 | Q13: ADM | R13: =COUNTIF(G:G,"="&G13) -> 8 | U13: CHP | AB13: Corn | AC13: D6 | AD13: Website | AE13: =IF(BK13=1,"Low","High") -> High | AG13: 332.3 | AH13: 04-A-314 | AJ13: =VLOOKUP(E13,'[1]Ethanol Plant Listing 2025'!$B$3:$E$220,4,FALSE) -> 300 | AK13: =+AJ13*[1]Yield!$K$4 -> 285 | AL13: =AK13/VLOOKUP(Q13,[1]Yield!$E$5:$F$14,2,FALSE) -> 98.958333 | AO13: =ROUND((+AL13*13.1*1000000)/2000,-3) -> 648000 | AP13: Rotary Dryer | AQ13: =IF(G13="POET Biorefining",G13,IF(T13="FQPT HI Pro",T13,IF(Z13="ICM FOT",Z13,IF(Q13="ICM",Q13,IF(Q13="ADM",Q13,"None"))))) -> ADM | AR13: =VLOOKUP(AQ13,[1]Yield!$A$5:$B$10,2,FALSE) -> 0.8 | AS13: =(AL13)*AR13 -> 79.166667 | AT13: Y | AY13: =IFERROR(VLOOKUP(AX13,[1]Sheet3!$H$3:$I$5,2,FALSE),0) -> 0 | AZ13: =AJ13 -> 300 | BA13: =+AJ13*6.85*0.48/2 -> 493.2 | BB13: =SUMIFS('[1]Corn 2023'!V:V,'[1]Corn 2023'!B:B,"=2023",'[1]Corn 2023'!L:L,"="&'Corn Processors'!L13) -> 147000 | BC13: Y | BD13: https://www.adm.com/ | BE13: UP | BF13: Yes | BK13: =IF(M13=2,10,5)+IF(Q13="ICM",10,5)+IF(X13="Y",10,5) -> 20
A14: 13 | D14: 3143 | E14: 3558 | F14: =IF(A14<300,"Active","Retired") -> Active | G14: ADM | H14: =VLOOKUP(E14,'[1]EPA Ethanol Capacity 2024'!$B$5:$C$235,2,FALSE) -> ADM Cedar Rapids IA Wet Mill | I14: IA | J14: Cedar Rapids | K14: 52404 | L14: Linn | M14: 2 | N14: 41.9156 | O14: -91.6888 | P14: 0 | Q14: Wet Mill | R14: =COUNTIF(G:G,"="&G14) -> 8 | U14: CHP | AB14: Corn | AC14: D6 | AD14: Website | AE14: =IF(BK14=1,"Low","High") -> High | AF14: 752.325 | AG14: 752.325 | AH14: 07-A-570 | AJ14: =VLOOKUP(E14,'[1]Ethanol Plant Listing 2025'!$B$3:$E$220,4,FALSE) -> 240 | AK14: =+AJ14*[1]Yield!$K$4 -> 228 | AL14: =AK14/VLOOKUP(Q14,[1]Yield!$E$5:$F$14,2,FALSE) -> 82.909091 | AO14: =ROUND((+AL14*13.1*1000000)/2000,-3) -> 543000 | AP14: Rotary Dryer | AQ14: =IF(G14="POET Biorefining",G14,IF(T14="FQPT HI Pro",T14,IF(Z14="ICM FOT",Z14,IF(Q14="ICM",Q14,IF(Q14="ADM",Q14,"None"))))) -> None | AR14: =VLOOKUP(AQ14,[1]Yield!$A$5:$B$10,2,FALSE) -> 0.815 | AS14: =(AL14)*AR14 -> 67.570909 | AT14: Y | AY14: =IFERROR(VLOOKUP(AX14,[1]Sheet3!$H$3:$I$5,2,FALSE),0) -> 0 | AZ14: =AJ14 -> 240 | BA14: =+AJ14*6.85*0.48/2 -> 394.56 | BB14: =SUMIFS('[1]Corn 2023'!V:V,'[1]Corn 2023'!B:B,"=2023",'[1]Corn 2023'!L:L,"="&'Corn Processors'!L14) -> 147000 | BC14: Y | BD14: https://www.adm.com/ | BE14: UP | BF14: Yes | BK14: =IF(M14=2,10,5)+IF(Q14="ICM",10,5)+IF(X14="Y",10,5) -> 20
A15: 14 | D15: 3144 | E15: 3559 | F15: =IF(A15<300,"Active","Retired") -> Active | G15: ADM | H15: =VLOOKUP(E15,'[1]EPA Ethanol Capacity 2024'!$B$5:$C$235,2,FALSE) -> ADM Clinton IA | I15: IA | J15: Clinton | K15: 52732 | L15: Clinton | M15: 2 | N15: 41.8173 | O15: -90.2162 | P15: 2008 | Q15: ADM | R15: =COUNTIF(G:G,"="&G15) -> 8 | U15: CHP | AB15: Corn | AC15: D6 | AD15: Website | AE15: =IF(BK15=1,"Low","High") -> High | AF15: 237.3 | AG15: 237.3 | AH15: 05-A-509 | AJ15: =VLOOKUP(E15,'[1]Ethanol Plant Listing 2025'!$B$3:$E$220,4,FALSE) -> 237 | AK15: =+AJ15*[1]Yield!$K$4 -> 225.15 | AL15: =AK15/VLOOKUP(Q15,[1]Yield!$E$5:$F$14,2,FALSE) -> 78.177083 | AO15: =ROUND((+AL15*13.1*1000000)/2000,-3) -> 512000 | AP15: Rotary Dryer | AQ15: =IF(G15="POET Biorefining",G15,IF(T15="FQPT HI Pro",T15,IF(Z15="ICM FOT",Z15,IF(Q15="ICM",Q15,IF(Q15="ADM",Q15,"None"))))) -> ADM | AR15: =VLOOKUP(AQ15,[1]Yield!$A$5:$B$10,2,FALSE) -> 0.8 | AS15: =(AL15)*AR15 -> 62.541667 | AT15: Y | AY15: =IFERROR(VLOOKUP(AX15,[1]Sheet3!$H$3:$I$5,2,FALSE),0) -> 0 | AZ15: =AJ15 -> 237 | BA15: =+AJ15*6.85*0.48/2 -> 389.628 | BB15: =SUMIFS('[1]Corn 2023'!V:V,'[1]Corn 2023'!B:B,"=2023",'[1]Corn 2023'!L:L,"="&'Corn Processors'!L15) -> 187500 | BC15: Y | BD15: https://www.adm.com/ | BE15: UP/CP | BF15: Yes | BK15: =IF(M15=2,10,5)+IF(Q15="ICM",10,5)+IF(X15="Y",10,5) -> 20
A16: 15 | D16: 3145 | E16: 3560 | F16: =IF(A16<300,"Active","Retired") -> Active | G16: ADM | H16: =VLOOKUP(E16,'[1]EPA Ethanol Capacity 2024'!$B$5:$C$235,2,FALSE) -> VCP Corn Processing | I16: NE | J16: Columbus | K16: 68601 | L16: Platte | M16: 2 | N16: 41.419 | O16: -97.2896 | P16: 2008 | Q16: ADM | R16: =COUNTIF(G:G,"="&G16) -> 8 | U16: CHP | AB16: Corn | AC16: D6 | AD16: Website | AE16: =IF(BK16=1,"Low","High") -> High | AI16: 39285 | AJ16: =VLOOKUP(E16,'[1]Ethanol Plant Listing 2025'!$B$3:$E$220,4,FALSE) -> 313 | AK16: =+AJ16*[1]Yield!$K$4 -> 297.35 | AL16: =AK16/VLOOKUP(Q16,[1]Yield!$E$5:$F$14,2,FALSE) -> 103.24653 | AO16: =ROUND((+AL16*13.1*1000000)/2000,-3) -> 676000 | AP16: Rotary Dryer | AQ16: =IF(G16="POET Biorefining",G16,IF(T16="FQPT HI Pro",T16,IF(Z16="ICM FOT",Z16,IF(Q16="ICM",Q16,IF(Q16="ADM",Q16,"None"))))) -> ADM | AR16: =VLOOKUP(AQ16,[1]Yield!$A$5:$B$10,2,FALSE) -> 0.8 | AS16: =(AL16)*AR16 -> 82.597222 | AT16: Y | AV16: Tall Grass | AX16: =IFERROR(VLOOKUP(E16,[1]Sheet3!$C$2:$E$68,2,FALSE),"None") -> Tall Grass | AY16: =IFERROR(VLOOKUP(AX16,[1]Sheet3!$H$3:$I$5,2,FALSE),0) -> 30 | AZ16: =AJ16 -> 313 | BA16: =+AJ16*6.85*0.48/2 -> 514.572 | BB16: =SUMIFS('[1]Corn 2023'!V:V,'[1]Corn 2023'!B:B,"=2023",'[1]Corn 2023'!L:L,"="&'Corn Processors'!L16) -> 0 | BC16: Y | BD16: https://www.adm.com/ | BE16: UP/BNSF | BF16: Yes | BI16: Impoter | BK16: =IF(M16=2,10,5)+IF(Q16="ICM",10,5)+IF(X16="Y",10,5) -> 20
A17: 16 | D17: 3146 | E17: 3561 | F17: =IF(A17<300,"Active","Retired") -> Active | G17: ADM | H17: =VLOOKUP(E17,'[1]EPA Ethanol Capacity 2024'!$B$5:$C$235,2,FALSE) -> ADM Columbus Wet Mill | I17: NE | J17: Columbus | K17: 68601 | L17: Platte | M17: 2 | N17: 41.4153 | O17: -97.2869 | P17: 1992 | Q17: Wet Mill | R17: =COUNTIF(G:G,"="&G17) -> 8 | U17: CHP | AB17: Corn | AC17: D6 | AD17: Website | AE17: =IF(BK17=1,"Low","High") -> High | AI17: 39285 | AJ17: =VLOOKUP(E17,'[1]Ethanol Plant Listing 2025'!$B$3:$E$220,4,FALSE) -> 100 | AK17: =+AJ17*[1]Yield!$K$4 -> 95 | AL17: =AK17/VLOOKUP(Q17,[1]Yield!$E$5:$F$14,2,FALSE) -> 34.545455 | AO17: =ROUND((+AL17*13.1*1000000)/2000,-3) -> 226000 | AP17: Rotary Dryer | AQ17: =IF(G17="POET Biorefining",G17,IF(T17="FQPT HI Pro",T17,IF(Z17="ICM FOT",Z17,IF(Q17="ICM",Q17,IF(Q17="ADM",Q17,"None"))))) -> None | AR17: =VLOOKUP(AQ17,[1]Yield!$A$5:$B$10,2,FALSE) -> 0.815 | AS17: =(AL17)*AR17 -> 28.154545 | AT17: Y | AV17: Tall Grass | AX17: =IFERROR(VLOOKUP(E17,[1]Sheet3!$C$2:$E$68,2,FALSE),"None") -> Tall Grass | AY17: =IFERROR(VLOOKUP(AX17,[1]Sheet3!$H$3:$I$5,2,FALSE),0) -> 30 | AZ17: =AJ17 -> 100 | BA17: =+AJ17*6.85*0.48/2 -> 164.4 | BB17: =SUMIFS('[1]Corn 2023'!V:V,'[1]Corn 2023'!B:B,"=2023",'[1]Corn 2023'!L:L,"="&'Corn Processors'!L17) -> 0 | BC17: Y | BD17: https://www.adm.com/ | BE17: UP/BNSF | BF17: Yes | BI17: Importer | BK17: =IF(M17=2,10,5)+IF(Q17="ICM",10,5)+IF(X17="Y",10,5) -> 20
A18: 17 | D18: 3147 | E18: 3562 | F18: =IF(A18<300,"Active","Retired") -> Active | G18: ADM | H18: =VLOOKUP(E18,'[1]EPA Ethanol Capacity 2024'!$B$5:$C$235,2,FALSE) -> ADM | I18: IL | J18: Decatur | K18: 62526 | L18: Macon | M18: 2 | N18: 39.8635 | O18: -88.8896 | P18: 0 | Q18: Wet Mill | R18: =COUNTIF(G:G,"="&G18) -> 8 | AB18: Corn | AC18: D6 | AD18: https://adm.gradable.com/market/ | AE18: =IF(BK18=1,"Low","High") -> High | AJ18: =VLOOKUP(E18,'[1]Ethanol Plant Listing 2025'!$B$3:$E$220,4,FALSE) -> 375 | AK18: =+AJ18*[1]Yield!$K$4 -> 356.25 | AL18: =AK18/VLOOKUP(Q18,[1]Yield!$E$5:$F$14,2,FALSE) -> 129.54545 | AO18: =ROUND((+AL18*13.1*1000000)/2000,-3) -> 849000 | AP18: Rotary Dryer | AQ18: =IF(G18="POET Biorefining",G18,IF(T18="FQPT HI Pro",T18,IF(Z18="ICM FOT",Z18,IF(Q18="ICM",Q18,IF(Q18="ADM",Q18,"None"))))) -> None | AR18: =VLOOKUP(AQ18,[1]Yield!$A$5:$B$10,2,FALSE) -> 0.815 | AS18: =(AL18)*AR18 -> 105.57955 | AT18: Y | AU18: Direct | AX18: =IFERROR(VLOOKUP(E18,[1]Sheet3!$C$2:$E$68,2,FALSE),"None") -> Direct Inject | AY18: =IFERROR(VLOOKUP(AX18,[1]Sheet3!$H$3:$I$5,2,FALSE),0) -> 32 | AZ18: =AJ18 -> 375 | BA18: =+AJ18*6.85*0.48/2 -> 616.5 | BB18: =SUMIFS('[1]Corn 2023'!V:V,'[1]Corn 2023'!B:B,"=2023",'[1]Corn 2023'!L:L,"="&'Corn Processors'!L18) -> 0 | BC18: Y | BD18: https://www.adm.com/ | BE18: NS/CN | BF18: Yes | BK18: =IF(M18=2,10,5)+IF(Q18="ICM",10,5)+IF(X18="Y",10,5) -> 20
A19: 18 | D19: 3148 | E19: 3563 | F19: =IF(A19<300,"Active","Retired") -> Active | G19: ADM | H19: =VLOOKUP(E19,'[1]EPA Ethanol Capacity 2024'!$B$5:$C$235,2,FALSE) -> ADM | I19: MN | J19: Marshall | K19: 56258 | L19: Lyon | M19: 2 | N19: 44.4748 | O19: -95.7796 | P19: 1988 | Q19: Wet Mill | R19: =COUNTIF(G:G,"="&G19) -> 8 | AB19: Corn | AC19: D6 | AD19: Website | AE19: =IF(BK19=1,"Low","High") -> High | AJ19: =VLOOKUP(E19,'[1]Ethanol Plant Listing 2025'!$B$3:$E$220,4,FALSE) -> 48 | AK19: =+AJ19*[1]Yield!$K$4 -> 45.6 | AL19: =AK19/VLOOKUP(Q19,[1]Yield!$E$5:$F$14,2,FALSE) -> 16.581818 | AO19: =ROUND((+AL19*13.1*1000000)/2000,-3) -> 109000 | AP19: Rotary Dryer | AQ19: =IF(G19="POET Biorefining",G19,IF(T19="FQPT HI Pro",T19,IF(Z19="ICM FOT",Z19,IF(Q19="ICM",Q19,IF(Q19="ADM",Q19,"None"))))) -> None | AR19: =VLOOKUP(AQ19,[1]Yield!$A$5:$B$10,2,FALSE) -> 0.815 | AS19: =(AL19)*AR19 -> 13.514182 | AT19: Likely | AX19: =IFERROR(VLOOKUP(E19,[1]Sheet3!$C$2:$E$68,2,FALSE),"None") -> None | AY19: =IFERROR(VLOOKUP(AX19,[1]Sheet3!$H$3:$I$5,2,FALSE),0) -> 0 | AZ19: =AJ19 -> 48 | BA19: =+AJ19*6.85*0.48/2 -> 78.912 | BB19: =SUMIFS('[1]Corn 2023'!V:V,'[1]Corn 2023'!B:B,"=2023",'[1]Corn 2023'!L:L,"="&'Corn Processors'!L19) -> 185500 | BC19: Y | BD19: https://www.adm.com/ | BE19: BNSF | BF19: Yes | BK19: =IF(M19=2,10,5)+IF(Q19="ICM",10,5)+IF(X19="Y",10,5) -> 20
A20: 19 | B20: 5715 | C20: 70247 | D20: 3149 | E20: 3564 | F20: =IF(A20<300,"Active","Retired") -> Active | G20: Conestoga Energy | H20: =VLOOKUP(E20,'[1]EPA Ethanol Capacity 2024'!$B$5:$C$235,2,FALSE) -> Arkalon Ethanol LLC | I20: KS | J20: Liberal | K20: 67901 | L20: Seward | M20: 2 | N20: 37.107107 | O20: -101.03083 | P20: 2007 | Q20: ICM | R20: =COUNTIF(G:G,"="&G20) -> 3 | U20: CHP | V20: 3 mw inefficient | AB20: Corn/Milo | AC20: D6 | AD20: Website | AE20: =IF(BK20=1,"Low","High") -> High | AJ20: =VLOOKUP(E20,'[1]Ethanol Plant Listing 2025'!$B$3:$E$220,4,FALSE) -> 121 | AK20: =+AJ20*[1]Yield!$K$4 -> 114.95 | AL20: =AK20/VLOOKUP(Q20,[1]Yield!$E$5:$F$14,2,FALSE) -> 38.966102 | AO20: =ROUND((+AL20*13.1*1000000)/2000,-3) -> 255000 | AP20: Rotary Dryer | AQ20: =IF(G20="POET Biorefining",G20,IF(T20="FQPT HI Pro",T20,IF(Z20="ICM FOT",Z20,IF(Q20="ICM",Q20,IF(Q20="ADM",Q20,"None"))))) -> ICM | AR20: =VLOOKUP(AQ20,[1]Yield!$A$5:$B$10,2,FALSE) -> 0.9 | AS20: =(AL20)*AR20 -> 35.069492 | AT20: Likely | AX20: =IFERROR(VLOOKUP(E20,[1]Sheet3!$C$2:$E$68,2,FALSE),"None") -> None | AY20: =IFERROR(VLOOKUP(AX20,[1]Sheet3!$H$3:$I$5,2,FALSE),0) -> 0 | AZ20: =AJ20 -> 121 | BA20: =+AJ20*6.85*0.48/2 -> 198.924 | BB20: =SUMIFS('[1]Corn 2023'!V:V,'[1]Corn 2023'!B:B,"=2023",'[1]Corn 2023'!L:L,"="&'Corn Processors'!L20) -> 0 | BD20: https://www.conestogaenergy.com/ | BE20: UP | BF20: Yes | BJ20: Member | BK20: =IF(M20=2,10,5)+IF(Q20="ICM",10,5)+IF(X20="Y",10,5) -> 25
A21: 20 | B21: 4469 | C21: 70130 | D21: 2861 | E21: 3567 | F21: =IF(A21<300,"Active","Retired") -> Active | G21: Badger State Ethanol | H21: =VLOOKUP(E21,'[1]EPA Ethanol Capacity 2024'!$B$5:$C$235,2,FALSE) -> Badger State Ethanol LLC | I21: WI | J21: Monroe | K21: 53566 | L21: Green | M21: 2 | N21: 42.5949 | O21: -89.66691 | P21: 2002 | Q21: ICM | R21: =COUNTIF(G:G,"="&G21) -> 1 | S21: EP3 | T21: FQPT HI PRO | Z21: =+T21 -> FQPT HI PRO | AB21: Corn | AC21: D6 | AD21: Website | AE21: =IF(BK21=1,"Low","High") -> High | AJ21: =VLOOKUP(E21,'[1]Ethanol Plant Listing 2025'!$B$3:$E$220,4,FALSE) -> 97 | AK21: =+AJ21*[1]Yield!$K$4 -> 92.15 | AL21: =AK21/VLOOKUP(Q21,[1]Yield!$E$5:$F$14,2,FALSE) -> 31.237288 | AO21: =ROUND((+AL21*13.1*1000000)/2000,-3) -> 205000 | AP21: Rotary Dryer | AQ21: =IF(G21="POET Biorefining",G21,IF(T21="FQPT HI Pro",T21,IF(Z21="ICM FOT",Z21,IF(Q21="ICM",Q21,IF(Q21="ADM",Q21,"None"))))) -> FQPT HI PRO | AR21: =VLOOKUP(AQ21,[1]Yield!$A$5:$B$10,2,FALSE) -> 1.05 | AS21: =(AL21)*AR21 -> 32.799153 | AT21: Likely | AX21: =IFERROR(VLOOKUP(E21,[1]Sheet3!$C$2:$E$68,2,FALSE),"None") -> None | AY21: =IFERROR(VLOOKUP(AX21,[1]Sheet3!$H$3:$I$5,2,FALSE),0) -> 0 | AZ21: =AJ21 -> 97 | BA21: =+AJ21*6.85*0.48/2 -> 159.468 | BB21: =SUMIFS('[1]Corn 2023'!V:V,'[1]Corn 2023'!B:B,"=2023",'[1]Corn 2023'!L:L,"="&'Corn Processors'!L21) -> 0 | BD21: https://badgerstateethanol.com/ | BE21: UP | BF21: Yes | BI21: Importer | BJ21: Member | BK21: =IF(M21=2,10,5)+IF(Q21="ICM",10,5)+IF(X21="Y",10,5) -> 25
A22: 21 | D22: 2862 | E22: 3568 | F22: =IF(A22<300,"Active","Retired") -> Active | G22: Big River Resources | H22: =VLOOKUP(E22,'[1]EPA Ethanol Capacity 2024'!$B$5:$C$235,2,FALSE) -> Big River Resources Boyceville LLC | I22: WI | J22: Boyceville | K22: 54725 | L22: Dunn | M22: 2 | N22: 45.050596 | O22: -91.980063 | P22: 2006 | Q22: ICM | R22: =COUNTIF(G:G,"="&G22) -> 4 | AB22: Corn | AC22: D6 | AD22: Website | AE22: =IF(BK22=1,"Low","High") -> High | AJ22: =VLOOKUP(E22,'[1]Ethanol Plant Listing 2025'!$B$3:$E$220,4,FALSE) -> 70 | AK22: =+AJ22*[1]Yield!$K$4 -> 66.5 | AL22: =AK22/VLOOKUP(Q22,[1]Yield!$E$5:$F$14,2,FALSE) -> 22.542373 | AO22: =ROUND((+AL22*13.1*1000000)/2000,-3) -> 148000 | AP22: Rotary Dryer | AQ22: =IF(G22="POET Biorefining",G22,IF(T22="FQPT HI Pro",T22,IF(Z22="ICM FOT",Z22,IF(Q22="ICM",Q22,IF(Q22="ADM",Q22,"None"))))) -> ICM | AR22: =VLOOKUP(AQ22,[1]Yield!$A$5:$B$10,2,FALSE) -> 0.9 | AS22: =(AL22)*AR22 -> 20.288136 | AT22: Unlikely | AX22: =IFERROR(VLOOKUP(E22,[1]Sheet3!$C$2:$E$68,2,FALSE),"None") -> None | AY22: =IFERROR(VLOOKUP(AX22,[1]Sheet3!$H$3:$I$5,2,FALSE),0) -> 0 | AZ22: =AJ22 -> 70 | BA22: =+AJ22*6.85*0.48/2 -> 115.08 | BB22: =SUMIFS('[1]Corn 2023'!V:V,'[1]Corn 2023'!K:K,"="&'Corn Processors'!J22,'[1]Corn 2023'!B:B,"=2023") -> 0 | BD22: https://www.bigriverresources.com/ | BE22: CN | BF22: Yes | BI22: Importer | BJ22: Member | BK22: =IF(M22=2,10,5)+IF(Q22="ICM",10,5)+IF(X22="Y",10,5) -> 25
A23: 22 | D23: 2863 | E23: 3569 | F23: =IF(A23<300,"Active","Retired") -> Active | G23: Big River Resources | H23: =VLOOKUP(E23,'[1]EPA Ethanol Capacity 2024'!$B$5:$C$235,2,FALSE) -> Big River Resources Galva LLC | I23: IL | J23: Galva | K23: 61434 | L23: Henry | M23: 2 | N23: 41.169691 | O23: -90.024473 | P23: 2009 | Q23: ICM | R23: =COUNTIF(G:G,"="&G23) -> 4 | S23: EP3 | AB23: Corn | AC23: D6 | AD23: https://www.rivervalleycoop.com/products-services/grain#grain-bids | AE23: =IF(BK23=1,"Low","High") -> High | AJ23: =VLOOKUP(E23,'[1]Ethanol Plant Listing 2025'!$B$3:$E$220,4,FALSE) -> 140 | AK23: =+AJ23*[1]Yield!$K$4 -> 133 | AL23: =AK23/VLOOKUP(Q23,[1]Yield!$E$5:$F$14,2,FALSE) -> 45.084746 | AO23: =ROUND((+AL23*13.1*1000000)/2000,-3) -> 295000 | AP23: Rotary Dryer | AQ23: =IF(G23="POET Biorefining",G23,IF(T23="FQPT HI Pro",T23,IF(Z23="ICM FOT",Z23,IF(Q23="ICM",Q23,IF(Q23="ADM",Q23,"None"))))) -> ICM | AR23: =VLOOKUP(AQ23,[1]Yield!$A$5:$B$10,2,FALSE) -> 0.9 | AS23: =(AL23)*AR23 -> 40.576271 | AT23: Y | AU23: Direct | AX23: Direct Inject | AY23: =IFERROR(VLOOKUP(AX23,[1]Sheet3!$H$3:$I$5,2,FALSE),0) -> 32 | AZ23: =AJ23 -> 140 | BA23: =+AJ23*6.85*0.48/2 -> 230.16 | BB23: =SUMIFS('[1]Corn 2023'!V:V,'[1]Corn 2023'!K:K,"="&'Corn Processors'!J23,'[1]Corn 2023'!B:B,"=2023") -> 0 | BD23: https://www.bigriverresources.com/ | BE23: BNSF | BF23: Yes | BJ23: Member | BK23: =IF(M23=2,10,5)+IF(Q23="ICM",10,5)+IF(X23="Y",10,5) -> 25
A24: 23 | D24: 2864 | E24: 3570 | F24: =IF(A24<300,"Active","Retired") -> Active | G24: Big River Resources | H24: =VLOOKUP(E24,'[1]EPA Ethanol Capacity 2024'!$B$5:$C$235,2,FALSE) -> Big River Resources West Burlington LLC | I24: IA | J24: West Burlington | K24: 52655 | L24: Des Moines | M24: 2 | N24: 40.831196 | O24: -91.220611 | P24: 2008 | Q24: ICM | R24: =COUNTIF(G:G,"="&G24) -> 4 | AB24: Corn | AC24: D6 | AD24: Website | AE24: =IF(BK24=1,"Low","High") -> High | AF24: 130 | AG24: 130 | AH24: 06-A-631 | AJ24: =VLOOKUP(E24,'[1]Ethanol Plant Listing 2025'!$B$3:$E$220,4,FALSE) -> 130 | AK24: =+AJ24*[1]Yield!$K$4 -> 123.5 | AL24: =AK24/VLOOKUP(Q24,[1]Yield!$E$5:$F$14,2,FALSE) -> 41.864407 | AO24: =ROUND((+AL24*13.1*1000000)/2000,-3) -> 274000 | AP24: Rotary Dryer | AQ24: =IF(G24="POET Biorefining",G24,IF(T24="FQPT HI Pro",T24,IF(Z24="ICM FOT",Z24,IF(Q24="ICM",Q24,IF(Q24="ADM",Q24,"None"))))) -> ICM | AR24: =VLOOKUP(AQ24,[1]Yield!$A$5:$B$10,2,FALSE) -> 0.9 | AS24: =(AL24)*AR24 -> 37.677966 | AT24: Y | AX24: =IFERROR(VLOOKUP(E24,[1]Sheet3!$C$2:$E$68,2,FALSE),"None") -> None | AY24: =IFERROR(VLOOKUP(AX24,[1]Sheet3!$H$3:$I$5,2,FALSE),0) -> 0 | AZ24: =AJ24 -> 130 | BA24: =+AJ24*6.85*0.48/2 -> 213.72 | BB24: =SUMIFS('[1]Corn 2023'!V:V,'[1]Corn 2023'!B:B,"=2023",'[1]Corn 2023'!L:L,"="&'Corn Processors'!L24) -> 74200 | BD24: https://www.bigriverresources.com/ | BE24: BNSF | BF24: Yes | BI24: Importer | BJ24: Member | BK24: =IF(M24=2,10,5)+IF(Q24="ICM",10,5)+IF(X24="Y",10,5) -> 25
A25: 24 | D25: 3153 | E25: 3571 | F25: =IF(A25<300,"Active","Retired") -> Active | G25: Big River Resources | H25: =VLOOKUP(E25,'[1]EPA Ethanol Capacity 2024'!$B$5:$C$235,2,FALSE) -> Big River United Energy LLC | I25: IA | J25: Dyersville | K25: 52040 | L25: Dubuque | M25: 2 | N25: 42.4872 | O25: -91.1633 | P25: 2009 | Q25: ICM | R25: =COUNTIF(G:G,"="&G25) -> 4 | S25: EP3 | AB25: Corn | AC25: D6 | AD25: Website | AE25: =IF(BK25=1,"Low","High") -> High | AF25: 140 | AG25: 120 | AH25: 06-A-725 | AJ25: =VLOOKUP(E25,'[1]Ethanol Plant Listing 2025'!$B$3:$E$220,4,FALSE) -> 140 | AK25: =+AJ25*[1]Yield!$K$4 -> 133 | AL25: =AK25/VLOOKUP(Q25,[1]Yield!$E$5:$F$14,2,FALSE) -> 45.084746 | AO25: =ROUND((+AL25*13.1*1000000)/2000,-3) -> 295000 | AP25: Rotary Dryer | AQ25: =IF(G25="POET Biorefining",G25,IF(T25="FQPT HI Pro",T25,IF(Z25="ICM FOT",Z25,IF(Q25="ICM",Q25,IF(Q25="ADM",Q25,"None"))))) -> ICM | AR25: =VLOOKUP(AQ25,[1]Yield!$A$5:$B$10,2,FALSE) -> 0.9 | AS25: =(AL25)*AR25 -> 40.576271 | AT25: Y | AX25: =IFERROR(VLOOKUP(E25,[1]Sheet3!$C$2:$E$68,2,FALSE),"None") -> None | AY25: =IFERROR(VLOOKUP(AX25,[1]Sheet3!$H$3:$I$5,2,FALSE),0) -> 0 | AZ25: =AJ25 -> 140 | BA25: =+AJ25*6.85*0.48/2 -> 230.16 | BB25: =SUMIFS('[1]Corn 2023'!V:V,'[1]Corn 2023'!B:B,"=2023",'[1]Corn 2023'!L:L,"="&'Corn Processors'!L25) -> 148500 | BD25: https://www.bigriverresources.com/ | BE25: CN | BF25: Yes | BI25: Importer | BJ25: Member | BK25: =IF(M25=2,10,5)+IF(Q25="ICM",10,5)+IF(X25="Y",10,5) -> 25 | BL25: 3/17/09 AgStar Financial purcahses US BioEnergy assets out of bancruptcy for $??M
A26: 25 | D26: 3154 | E26: 3572 | F26: =IF(A26<300,"Active","Retired") -> Active | G26: BioUrja | H26: =VLOOKUP(E26,'[1]EPA Ethanol Capacity 2024'!$B$5:$C$235,2,FALSE) -> Biourja Renewables LLC | I26: IL | J26: Peoria | K26: 61602 | L26: Peoria | M26: 2 | N26: 40.6776 | O26: -89.6069 | P26: 1982 | Q26: ADM | R26: =COUNTIF(G:G,"="&G26) -> 1 | AB26: Corn | AC26: D6 | AD26: https://www.rivervalleycoop.com/products-services/grain#grain-bids | AE26: =IF(BK26=1,"Low","High") -> High | AJ26: =VLOOKUP(E26,'[1]Ethanol Plant Listing 2025'!$B$3:$E$220,4,FALSE) -> 61 | AK26: =+AJ26*[1]Yield!$K$4 -> 57.95 | AL26: =AK26/VLOOKUP(Q26,[1]Yield!$E$5:$F$14,2,FALSE) -> 20.121528 | AO26: =ROUND((+AL26*13.1*1000000)/2000,-3) -> 132000 | AP26: Rotary Dryer | AQ26: =IF(G26="POET Biorefining",G26,IF(T26="FQPT HI Pro",T26,IF(Z26="ICM FOT",Z26,IF(Q26="ICM",Q26,IF(Q26="ADM",Q26,"None"))))) -> ADM | AR26: =VLOOKUP(AQ26,[1]Yield!$A$5:$B$10,2,FALSE) -> 0.8 | AS26: =(AL26)*AR26 -> 16.097222 | AT26: Likely | AX26: =IFERROR(VLOOKUP(E26,[1]Sheet3!$C$2:$E$68,2,FALSE),"None") -> None | AY26: =IFERROR(VLOOKUP(AX26,[1]Sheet3!$H$3:$I$5,2,FALSE),0) -> 0 | AZ26: =AJ26 -> 61 | BA26: =+AJ26*6.85*0.48/2 -> 100.284 | BB26: =SUMIFS('[1]Corn 2023'!V:V,'[1]Corn 2023'!K:K,"="&'Corn Processors'!J26,'[1]Corn 2023'!B:B,"=2023") -> 0 | BD26: https://www.biourja.com/ | BE26: UP | BF26: Yes | BK26: =IF(M26=2,10,5)+IF(Q26="ICM",10,5)+IF(X26="Y",10,5) -> 20 | BL26: 10/21/21 BioUrja purcahses from ADM
A27: 26 | D27: 3155 | E27: 3573 | F27: =IF(A27<300,"Active","Retired") -> Active | G27: Harvestone | H27: =VLOOKUP(E27,'[1]EPA Ethanol Capacity 2024'!$B$5:$C$235,2,FALSE) -> Blue Flint Ethanol LLC | I27: ND | J27: Underwood | K27: 58576 | L27: McLean | M27: 2 | N27: 47.377226 | O27: -101.1523 | P27: 2007 | Q27: ICM | R27: =COUNTIF(G:G,"="&G27) -> 3 | U27: CHP | AB27: Corn | AC27: D6 | AD27: Website | AE27: =IF(BK27=1,"Low","High") -> High | AJ27: =VLOOKUP(E27,'[1]Ethanol Plant Listing 2025'!$B$3:$E$220,4,FALSE) -> 75.7 | AK27: =+AJ27*[1]Yield!$K$4 -> 71.915 | AL27: =AK27/VLOOKUP(Q27,[1]Yield!$E$5:$F$14,2,FALSE) -> 24.377966 | AO27: =ROUND((+AL27*13.1*1000000)/2000,-3) -> 160000 | AP27: Rotary Dryer | AQ27: =IF(G27="POET Biorefining",G27,IF(T27="FQPT HI Pro",T27,IF(Z27="ICM FOT",Z27,IF(Q27="ICM",Q27,IF(Q27="ADM",Q27,"None"))))) -> ICM | AR27: =VLOOKUP(AQ27,[1]Yield!$A$5:$B$10,2,FALSE) -> 0.9 | AS27: =(AL27)*AR27 -> 21.940169 | AT27: Likely | AU27: Direct | AX27: =IFERROR(VLOOKUP(E27,[1]Sheet3!$C$2:$E$68,2,FALSE),"None") -> Direct Inject | AY27: =IFERROR(VLOOKUP(AX27,[1]Sheet3!$H$3:$I$5,2,FALSE),0) -> 32 | AZ27: =AJ27 -> 75.7 | BA27: =+AJ27*6.85*0.48/2 -> 124.4508 | BB27: =SUMIFS('[1]Corn 2023'!V:V,'[1]Corn 2023'!K:K,"="&'Corn Processors'!J27,'[1]Corn 2023'!B:B,"=2023") -> 0 | BD27: https://www.midwestagenergy.com/fccp-blue-flint-19634 | BE27: UP | BF27: Yes | BK27: =IF(M27=2,10,5)+IF(Q27="ICM",10,5)+IF(X27="Y",10,5) -> 25
A28: 27 | B28: 4054 | C28: 70117 | D28: 3156 | E28: 3574 | F28: =IF(A28<300,"Active","Retired") -> Active | G28: Conestoga Energy | H28: =VLOOKUP(E28,'[1]EPA Ethanol Capacity 2024'!$B$5:$C$235,2,FALSE) -> Bonanza Bioenergy LLC | I28: KS | J28: Garden City | K28: 33923 | L28: #N/A | M28: 2 | N28: 37.959051 | O28: -100.83913 | P28: 2007 | Q28: ICM | R28: =COUNTIF(G:G,"="&G28) -> 3 | U28: CHP | AB28: Corn/Milo | AC28: D6 | AD28: Website | AE28: =IF(BK28=1,"Low","High") -> High | AJ28: =VLOOKUP(E28,'[1]Ethanol Plant Listing 2025'!$B$3:$E$220,4,FALSE) -> 73.5 | AK28: =+AJ28*[1]Yield!$K$4 -> 69.825 | AL28: =AK28/VLOOKUP(Q28,[1]Yield!$E$5:$F$14,2,FALSE) -> 23.669492 | AO28: =ROUND((+AL28*13.1*1000000)/2000,-3) -> 155000 | AP28: Rotary Dryer | AQ28: =IF(G28="POET Biorefining",G28,IF(T28="FQPT HI Pro",T28,IF(Z28="ICM FOT",Z28,IF(Q28="ICM",Q28,IF(Q28="ADM",Q28,"None"))))) -> ICM | AR28: =VLOOKUP(AQ28,[1]Yield!$A$5:$B$10,2,FALSE) -> 0.9 | AS28: =(AL28)*AR28 -> 21.302542 | AT28: Likely | AU28: Direct | AX28: =IFERROR(VLOOKUP(E28,[1]Sheet3!$C$2:$E$68,2,FALSE),"None") -> Direct Inject | AY28: =IFERROR(VLOOKUP(AX28,[1]Sheet3!$H$3:$I$5,2,FALSE),0) -> 32 | AZ28: =AJ28 -> 73.5 | BA28: =+AJ28*6.85*0.48/2 -> 120.834 | BB28: =SUMIFS('[1]Corn 2023'!V:V,'[1]Corn 2023'!K:K,"="&'Corn Processors'!J28,'[1]Corn 2023'!B:B,"=2023") -> 0 | BD28: https://www.conestogaenergy.com/ | BE28: BNSF | BF28: Yes | BK28: =IF(M28=2,10,5)+IF(Q28="ICM",10,5)+IF(X28="Y",10,5) -> 25
A29: 28 | B29: 5934 | C29: 70217 | D29: 3157 | E29: 3575 | F29: =IF(A29<300,"Active","Retired") -> Active | G29: Bridgeport Ethanol | H29: =VLOOKUP(E29,'[1]EPA Ethanol Capacity 2024'!$B$5:$C$235,2,FALSE) -> Bridgeport Ethanol LLC | I29: NE | J29: Bridgeport | K29: 69336 | L29: Morrill | M29: 2 | N29: 41.6432 | O29: -103.07863 | P29: 2008 | Q29: ICM | R29: =COUNTIF(G:G,"="&G29) -> 1 | U29: CHP | AB29: Corn | AC29: D6 | AD29: Website | AE29: =IF(BK29=1,"Low","High") -> High | AF29: 60 | AG29: 50 | AH29: AIR>CONSTRUCTION | AI29: 87464 | AJ29: =VLOOKUP(E29,'[1]Ethanol Plant Listing 2025'!$B$3:$E$220,4,FALSE) -> 60 | AK29: =+AJ29*[1]Yield!$K$4 -> 57 | AL29: =AK29/VLOOKUP(Q29,[1]Yield!$E$5:$F$14,2,FALSE) -> 19.322034 | AO29: =ROUND((+AL29*13.1*1000000)/2000,-3) -> 127000 | AP29: Rotary Dryer | AQ29: =IF(G29="POET Biorefining",G29,IF(T29="FQPT HI Pro",T29,IF(Z29="ICM FOT",Z29,IF(Q29="ICM",Q29,IF(Q29="ADM",Q29,"None"))))) -> ICM | AR29: =VLOOKUP(AQ29,[1]Yield!$A$5:$B$10,2,FALSE) -> 0.9 | AS29: =(AL29)*AR29 -> 17.389831 | AT29: Y | AX29: =IFERROR(VLOOKUP(E29,[1]Sheet3!$C$2:$E$68,2,FALSE),"None") -> None | AY29: =IFERROR(VLOOKUP(AX29,[1]Sheet3!$H$3:$I$5,2,FALSE),0) -> 0 | AZ29: =AJ29 -> 60 | BA29: =+AJ29*6.85*0.48/2 -> 98.64 | BB29: =SUMIFS('[1]Corn 2023'!V:V,'[1]Corn 2023'!K:K,"="&'Corn Processors'!J29,'[1]Corn 2023'!B:B,"=2023") -> 0 | BD29: http://www.bridgeportethanol.com/index.cfm?show=10&mid=29 | BE29: BNSF | BF29: Yes | BK29: =IF(M29=2,10,5)+IF(Q29="ICM",10,5)+IF(X29="Y",10,5) -> 25
A30: 29 | B30: 4063 | C30: 70109 | D30: 3158 | E30: 3576 | F30: =IF(A30<300,"Active","Retired") -> Active | G30: Bushmills Ethanol Inc. | H30: =VLOOKUP(E30,'[1]EPA Ethanol Capacity 2024'!$B$5:$C$235,2,FALSE) -> Bushmills Ethanol Inc | I30: MN | J30: Atwater | K30: 56209 | L30: Kandiyohi | M30: 2 | N30: 45.07333 | O30: -94.755556 | P30: 2005 | Q30: ICM | R30: =COUNTIF(G:G,"="&G30) -> 1 | S30: EP3 | AB30: Corn | AC30: D6 | AD30: Website | AE30: =IF(BK30=1,"Low","High") -> High | AJ30: =VLOOKUP(E30,'[1]Ethanol Plant Listing 2025'!$B$3:$E$220,4,FALSE) -> 90 | AK30: =+AJ30*[1]Yield!$K$4 -> 85.5 | AL30: =AK30/VLOOKUP(Q30,[1]Yield!$E$5:$F$14,2,FALSE) -> 28.983051 | AO30: =ROUND((+AL30*13.1*1000000)/2000,-3) -> 190000 | AP30: Rotary Dryer | AQ30: =IF(G30="POET Biorefining",G30,IF(T30="FQPT HI Pro",T30,IF(Z30="ICM FOT",Z30,IF(Q30="ICM",Q30,IF(Q30="ADM",Q30,"None"))))) -> ICM | AR30: =VLOOKUP(AQ30,[1]Yield!$A$5:$B$10,2,FALSE) -> 0.9 | AS30: =(AL30)*AR30 -> 26.084746 | AT30: Y | AX30: =IFERROR(VLOOKUP(E30,[1]Sheet3!$C$2:$E$68,2,FALSE),"None") -> Summit Carbon Solutions | AY30: =IFERROR(VLOOKUP(AX30,[1]Sheet3!$H$3:$I$5,2,FALSE),0) -> 31 | AZ30: =AJ30 -> 90 | BA30: =+AJ30*6.85*0.48/2 -> 147.96 | BB30: =SUMIFS('[1]Corn 2023'!V:V,'[1]Corn 2023'!K:K,"="&'Corn Processors'!J30,'[1]Corn 2023'!B:B,"=2023") -> 0 | BD30: https://bushmillsethanol.com/ | BE30: BNSF | BF30: Yes | BK30: =IF(M30=2,10,5)+IF(Q30="ICM",10,5)+IF(X30="Y",10,5) -> 25
A31: 30 | B31: 7354 | C31: 70317 | D31: 3159 | E31: 3577 | F31: =IF(A31<300,"Active","Retired") -> Active | G31: Calgren Renewable Fuels | H31: =VLOOKUP(E31,'[1]EPA Ethanol Capacity 2024'!$B$5:$C$235,2,FALSE) -> Calgren Renewable Fuels LLC | I31: CA | J31: Pixley | K31: 93256 | L31: Tulare | M31: 5 | N31: 36.0019 | O31: -119.30233 | P31: 2009 | Q31: Lurgi | R31: =COUNTIF(G:G,"="&G31) -> 1 | U31: CHP | AB31: Corn | AC31: D6 | AD31: Website | AE31: =IF(BK31=1,"Low","High") -> High | AJ31: =VLOOKUP(E31,'[1]Ethanol Plant Listing 2025'!$B$3:$E$220,4,FALSE) -> 55 | AK31: =+AJ31*[1]Yield!$K$4 -> 52.25 | AL31: =AK31/VLOOKUP(Q31,[1]Yield!$E$5:$F$14,2,FALSE) -> 18.333333 | AO31: =ROUND((+AL31*13.1*1000000)/2000,-3) -> 120000 | AQ31: =IF(G31="POET Biorefining",G31,IF(T31="FQPT HI Pro",T31,IF(Z31="ICM FOT",Z31,IF(Q31="ICM",Q31,IF(Q31="ADM",Q31,"None"))))) -> None | AR31: =VLOOKUP(AQ31,[1]Yield!$A$5:$B$10,2,FALSE) -> 0.815 | AS31: =(AL31)*AR31 -> 14.941667 | AT31: Likely | AX31: =IFERROR(VLOOKUP(E31,[1]Sheet3!$C$2:$E$68,2,FALSE),"None") -> None | AY31: =IFERROR(VLOOKUP(AX31,[1]Sheet3!$H$3:$I$5,2,FALSE),0) -> 0 | AZ31: =AJ31 -> 55 | BA31: =+AJ31*6.85*0.48/2 -> 90.42 | BB31: =SUMIFS('[1]Corn 2023'!V:V,'[1]Corn 2023'!K:K,"="&'Corn Processors'!J31,'[1]Corn 2023'!B:B,"=2023") -> 0 | BD31: https://www.calgren.com/ | BE31: UP | BF31: No | BJ31: Member | BK31: =IF(M31=2,10,5)+IF(Q31="ICM",10,5)+IF(X31="Y",10,5) -> 15
A32: 31 | D32: 3160 | E32: 3578 | F32: =IF(A32<300,"Active","Retired") -> Active | G32: Carbon Green Bioenergy | H32: =VLOOKUP(E32,'[1]EPA Ethanol Capacity 2024'!$B$5:$C$235,2,FALSE) -> Carbon Green Bioenergy LLC | I32: MI | J32: Lake Odessa | K32: 48849 | L32: Ionia | M32: 2 | N32: 42.76601 | O32: -85.07428 | P32: 2006 | Q32: ICM | R32: =COUNTIF(G:G,"="&G32) -> 1 | S32: EP3 | AB32: Corn | AC32: D6 | AD32: Website | AE32: =IF(BK32=1,"Low","High") -> High | AJ32: =VLOOKUP(E32,'[1]Ethanol Plant Listing 2025'!$B$3:$E$220,4,FALSE) -> 59 | AK32: =+AJ32*[1]Yield!$K$4 -> 56.05 | AL32: =AK32/VLOOKUP(Q32,[1]Yield!$E$5:$F$14,2,FALSE) -> 19 | AO32: =ROUND((+AL32*13.1*1000000)/2000,-3) -> 124000 | AP32: Rotary Dryer | AQ32: =IF(G32="POET Biorefining",G32,IF(T32="FQPT HI Pro",T32,IF(Z32="ICM FOT",Z32,IF(Q32="ICM",Q32,IF(Q32="ADM",Q32,"None"))))) -> ICM | AR32: =VLOOKUP(AQ32,[1]Yield!$A$5:$B$10,2,FALSE) -> 0.9 | AS32: =(AL32)*AR32 -> 17.1 | AT32: Likely | AX32: =IFERROR(VLOOKUP(E32,[1]Sheet3!$C$2:$E$68,2,FALSE),"None") -> None | AY32: =IFERROR(VLOOKUP(AX32,[1]Sheet3!$H$3:$I$5,2,FALSE),0) -> 0 | AZ32: =AJ32 -> 59 | BA32: =+AJ32*6.85*0.48/2 -> 96.996 | BB32: =SUMIFS('[1]Corn 2023'!V:V,'[1]Corn 2023'!K:K,"="&'Corn Processors'!J32,'[1]Corn 2023'!B:B,"=2023") -> 0 | BD32: https://cgbioenergy.com/ | BE32: CSX | BF32: No | BK32: =IF(M32=2,10,5)+IF(Q32="ICM",10,5)+IF(X32="Y",10,5) -> 25
A33: 32 | D33: 3161 | E33: 3579 | F33: =IF(A33<300,"Active","Retired") -> Active | G33: Cardinal Ethanol | H33: =VLOOKUP(E33,'[1]EPA Ethanol Capacity 2024'!$B$5:$C$235,2,FALSE) -> Cardinal Ethanol LLC | I33: IN | J33: Union City | K33: 47390 | L33: Randolph | M33: 2 | N33: 40.18682 | O33: -84.86226 | P33: 2008 | Q33: ICM | R33: =COUNTIF(G:G,"="&G33) -> 2 | S33: EP3 | T33: ICM HI PRO | AB33: Corn | AC33: D6 | AD33: Website | AE33: =IF(BK33=1,"Low","High") -> High | AJ33: =VLOOKUP(E33,'[1]Ethanol Plant Listing 2025'!$B$3:$E$220,4,FALSE) -> 136 | AK33: =+AJ33*[1]Yield!$K$4 -> 129.2 | AL33: =AK33/VLOOKUP(Q33,[1]Yield!$E$5:$F$14,2,FALSE) -> 43.79661 | AO33: =ROUND((+AL33*13.1*1000000)/2000,-3) -> 287000 | AP33: Rotary Dryer | AQ33: =IF(G33="POET Biorefining",G33,IF(T33="FQPT HI Pro",T33,IF(Z33="ICM FOT",Z33,IF(Q33="ICM",Q33,IF(Q33="ADM",Q33,"None"))))) -> ICM | AR33: =VLOOKUP(AQ33,[1]Yield!$A$5:$B$10,2,FALSE) -> 0.9 | AS33: =(AL33)*AR33 -> 39.416949 | AT33: Likely | AX33: =IFERROR(VLOOKUP(E33,[1]Sheet3!$C$2:$E$68,2,FALSE),"None") -> None | AY33: =IFERROR(VLOOKUP(AX33,[1]Sheet3!$H$3:$I$5,2,FALSE),0) -> 0 | AZ33: =AJ33 -> 136 | BA33: =+AJ33*6.85*0.48/2 -> 223.584 | BB33: =SUMIFS('[1]Corn 2023'!V:V,'[1]Corn 2023'!K:K,"="&'Corn Processors'!J33,'[1]Corn 2023'!B:B,"=2023") -> 0 | BC33: Y | BD33: https://www.cardinalethanol.com/ | BE33: CSX | BF33: Yes | BK33: =IF(M33=2,10,5)+IF(Q33="ICM",10,5)+IF(X33="Y",10,5) -> 25
A34: 33 | D34: 3162 | E34: 3580 | F34: =IF(A34<300,"Active","Retired") -> Active | G34: Cargill | H34: =VLOOKUP(E34,'[1]EPA Ethanol Capacity 2024'!$B$5:$C$235,2,FALSE) -> Cargill Inc | I34: NE | J34: Blair | K34: 68008 | L34: Washington | M34: 2 | N34: 41.544697 | O34: -96.13507 | P34: 1995 | Q34: Vogelbusch | R34: =COUNTIF(G:G,"="&G34) -> 3 | AB34: Corn | AC34: D6/D5 | AD34: Website | AE34: =IF(BK34=1,"Low","High") -> High | AI34: 57902 | AJ34: =VLOOKUP(E34,'[1]Ethanol Plant Listing 2025'!$B$3:$E$220,4,FALSE) -> 210 | AK34: =+AJ34*[1]Yield!$K$4 -> 199.5 | AL34: =AK34/VLOOKUP(Q34,[1]Yield!$E$5:$F$14,2,FALSE) -> 68.793103 | AO34: =ROUND((+AL34*13.1*1000000)/2000,-3) -> 451000 | AQ34: =IF(G34="POET Biorefining",G34,IF(T34="FQPT HI Pro",T34,IF(Z34="ICM FOT",Z34,IF(Q34="ICM",Q34,IF(Q34="ADM",Q34,"None"))))) -> None | AR34: =VLOOKUP(AQ34,[1]Yield!$A$5:$B$10,2,FALSE) -> 0.815 | AS34: =(AL34)*AR34 -> 56.066379 | AT34: Likely | AX34: =IFERROR(VLOOKUP(E34,[1]Sheet3!$C$2:$E$68,2,FALSE),"None") -> None | AY34: =IFERROR(VLOOKUP(AX34,[1]Sheet3!$H$3:$I$5,2,FALSE),0) -> 0 | AZ34: =AJ34 -> 210 | BA34: =+AJ34*6.85*0.48/2 -> 345.24 | BB34: =SUMIFS('[1]Corn 2023'!V:V,'[1]Corn 2023'!K:K,"="&'Corn Processors'!J34,'[1]Corn 2023'!B:B,"=2023") -> 0 | BD34: https://www.cargill.com/home | BE34: UP | BF34: Yes | BK34: =IF(M34=2,10,5)+IF(Q34="ICM",10,5)+IF(X34="Y",10,5) -> 20
A35: 34 | D35: 3163 | E35: 3581 | F35: =IF(A35<300,"Active","Retired") -> Active | G35: Cargill | H35: =VLOOKUP(E35,'[1]EPA Ethanol Capacity 2024'!$B$5:$C$235,2,FALSE) -> Cargill Inc | I35: IA | J35: Eddyville | K35: 52553 | L35: Wapello | M35: 2 | N35: 41.55 | O35: -92.6343 | P35: 0 | Q35: Wet Mill | R35: =COUNTIF(G:G,"="&G35) -> 3 | U35: CHP | AB35: Corn | AC35: D6/D5 | AD35: Website | AE35: =IF(BK35=1,"Low","High") -> High | AF35: 70.1 | AG35: =0.165*365 -> 60.225 | AH35: 91-A-236 | AJ35: =VLOOKUP(E35,'[1]Ethanol Plant Listing 2025'!$B$3:$E$220,4,FALSE) -> 71 | AK35: =+AJ35*[1]Yield!$K$4 -> 67.45 | AL35: =AK35/VLOOKUP(Q35,[1]Yield!$E$5:$F$14,2,FALSE) -> 24.527273 | AO35: =ROUND((+AL35*13.1*1000000)/2000,-3) -> 161000 | AQ35: =IF(G35="POET Biorefining",G35,IF(T35="FQPT HI Pro",T35,IF(Z35="ICM FOT",Z35,IF(Q35="ICM",Q35,IF(Q35="ADM",Q35,"None"))))) -> None | AR35: =VLOOKUP(AQ35,[1]Yield!$A$5:$B$10,2,FALSE) -> 0.815 | AS35: =(AL35)*AR35 -> 19.989727 | AT35: Likely | AX35: =IFERROR(VLOOKUP(E35,[1]Sheet3!$C$2:$E$68,2,FALSE),"None") -> None | AY35: =IFERROR(VLOOKUP(AX35,[1]Sheet3!$H$3:$I$5,2,FALSE),0) -> 0 | AZ35: =AJ35 -> 71 | BA35: =+AJ35*6.85*0.48/2 -> 116.724 | BB35: =SUMIFS('[1]Corn 2023'!V:V,'[1]Corn 2023'!B:B,"=2023",'[1]Corn 2023'!L:L,"="&'Corn Processors'!L35) -> 58400 | BD35: https://www.cargill.com/home | BE35: UP/BNSF | BF35: Yes | BK35: =IF(M35=2,10,5)+IF(Q35="ICM",10,5)+IF(X35="Y",10,5) -> 20
A36: 35 | D36: 3164 | E36: 3582 | F36: =IF(A36<300,"Active","Retired") -> Active | G36: Cargill | H36: =VLOOKUP(E36,'[1]EPA Ethanol Capacity 2024'!$B$5:$C$235,2,FALSE) -> Cargill Inc | I36: IA | J36: Fort Dodge | K36: 50501 | L36: Webster | M36: 2 | N36: 42.506334 | O36: -94.313203 | P36: 2013 | Q36: Wet Mill | R36: =COUNTIF(G:G,"="&G36) -> 3 | AB36: Corn | AC36: D6/D5 | AD36: Website | AE36: =IF(BK36=1,"Low","High") -> High | AF36: 130 | AG36: 115 | AH36: 07-A-846 | AJ36: =VLOOKUP(E36,'[1]Ethanol Plant Listing 2025'!$B$3:$E$220,4,FALSE) -> 130 | AK36: =+AJ36*[1]Yield!$K$4 -> 123.5 | AL36: =AK36/VLOOKUP(Q36,[1]Yield!$E$5:$F$14,2,FALSE) -> 44.909091 | AO36: =ROUND((+AL36*13.1*1000000)/2000,-3) -> 294000 | AQ36: =IF(G36="POET Biorefining",G36,IF(T36="FQPT HI Pro",T36,IF(Z36="ICM FOT",Z36,IF(Q36="ICM",Q36,IF(Q36="ADM",Q36,"None"))))) -> None | AR36: =VLOOKUP(AQ36,[1]Yield!$A$5:$B$10,2,FALSE) -> 0.815 | AS36: =(AL36)*AR36 -> 36.600909 | AT36: Likely | AX36: =IFERROR(VLOOKUP(E36,[1]Sheet3!$C$2:$E$68,2,FALSE),"None") -> None | AY36: =IFERROR(VLOOKUP(AX36,[1]Sheet3!$H$3:$I$5,2,FALSE),0) -> 0 | AZ36: =AJ36 -> 130 | BA36: =+AJ36*6.85*0.48/2 -> 213.72 | BB36: =SUMIFS('[1]Corn 2023'!V:V,'[1]Corn 2023'!B:B,"=2023",'[1]Corn 2023'!L:L,"="&'Corn Processors'!L36) -> 195000 | BD36: https://www.cargill.com/home | BE36: UP/CN | BF36: Yes | BK36: =IF(M36=2,10,5)+IF(Q36="ICM",10,5)+IF(X36="Y",10,5) -> 20
A37: 36 | C37: 70150 | D37: 3166 | E37: 3585 | F37: =IF(A37<300,"Active","Retired") -> Active | G37: Chief Industries | H37: =VLOOKUP(E37,'[1]EPA Ethanol Capacity 2024'!$B$5:$C$235,2,FALSE) -> Chief Ethanol Fuels Inc | I37: NE | J37: Hastings | K37: 68901 | L37: Adams | M37: 2 | N37: 40.585 | O37: -98.318889 | P37: 1985 | Q37: Vogelbusch | R37: =COUNTIF(G:G,"="&G37) -> 2 | AB37: Corn | AC37: D6 | AD37: Website | AE37: =IF(BK37=1,"Low","High") -> High | AF37: 53 | AG37: 53 | AH37: AIR>CONSTRUCTION | AI37: 84534 | AJ37: =VLOOKUP(E37,'[1]Ethanol Plant Listing 2025'!$B$3:$E$220,4,FALSE) -> 70 | AK37: =+AJ37*[1]Yield!$K$4 -> 66.5 | AL37: =AK37/VLOOKUP(Q37,[1]Yield!$E$5:$F$14,2,FALSE) -> 22.931034 | AO37: =ROUND((+AL37*13.1*1000000)/2000,-3) -> 150000 | AQ37: =IF(G37="POET Biorefining",G37,IF(T37="FQPT HI Pro",T37,IF(Z37="ICM FOT",Z37,IF(Q37="ICM",Q37,IF(Q37="ADM",Q37,"None"))))) -> None | AR37: =VLOOKUP(AQ37,[1]Yield!$A$5:$B$10,2,FALSE) -> 0.815 | AS37: =(AL37)*AR37 -> 18.688793 | AT37: Y | AV37: =+AX37 -> Tall Grass | AX37: =IFERROR(VLOOKUP(E37,[1]Sheet3!$C$2:$E$68,2,FALSE),"None") -> Tall Grass | AY37: =IFERROR(VLOOKUP(AX37,[1]Sheet3!$H$3:$I$5,2,FALSE),0) -> 30 | AZ37: =AJ37 -> 70 | BA37: =+AJ37*6.85*0.48/2 -> 115.08 | BB37: =SUMIFS('[1]Corn 2023'!V:V,'[1]Corn 2023'!K:K,"="&'Corn Processors'!J37,'[1]Corn 2023'!B:B,"=2023") -> 0 | BD37: https://chiefethanol.com/ | BE37: UP/BNSF | BF37: Yes | BJ37: Member | BK37: =IF(M37=2,10,5)+IF(Q37="ICM",10,5)+IF(X37="Y",10,5) -> 20 | BL37: 10/31/22 Central Indiana Ethanol purchases from Louis Dreyfus for an undisclosed amount, Ocean Park was the advisor
A38: 37 | C38: 70241 | D38: 3167 | E38: 3586 | F38: =IF(A38<300,"Active","Retired") -> Active | G38: Chief Industries | H38: =VLOOKUP(E38,'[1]EPA Ethanol Capacity 2024'!$B$5:$C$235,2,FALSE) -> Chief Ethanol Fuels Inc | I38: NE | J38: Lexington | K38: 68850 | L38: Dawson | M38: 2 | N38: 40.746088 | O38: -99.767869 | P38: 2006 | Q38: Vogelbusch | R38: =COUNTIF(G:G,"="&G38) -> 2 | AB38: Corn | AC38: D6 | AD38: Website | AE38: =IF(BK38=1,"Low","High") -> High | AF38: 80 | AG38: 65 | AH38: AIR>CONSTRUCTION | AI38: 58049 | AJ38: =VLOOKUP(E38,'[1]Ethanol Plant Listing 2025'!$B$3:$E$220,4,FALSE) -> 52 | AK38: =+AJ38*[1]Yield!$K$4 -> 49.4 | AL38: =AK38/VLOOKUP(Q38,[1]Yield!$E$5:$F$14,2,FALSE) -> 17.034483 | AO38: =ROUND((+AL38*13.1*1000000)/2000,-3) -> 112000 | AQ38: =IF(G38="POET Biorefining",G38,IF(T38="FQPT HI Pro",T38,IF(Z38="ICM FOT",Z38,IF(Q38="ICM",Q38,IF(Q38="ADM",Q38,"None"))))) -> None | AR38: =VLOOKUP(AQ38,[1]Yield!$A$5:$B$10,2,FALSE) -> 0.815 | AS38: =(AL38)*AR38 -> 13.883103 | AT38: Y | AV38: =+AX38 -> Tall Grass | AX38: =IFERROR(VLOOKUP(E38,[1]Sheet3!$C$2:$E$68,2,FALSE),"None") -> Tall Grass | AY38: =IFERROR(VLOOKUP(AX38,[1]Sheet3!$H$3:$I$5,2,FALSE),0) -> 30 | AZ38: =AJ38 -> 52 | BA38: =+AJ38*6.85*0.48/2 -> 85.488 | BB38: =SUMIFS('[1]Corn 2023'!V:V,'[1]Corn 2023'!K:K,"="&'Corn Processors'!J38,'[1]Corn 2023'!B:B,"=2023") -> 0 | BD38: https://chiefethanol.com/ | BE38: UP | BF38: Yes | BJ38: Member | BK38: =IF(M38=2,10,5)+IF(Q38="ICM",10,5)+IF(X38="Y",10,5) -> 20
A39: 38 | C39: 70078 | D39: 2644 | E39: 3587 | F39: =IF(A39<300,"Active","Retired") -> Active | G39: Chippewa Valley Ethanol Co. | H39: =VLOOKUP(E39,'[1]EPA Ethanol Capacity 2024'!$B$5:$C$235,2,FALSE) -> Chippewa Valley Ethanol Co LLLP | I39: MN | J39: Benson | K39: 56215 | L39: Swift | M39: 2 | N39: 45.327 | O39: -95.6377 | P39: 1996 | Q39: Delta-T | R39: =COUNTIF(G:G,"="&G39) -> 1 | X39: White Fox ICM | Z39: Fluid Quip | AB39: Corn | AC39: D6 | AD39: Website | AE39: =IF(BK39=1,"Low","High") -> High | AI39: 77755 | AJ39: =VLOOKUP(E39,'[1]Ethanol Plant Listing 2025'!$B$3:$E$220,4,FALSE) -> 50 | AK39: =+AJ39*[1]Yield!$K$4 -> 47.5 | AL39: =AK39/VLOOKUP(Q39,[1]Yield!$E$5:$F$14,2,FALSE) -> 16.493056 | AO39: =ROUND((+AL39*13.1*1000000)/2000,-3) -> 108000 | AP39: Ring Dryer | AQ39: =IF(G39="POET Biorefining",G39,IF(T39="FQPT HI Pro",T39,IF(Z39="ICM FOT",Z39,IF(Q39="ICM",Q39,IF(Q39="ADM",Q39,"None"))))) -> None | AR39: =VLOOKUP(AQ39,[1]Yield!$A$5:$B$10,2,FALSE) -> 0.815 | AS39: =(AL39)*AR39 -> 13.44184 | AT39: Likely | AX39: =IFERROR(VLOOKUP(E39,[1]Sheet3!$C$2:$E$68,2,FALSE),"None") -> None | AY39: =IFERROR(VLOOKUP(AX39,[1]Sheet3!$H$3:$I$5,2,FALSE),0) -> 0 | AZ39: =AJ39 -> 50 | BA39: =+AJ39*6.85*0.48/2 -> 82.2 | BB39: =SUMIFS('[1]Corn 2023'!V:V,'[1]Corn 2023'!K:K,"="&'Corn Processors'!J39,'[1]Corn 2023'!B:B,"=2023") -> 0 | BD39: http://cvec.com/ | BE39: BNSF | BF39: No | BJ39: Member | BK39: =IF(M39=2,10,5)+IF(Q39="ICM",10,5)+IF(X39="Y",10,5) -> 20 | BL39: 5/27/16 Chief purchases from Cornhusker
A40: 39 | D40: 2436 | E40: 3588 | F40: =IF(A40<300,"Active","Retired") -> Active | G40: CHS | H40: =VLOOKUP(E40,'[1]EPA Ethanol Capacity 2024'!$B$5:$C$235,2,FALSE) -> CHS - Annawan | I40: IL | J40: Annawan | K40: 61234 | L40: Henry | M40: 2 | N40: 41.393398 | O40: -89.872214 | P40: 2008 | Q40: ICM | R40: =COUNTIF(G:G,"="&G40) -> 2 | S40: EP3 | X40: White Fox | AB40: Corn | AC40: D6 | AD40: https://www.chs-illinois.com/grain/cash-bids/ | AE40: =IF(BK40=1,"Low","High") -> High | AJ40: =VLOOKUP(E40,'[1]Ethanol Plant Listing 2025'!$B$3:$E$220,4,FALSE) -> 130 | AK40: =+AJ40*[1]Yield!$K$4 -> 123.5 | AL40: =AK40/VLOOKUP(Q40,[1]Yield!$E$5:$F$14,2,FALSE) -> 41.864407 | AO40: =ROUND((+AL40*13.1*1000000)/2000,-3) -> 274000 | AP40: Rotary Dryer | AQ40: =IF(G40="POET Biorefining",G40,IF(T40="FQPT HI Pro",T40,IF(Z40="ICM FOT",Z40,IF(Q40="ICM",Q40,IF(Q40="ADM",Q40,"None"))))) -> ICM | AR40: =VLOOKUP(AQ40,[1]Yield!$A$5:$B$10,2,FALSE) -> 0.9 | AS40: =(AL40)*AR40 -> 37.677966 | AT40: Likely | AX40: =IFERROR(VLOOKUP(E40,[1]Sheet3!$C$2:$E$68,2,FALSE),"None") -> None | AY40: =IFERROR(VLOOKUP(AX40,[1]Sheet3!$H$3:$I$5,2,FALSE),0) -> 0 | AZ40: =AJ40 -> 130 | BA40: =+AJ40*6.85*0.48/2 -> 213.72 | BB40: =SUMIFS('[1]Corn 2023'!V:V,'[1]Corn 2023'!K:K,"="&'Corn Processors'!J40,'[1]Corn 2023'!B:B,"=2023") -> 0 | BD40: https://www.chsinc.com/our-businesses/renewable-fuels | BE40: IAIS | BF40: Yes | BJ40: Member | BK40: =IF(M40=2,10,5)+IF(Q40="ICM",10,5)+IF(X40="Y",10,5) -> 25
A41: 40 | D41: 2437 | E41: 3589 | F41: =IF(A41<300,"Active","Retired") -> Active | G41: CHS | H41: =VLOOKUP(E41,'[1]EPA Ethanol Capacity 2024'!$B$5:$C$235,2,FALSE) -> CHS - Rochelle | I41: IL | J41: Rochelle | K41: 61068 | L41: Ogle | M41: 2 | N41: 41.89508 | O41: -89.02898 | P41: 2006 | Q41: ICM | R41: =COUNTIF(G:G,"="&G41) -> 2 | S41: EP3 | AB41: Corn | AC41: D6 | AD41: https://www.chs-illinois.com/grain/cash-bids/ | AE41: =IF(BK41=1,"Low","High") -> High | AJ41: =VLOOKUP(E41,'[1]Ethanol Plant Listing 2025'!$B$3:$E$220,4,FALSE) -> 138 | AK41: =+AJ41*[1]Yield!$K$4 -> 131.1 | AL41: =AK41/VLOOKUP(Q41,[1]Yield!$E$5:$F$14,2,FALSE) -> 44.440678 | AO41: =ROUND((+AL41*13.1*1000000)/2000,-3) -> 291000 | AP41: Rotary Dryer | AQ41: =IF(G41="POET Biorefining",G41,IF(T41="FQPT HI Pro",T41,IF(Z41="ICM FOT",Z41,IF(Q41="ICM",Q41,IF(Q41="ADM",Q41,"None"))))) -> ICM | AR41: =VLOOKUP(AQ41,[1]Yield!$A$5:$B$10,2,FALSE) -> 0.9 | AS41: =(AL41)*AR41 -> 39.99661 | AT41: Likely | AX41: =IFERROR(VLOOKUP(E41,[1]Sheet3!$C$2:$E$68,2,FALSE),"None") -> None | AY41: =IFERROR(VLOOKUP(AX41,[1]Sheet3!$H$3:$I$5,2,FALSE),0) -> 0 | AZ41: =AJ41 -> 138 | BA41: =+AJ41*6.85*0.48/2 -> 226.872 | BB41: =SUMIFS('[1]Corn 2023'!V:V,'[1]Corn 2023'!K:K,"="&'Corn Processors'!J41,'[1]Corn 2023'!B:B,"=2023") -> 0 | BD41: https://www.chsinc.com/our-businesses/renewable-fuels | BE41: BNSF | BF41: Yes | BJ41: Member | BK41: =IF(M41=2,10,5)+IF(Q41="ICM",10,5)+IF(X41="Y",10,5) -> 25 | BL41: 6/1/15 CHS purchases Patriot Renewable Fuels for $196M
A42: 41 | D42: 3165 | E42: 3583 | F42: =IF(A42<300,"Active","Retired") -> Active | G42: Central Indiana Ethanol | H42: =VLOOKUP(E42,'[1]EPA Ethanol Capacity 2024'!$B$5:$C$235,2,FALSE) -> Central Indiana Ethanol | I42: IN | J42: Marion | K42: 46952 | L42: Grant | M42: 2 | N42: 40.56492 | O42: -85.72772 | P42: 2007 | Q42: ICM | R42: =COUNTIF(G:G,"="&G42) -> 2 | AB42: Corn | AC42: D6 | AD42: Website | AE42: =IF(BK42=1,"Low","High") -> High | AJ42: =VLOOKUP(E42,'[1]Ethanol Plant Listing 2025'!$B$3:$E$220,4,FALSE) -> 50 | AK42: =+AJ42*[1]Yield!$K$4 -> 47.5 | AL42: =AK42/VLOOKUP(Q42,[1]Yield!$E$5:$F$14,2,FALSE) -> 16.101695 | AO42: =ROUND((+AL42*13.1*1000000)/2000,-3) -> 105000 | AP42: Rotary Dryer | AQ42: =IF(G42="POET Biorefining",G42,IF(T42="FQPT HI Pro",T42,IF(Z42="ICM FOT",Z42,IF(Q42="ICM",Q42,IF(Q42="ADM",Q42,"None"))))) -> ICM | AR42: =VLOOKUP(AQ42,[1]Yield!$A$5:$B$10,2,FALSE) -> 0.9 | AS42: =(AL42)*AR42 -> 14.491525 | AT42: Likely | AX42: =IFERROR(VLOOKUP(E42,[1]Sheet3!$C$2:$E$68,2,FALSE),"None") -> None | AY42: =IFERROR(VLOOKUP(AX42,[1]Sheet3!$H$3:$I$5,2,FALSE),0) -> 0 | AZ42: =AJ42 -> 50 | BA42: =+AJ42*6.85*0.48/2 -> 82.2 | BB42: =SUMIFS('[1]Corn 2023'!V:V,'[1]Corn 2023'!K:K,"="&'Corn Processors'!J42,'[1]Corn 2023'!B:B,"=2023") -> 75300 | BD42: https://www.cie.us/ | BE42: NS | BF42: Yes | BJ42: Member | BK42: =IF(M42=2,10,5)+IF(Q42="ICM",10,5)+IF(X42="Y",10,5) -> 25
A43: 42 | B43: 4833 | C43: 70095 | D43: 3213 | E43: 3584 | F43: =IF(A43<300,"Active","Retired") -> Active | G43: Central Indiana Ethanol | H43: =VLOOKUP(E43,'[1]EPA Ethanol Capacity 2024'!$B$5:$C$235,2,FALSE) -> CIE Norfolk GNS LLC | I43: NE | J43: Norfolk | K43: 68701 | L43: Madison | M43: 2 | N43: 42.06672 | O43: -97.3815 | P43: 2007 | Q43: ICM | R43: =COUNTIF(G:G,"="&G43) -> 2 | S43: EP3 | AB43: Corn | AC43: D6 | AD43: Website | AE43: =IF(BK43=1,"Low","High") -> High | AF43: 110 | AG43: 110 | AH43: 07-A-767 | AJ43: =VLOOKUP(E43,'[1]Ethanol Plant Listing 2025'!$B$3:$E$220,4,FALSE) -> 60 | AK43: =+AJ43*[1]Yield!$K$4 -> 57 | AL43: =AK43/VLOOKUP(Q43,[1]Yield!$E$5:$F$14,2,FALSE) -> 19.322034 | AO43: =ROUND((+AL43*13.1*1000000)/2000,-3) -> 127000 | AP43: Rotary Dryer | AQ43: =IF(G43="POET Biorefining",G43,IF(T43="FQPT HI Pro",T43,IF(Z43="ICM FOT",Z43,IF(Q43="ICM",Q43,IF(Q43="ADM",Q43,"None"))))) -> ICM | AR43: =VLOOKUP(AQ43,[1]Yield!$A$5:$B$10,2,FALSE) -> 0.9 | AS43: =(AL43)*AR43 -> 17.389831 | AT43: Y | AX43: =IFERROR(VLOOKUP(E43,[1]Sheet3!$C$2:$E$68,2,FALSE),"None") -> None | AY43: =IFERROR(VLOOKUP(AX43,[1]Sheet3!$H$3:$I$5,2,FALSE),0) -> 0 | AZ43: =AJ43 -> 60 | BA43: =+AJ43*6.85*0.48/2 -> 98.64 | BB43: =SUMIFS('[1]Corn 2023'!V:V,'[1]Corn 2023'!K:K,"="&'Corn Processors'!J43,'[1]Corn 2023'!B:B,"=2023") -> 0 | BD43: https://www.cie.us/ | BE43: NCRC/WC1s | BF43: No | BJ43: Member | BK43: =IF(M43=2,10,5)+IF(Q43="ICM",10,5)+IF(X43="Y",10,5) -> 25
A44: 43 | D44: 3168 | E44: 3590 | F44: =IF(A44<300,"Active","Retired") -> Active | G44: Hopkinsville Elevator CO-OP | H44: =VLOOKUP(E44,'[1]EPA Ethanol Capacity 2024'!$B$5:$C$235,2,FALSE) -> Commonwealth Agri-Energy | I44: KY | J44: Hopkinsville | K44: 42240 | L44: Christian | M44: 2 | N44: 36.81342 | O44: -87.41009 | P44: 2004 | Q44: ICM | R44: =COUNTIF(G:G,"="&G44) -> 1 | S44: EP3 | U44: CHP | AB44: Corn | AC44: D6 | AD44: Website | AE44: =IF(BK44=1,"Low","High") -> High | AJ44: =VLOOKUP(E44,'[1]Ethanol Plant Listing 2025'!$B$3:$E$220,4,FALSE) -> 49 | AK44: =+AJ44*[1]Yield!$K$4 -> 46.55 | AL44: =AK44/VLOOKUP(Q44,[1]Yield!$E$5:$F$14,2,FALSE) -> 15.779661 | AO44: =ROUND((+AL44*13.1*1000000)/2000,-3) -> 103000 | AP44: Rotary Dryer | AQ44: =IF(G44="POET Biorefining",G44,IF(T44="FQPT HI Pro",T44,IF(Z44="ICM FOT",Z44,IF(Q44="ICM",Q44,IF(Q44="ADM",Q44,"None"))))) -> ICM | AR44: =VLOOKUP(AQ44,[1]Yield!$A$5:$B$10,2,FALSE) -> 0.9 | AS44: =(AL44)*AR44 -> 14.201695 | AT44: Likely | AX44: =IFERROR(VLOOKUP(E44,[1]Sheet3!$C$2:$E$68,2,FALSE),"None") -> None | AY44: =IFERROR(VLOOKUP(AX44,[1]Sheet3!$H$3:$I$5,2,FALSE),0) -> 0 | AZ44: =AJ44 -> 49 | BA44: =+AJ44*6.85*0.48/2 -> 80.556 | BB44: =SUMIFS('[1]Corn 2023'!V:V,'[1]Corn 2023'!K:K,"="&'Corn Processors'!J44,'[1]Corn 2023'!B:B,"=2023") -> 0 | BD44: http://www.commonwealthagrienergy.com/ | BE44: CSX | BF44: No | BK44: =IF(M44=2,10,5)+IF(Q44="ICM",10,5)+IF(X44="Y",10,5) -> 25
A45: 44 | B45: 5065 | C45: 70145 | D45: 2439 | E45: 3591 | F45: =IF(A45<300,"Active","Retired") -> Active | G45: Gold-Eagle Cooperative | H45: =VLOOKUP(E45,'[1]EPA Ethanol Capacity 2024'!$B$5:$C$235,2,FALSE) -> Corn LP | I45: IA | J45: Goldfield | K45: 50542 | L45: Wright | M45: 2 | N45: 42.733339 | O45: -93.910902 | P45: 2006 | Q45: ICM | R45: =COUNTIF(G:G,"="&G45) -> 1 | T45: ICM HI PRO | AB45: Corn | AC45: D6 | AD45: Website | AE45: =IF(BK45=1,"Low","High") -> High | AJ45: =VLOOKUP(E45,'[1]Ethanol Plant Listing 2025'!$B$3:$E$220,4,FALSE) -> 80 | AK45: =+AJ45*[1]Yield!$K$4 -> 76 | AL45: =AK45/VLOOKUP(Q45,[1]Yield!$E$5:$F$14,2,FALSE) -> 25.762712 | AO45: =ROUND((+AL45*13.1*1000000)/2000,-3) -> 169000 | AP45: Rotary Dryer | AQ45: =IF(G45="POET Biorefining",G45,IF(T45="FQPT HI Pro",T45,IF(Z45="ICM FOT",Z45,IF(Q45="ICM",Q45,IF(Q45="ADM",Q45,"None"))))) -> ICM | AR45: =VLOOKUP(AQ45,[1]Yield!$A$5:$B$10,2,FALSE) -> 0.9 | AS45: =(AL45)*AR45 -> 23.186441 | AT45: Y | AV45: SCS | AX45: =IFERROR(VLOOKUP(E45,[1]Sheet3!$C$2:$E$68,2,FALSE),"None") -> Summit Carbon Solutions | AY45: =IFERROR(VLOOKUP(AX45,[1]Sheet3!$H$3:$I$5,2,FALSE),0) -> 31 | AZ45: =AJ45 -> 80 | BA45: =+AJ45*6.85*0.48/2 -> 131.52 | BB45: =SUMIFS('[1]Corn 2023'!V:V,'[1]Corn 2023'!B:B,"=2023",'[1]Corn 2023'!L:L,"="&'Corn Processors'!L45) -> 171000 | BD45: http://www.cornlp.com/ | BE45: UP | BF45: Yes | BK45: =IF(M45=2,10,5)+IF(Q45="ICM",10,5)+IF(X45="Y",10,5) -> 25
A46: 45 | B46: 4810 | C46: 70083 | D46: 3169 | E46: 3592 | F46: =IF(A46<300,"Active","Retired") -> Active | G46: Dakota Ethanol | H46: =VLOOKUP(E46,'[1]EPA Ethanol Capacity 2024'!$B$5:$C$235,2,FALSE) -> Dakota Ethanol LLC | I46: SD | J46: Wentworth | K46: 57075 | L46: Lake | M46: 2 | N46: 43.976389 | O46: -96.95333 | P46: 2001 | Q46: ICM | R46: =COUNTIF(G:G,"="&G46) -> 1 | S46: EP3 | AB46: Corn | AC46: D6 | AD46: Website | AE46: =IF(BK46=1,"Low","High") -> High | AF46: 80 | AG46: 55 | AH46: 05-A-113 | AJ46: =VLOOKUP(E46,'[1]Ethanol Plant Listing 2025'!$B$3:$E$220,4,FALSE) -> 100 | AK46: =+AJ46*[1]Yield!$K$4 -> 95 | AL46: =AK46/VLOOKUP(Q46,[1]Yield!$E$5:$F$14,2,FALSE) -> 32.20339 | AO46: =ROUND((+AL46*13.1*1000000)/2000,-3) -> 211000 | AP46: Rotary Dryer | AQ46: =IF(G46="POET Biorefining",G46,IF(T46="FQPT HI Pro",T46,IF(Z46="ICM FOT",Z46,IF(Q46="ICM",Q46,IF(Q46="ADM",Q46,"None"))))) -> ICM | AR46: =VLOOKUP(AQ46,[1]Yield!$A$5:$B$10,2,FALSE) -> 0.9 | AS46: =(AL46)*AR46 -> 28.983051 | AT46: Y | AV46: SCS | AX46: =IFERROR(VLOOKUP(E46,[1]Sheet3!$C$2:$E$68,2,FALSE),"None") -> Summit Carbon Solutions | AY46: =IFERROR(VLOOKUP(AX46,[1]Sheet3!$H$3:$I$5,2,FALSE),0) -> 31 | AZ46: =AJ46 -> 100 | BA46: =+AJ46*6.85*0.48/2 -> 164.4 | BB46: =SUMIFS('[1]Corn 2023'!V:V,'[1]Corn 2023'!K:K,"="&'Corn Processors'!J46,'[1]Corn 2023'!B:B,"=2023") -> 0 | BD46: https://www.dakotaethanol.com/ | BE46: BNSF | BF46: Yes | BJ46: Member | BK46: =IF(M46=2,10,5)+IF(Q46="ICM",10,5)+IF(X46="Y",10,5) -> 25
A47: 46 | D47: 3170 | E47: 3593 | F47: =IF(A47<300,"Active","Retired") -> Active | G47: Harvestone | H47: =VLOOKUP(E47,'[1]EPA Ethanol Capacity 2024'!$B$5:$C$235,2,FALSE) -> Dakota Spirit Agenergy | I47: ND | J47: Spiritwood | K47: 58481 | L47: Barnes | M47: 2 | N47: 46.924798 | O47: -98.503225 | P47: 2007 | Q47: ICM | R47: =COUNTIF(G:G,"="&G47) -> 3 | Z47: Alpha Laval | AB47: Corn | AC47: D6 | AD47: Website | AE47: =IF(BK47=1,"Low","High") -> High | AJ47: =VLOOKUP(E47,'[1]Ethanol Plant Listing 2025'!$B$3:$E$220,4,FALSE) -> 80 | AK47: =+AJ47*[1]Yield!$K$4 -> 76 | AL47: =AK47/VLOOKUP(Q47,[1]Yield!$E$5:$F$14,2,FALSE) -> 25.762712 | AO47: =ROUND((+AL47*13.1*1000000)/2000,-3) -> 169000 | AP47: Rotary Dryer | AQ47: =IF(G47="POET Biorefining",G47,IF(T47="FQPT HI Pro",T47,IF(Z47="ICM FOT",Z47,IF(Q47="ICM",Q47,IF(Q47="ADM",Q47,"None"))))) -> ICM | AR47: =VLOOKUP(AQ47,[1]Yield!$A$5:$B$10,2,FALSE) -> 0.9 | AS47: =(AL47)*AR47 -> 23.186441 | AT47: Likely | AU47: Direct | AX47: =IFERROR(VLOOKUP(E47,[1]Sheet3!$C$2:$E$68,2,FALSE),"None") -> Direct Inject | AY47: =IFERROR(VLOOKUP(AX47,[1]Sheet3!$H$3:$I$5,2,FALSE),0) -> 32 | AZ47: =AJ47 -> 80 | BA47: =+AJ47*6.85*0.48/2 -> 131.52 | BB47: =SUMIFS('[1]Corn 2023'!V:V,'[1]Corn 2023'!K:K,"="&'Corn Processors'!J47,'[1]Corn 2023'!B:B,"=2023") -> 0 | BD47: https://www.midwestagenergy.com/fccp-dakota-spirit-19635 | BE47: BNSF | BF47: Yes | BJ47: Member | BK47: =IF(M47=2,10,5)+IF(Q47="ICM",10,5)+IF(X47="Y",10,5) -> 25
A48: 47 | C48: 70082 | D48: 2882 | E48: 3594 | F48: =IF(A48<300,"Active","Retired") -> Active | G48: DENCO II | H48: =VLOOKUP(E48,'[1]EPA Ethanol Capacity 2024'!$B$5:$C$235,2,FALSE) -> Denco II LLC | I48: MN | J48: Morris | K48: 56267 | L48: Stevens | M48: 2 | N48: 45.57516 | O48: -95.912386 | P48: 1991 | Q48: ICM | R48: =COUNTIF(G:G,"="&G48) -> 1 | Z48: Alpha Laval | AB48: Corn | AC48: D6/D5 | AD48: Website | AE48: =IF(BK48=1,"Low","High") -> High | AJ48: =VLOOKUP(E48,'[1]Ethanol Plant Listing 2025'!$B$3:$E$220,4,FALSE) -> 30 | AK48: =+AJ48*[1]Yield!$K$4 -> 28.5 | AL48: =AK48/VLOOKUP(Q48,[1]Yield!$E$5:$F$14,2,FALSE) -> 9.6610169 | AO48: =ROUND((+AL48*13.1*1000000)/2000,-3) -> 63000 | AP48: Rotary Dryer | AQ48: =IF(G48="POET Biorefining",G48,IF(T48="FQPT HI Pro",T48,IF(Z48="ICM FOT",Z48,IF(Q48="ICM",Q48,IF(Q48="ADM",Q48,"None"))))) -> ICM | AR48: =VLOOKUP(AQ48,[1]Yield!$A$5:$B$10,2,FALSE) -> 0.9 | AS48: =(AL48)*AR48 -> 8.6949153 | AT48: Likely | AX48: =IFERROR(VLOOKUP(E48,[1]Sheet3!$C$2:$E$68,2,FALSE),"None") -> None | AY48: =IFERROR(VLOOKUP(AX48,[1]Sheet3!$H$3:$I$5,2,FALSE),0) -> 0 | AZ48: =AJ48 -> 30 | BA48: =+AJ48*6.85*0.48/2 -> 49.32 | BB48: =SUMIFS('[1]Corn 2023'!V:V,'[1]Corn 2023'!K:K,"="&'Corn Processors'!J48,'[1]Corn 2023'!B:B,"=2023") -> 0 | BD48: http://www.dencollc.com/ | BE48: UnKnown | BF48: No | BG48: Yes | BK48: =IF(M48=2,10,5)+IF(Q48="ICM",10,5)+IF(X48="Y",10,5) -> 25
A49: 48 | D49: 3171 | E49: 3595 | F49: =IF(A49<300,"Active","Retired") -> Active | G49: Conestoga Energy | H49: =VLOOKUP(E49,'[1]EPA Ethanol Capacity 2024'!$B$5:$C$235,2,FALSE) -> HET Levelland LLC | I49: TX | J49: Levelland | K49: 79336 | L49: Hockley | M49: 3 | N49: 33.588611 | O49: -102.26278 | P49: 2007 | Q49: ICM | R49: =COUNTIF(G:G,"="&G49) -> 3 | AB49: Corn/Milo | AC49: D6 | AD49: Website | AE49: =IF(BK49=1,"Low","High") -> High | AJ49: =VLOOKUP(E49,'[1]Ethanol Plant Listing 2025'!$B$3:$E$220,4,FALSE) -> 50.274 | AK49: =+AJ49*[1]Yield!$K$4 -> 47.7603 | AL49: =AK49/VLOOKUP(Q49,[1]Yield!$E$5:$F$14,2,FALSE) -> 16.189932 | AO49: =ROUND((+AL49*13.1*1000000)/2000,-3) -> 106000 | AP49: Rotary Dryer | AQ49: =IF(G49="POET Biorefining",G49,IF(T49="FQPT HI Pro",T49,IF(Z49="ICM FOT",Z49,IF(Q49="ICM",Q49,IF(Q49="ADM",Q49,"None"))))) -> ICM | AR49: =VLOOKUP(AQ49,[1]Yield!$A$5:$B$10,2,FALSE) -> 0.9 | AS49: =(AL49)*AR49 -> 14.570939 | AT49: Likely | AX49: =IFERROR(VLOOKUP(E49,[1]Sheet3!$C$2:$E$68,2,FALSE),"None") -> None | AY49: =IFERROR(VLOOKUP(AX49,[1]Sheet3!$H$3:$I$5,2,FALSE),0) -> 0 | AZ49: =AJ49 -> 50.274 | BA49: =+AJ49*6.85*0.48/2 -> 82.650456 | BB49: =SUMIFS('[1]Corn 2023'!V:V,'[1]Corn 2023'!K:K,"="&'Corn Processors'!J49,'[1]Corn 2023'!B:B,"=2023") -> 0 | BD49: https://www.conestogaenergy.com/ | BE49: BNSF | BF49: Yes | BK49: =IF(M49=2,10,5)+IF(Q49="ICM",10,5)+IF(X49="Y",10,5) -> 20
A50: 49 | D50: 3172 | E50: 3596 | F50: =IF(A50<300,"Active","Retired") -> Active | G50: Didion Milling | H50: =VLOOKUP(E50,'[1]EPA Ethanol Capacity 2024'!$B$5:$C$235,2,FALSE) -> Didion Ethanol LLC | I50: WI | J50: Cambria | K50: 53923 | L50: Columbia | M50: 2 | N50: 43.53731 | O50: -89.10315 | P50: 0 | Q50: Delta-T | R50: =COUNTIF(G:G,"="&G50) -> 1 | S50: EP3 | AB50: Corn | AC50: D6 | AD50: Website | AE50: =IF(BK50=1,"Low","High") -> High | AJ50: =VLOOKUP(E50,'[1]Ethanol Plant Listing 2025'!$B$3:$E$220,4,FALSE) -> 54 | AK50: =+AJ50*[1]Yield!$K$4 -> 51.3 | AL50: =AK50/VLOOKUP(Q50,[1]Yield!$E$5:$F$14,2,FALSE) -> 17.8125 | AO50: =ROUND((+AL50*13.1*1000000)/2000,-3) -> 117000 | AP50: Ring Dryer | AQ50: =IF(G50="POET Biorefining",G50,IF(T50="FQPT HI Pro",T50,IF(Z50="ICM FOT",Z50,IF(Q50="ICM",Q50,IF(Q50="ADM",Q50,"None"))))) -> None | AR50: =VLOOKUP(AQ50,[1]Yield!$A$5:$B$10,2,FALSE) -> 0.815 | AS50: =(AL50)*AR50 -> 14.517187 | AT50: Unlikely | AX50: =IFERROR(VLOOKUP(E50,[1]Sheet3!$C$2:$E$68,2,FALSE),"None") -> None | AY50: =IFERROR(VLOOKUP(AX50,[1]Sheet3!$H$3:$I$5,2,FALSE),0) -> 0 | AZ50: =AJ50 -> 54 | BA50: =+AJ50*6.85*0.48/2 -> 88.776 | BB50: =SUMIFS('[1]Corn 2023'!V:V,'[1]Corn 2023'!K:K,"="&'Corn Processors'!J50,'[1]Corn 2023'!B:B,"=2023") -> 0 | BD50: https://didioninc.com/ | BE50: WSOR/CN/UP | BF50: No | BK50: =IF(M50=2,10,5)+IF(Q50="ICM",10,5)+IF(X50="Y",10,5) -> 20
A51: 50 | B51: 4831 | C51: 70093 | D51: 3173 | E51: 3597 | F51: =IF(A51<300,"Active","Retired") -> Active | G51: E Energy Adams, LLC | H51: =VLOOKUP(E51,'[1]EPA Ethanol Capacity 2024'!$B$5:$C$235,2,FALSE) -> E Energy Adams LLC | I51: NE | J51: Adams | K51: 68301 | L51: Gage | M51: 2 | N51: 40.4842 | O51: -96.5459 | P51: 2007 | Q51: ICM | R51: =COUNTIF(G:G,"="&G51) -> 1 | S51: EP3 | X51: White Fox ICE | Y51: DEER | Z51: Fluid Quip | AB51: Corn | AC51: D6 | AD51: Website | AE51: =IF(BK51=1,"Low","High") -> High | AJ51: =VLOOKUP(E51,'[1]Ethanol Plant Listing 2025'!$B$3:$E$220,4,FALSE) -> 101 | AK51: =+AJ51*[1]Yield!$K$4 -> 95.95 | AL51: =AK51/VLOOKUP(Q51,[1]Yield!$E$5:$F$14,2,FALSE) -> 32.525424 | AO51: =ROUND((+AL51*13.1*1000000)/2000,-3) -> 213000 | AP51: Rotary Dryer | AQ51: =IF(G51="POET Biorefining",G51,IF(T51="FQPT HI Pro",T51,IF(Z51="ICM FOT",Z51,IF(Q51="ICM",Q51,IF(Q51="ADM",Q51,"None"))))) -> ICM | AR51: =VLOOKUP(AQ51,[1]Yield!$A$5:$B$10,2,FALSE) -> 0.9 | AS51: =(AL51)*AR51 -> 29.272881 | AT51: Likely | AX51: =IFERROR(VLOOKUP(E51,[1]Sheet3!$C$2:$E$68,2,FALSE),"None") -> None | AY51: =IFERROR(VLOOKUP(AX51,[1]Sheet3!$H$3:$I$5,2,FALSE),0) -> 0 | AZ51: =AJ51 -> 101 | BA51: =+AJ51*6.85*0.48/2 -> 166.044 | BB51: =SUMIFS('[1]Corn 2023'!V:V,'[1]Corn 2023'!K:K,"="&'Corn Processors'!J51,'[1]Corn 2023'!B:B,"=2023") -> 0 | BD51: http://www.eenergyadams.com/ | BE51: BNSF | BF51: Yes | BJ51: Member | BK51: =IF(M51=2,10,5)+IF(Q51="ICM",10,5)+IF(X51="Y",10,5) -> 25
A52: 51 | B52: 4483 | C52: 83483 | D52: 3174 | E52: 3598 | F52: =IF(A52<300,"Active","Retired") -> Active | G52: East Kansas Agri-Energy | H52: =VLOOKUP(E52,'[1]EPA Ethanol Capacity 2024'!$B$5:$C$235,2,FALSE) -> East Kansas Agri-Energy LLC | I52: KS | J52: Garnett | K52: 66032 | L52: Anderson | M52: 2 | N52: 38.271522 | O52: -95.237414 | P52: 2004 | Q52: ICM | R52: =COUNTIF(G:G,"="&G52) -> 1 | S52: EP3 | AB52: Corn | AC52: D6 | AD52: Website | AE52: =IF(BK52=1,"Low","High") -> High | AF52: 101 | AG52: 55 | AH52: AIR>CONSTRUCTION | AI52: 86373 | AJ52: =VLOOKUP(E52,'[1]Ethanol Plant Listing 2025'!$B$3:$E$220,4,FALSE) -> 48 | AK52: =+AJ52*[1]Yield!$K$4 -> 45.6 | AL52: =AK52/VLOOKUP(Q52,[1]Yield!$E$5:$F$14,2,FALSE) -> 15.457627 | AO52: =ROUND((+AL52*13.1*1000000)/2000,-3) -> 101000 | AP52: Rotary Dryer | AQ52: =IF(G52="POET Biorefining",G52,IF(T52="FQPT HI Pro",T52,IF(Z52="ICM FOT",Z52,IF(Q52="ICM",Q52,IF(Q52="ADM",Q52,"None"))))) -> ICM | AR52: =VLOOKUP(AQ52,[1]Yield!$A$5:$B$10,2,FALSE) -> 0.9 | AS52: =(AL52)*AR52 -> 13.911864 | AT52: Likely | AY52: =IFERROR(VLOOKUP(AX52,[1]Sheet3!$H$3:$I$5,2,FALSE),0) -> 0 | AZ52: =AJ52 -> 48 | BA52: =+AJ52*6.85*0.48/2 -> 78.912 | BD52: https://ekaellc.com/ | BE52: UP | BF52: No | BG52: Yes | BJ52: Member | BK52: =IF(M52=2,10,5)+IF(Q52="ICM",10,5)+IF(X52="Y",10,5) -> 25
A53: 52 | B53: 6500 | C53: 71287 | D53: 3176 | E53: 3600 | F53: =IF(A53<300,"Active","Retired") -> Active | G53: Elite Octane | H53: =VLOOKUP(E53,'[1]EPA Ethanol Capacity 2024'!$B$5:$C$235,2,FALSE) -> Elite Octane LLC | I53: IA | J53: Atlantic | K53: 50022 | L53: Cass | M53: 2 | N53: 41.41772 | O53: -95.03182 | P53: 2019 | Q53: ICM | R53: =COUNTIF(G:G,"="&G53) -> 1 | S53: EP3 | Z53: ICM | AB53: Corn | AC53: D6 | AD53: Website | AE53: =IF(BK53=1,"Low","High") -> High | AJ53: =VLOOKUP(E53,'[1]Ethanol Plant Listing 2025'!$B$3:$E$220,4,FALSE) -> 175 | AK53: =+AJ53*[1]Yield!$K$4 -> 166.25 | AL53: =AK53/VLOOKUP(Q53,[1]Yield!$E$5:$F$14,2,FALSE) -> 56.355932 | AO53: =ROUND((+AL53*13.1*1000000)/2000,-3) -> 369000 | AP53: Rotary Dryer | AQ53: =IF(G53="POET Biorefining",G53,IF(T53="FQPT HI Pro",T53,IF(Z53="ICM FOT",Z53,IF(Q53="ICM",Q53,IF(Q53="ADM",Q53,"None"))))) -> ICM | AR53: =VLOOKUP(AQ53,[1]Yield!$A$5:$B$10,2,FALSE) -> 0.9 | AS53: =(AL53)*AR53 -> 50.720339 | AT53: Likely | AX53: =IFERROR(VLOOKUP(E53,[1]Sheet3!$C$2:$E$68,2,FALSE),"None") -> None | AY53: =IFERROR(VLOOKUP(AX53,[1]Sheet3!$H$3:$I$5,2,FALSE),0) -> 0 | AZ53: =AJ53 -> 175 | BA53: =+AJ53*6.85*0.48/2 -> 287.7 | BB53: =SUMIFS('[1]Corn 2023'!V:V,'[1]Corn 2023'!B:B,"=2023",'[1]Corn 2023'!L:L,"="&'Corn Processors'!L53) -> 0 | BD53: https://www.eliteoctane.net/ | BE53: IAIS | BF53: Yes | BI53: Importer | BJ53: Member | BK53: =IF(M53=2,10,5)+IF(Q53="ICM",10,5)+IF(X53="Y",10,5) -> 25
A54: 53 | D54: 3175 | E54: 3601 | F54: =IF(A54<300,"Active","Retired") -> Active | G54: ACE Ethanol | H54: =VLOOKUP(E54,'[1]EPA Ethanol Capacity 2024'!$B$5:$C$235,2,FALSE) -> Fox River Valley Ethanol LLC | I54: WI | J54: Oshkosh | K54: 54904 | L54: Winnebago | M54: 2 | N54: 43.980233 | O54: -88.651815 | P54: 0 | Q54: Delta-T | R54: =COUNTIF(G:G,"="&G54) -> 2 | X54: White Fox ICE | AB54: Corn | AC54: D6 | AD54: Website | AE54: =IF(BK54=1,"Low","High") -> High | AF54: 150 | AG54: 150 | AH54: 15-A-091 | AJ54: =VLOOKUP(E54,'[1]Ethanol Plant Listing 2025'!$B$3:$E$220,4,FALSE) -> 64 | AK54: =+AJ54*[1]Yield!$K$4 -> 60.8 | AL54: =AK54/VLOOKUP(Q54,[1]Yield!$E$5:$F$14,2,FALSE) -> 21.111111 | AO54: =ROUND((+AL54*13.1*1000000)/2000,-3) -> 138000 | AP54: Ring Dryer | AQ54: =IF(G54="POET Biorefining",G54,IF(T54="FQPT HI Pro",T54,IF(Z54="ICM FOT",Z54,IF(Q54="ICM",Q54,IF(Q54="ADM",Q54,"None"))))) -> None | AR54: =VLOOKUP(AQ54,[1]Yield!$A$5:$B$10,2,FALSE) -> 0.815 | AS54: =(AL54)*AR54 -> 17.205556 | AT54: Unlikely | AX54: =IFERROR(VLOOKUP(E54,[1]Sheet3!$C$2:$E$68,2,FALSE),"None") -> None | AY54: =IFERROR(VLOOKUP(AX54,[1]Sheet3!$H$3:$I$5,2,FALSE),0) -> 0 | AZ54: =AJ54 -> 64 | BA54: =+AJ54*6.85*0.48/2 -> 105.216 | BD54: https://www.frvethanol.com/ | BE54: WSOR/CN/UP | BF54: No | BG54: Yes | BI54: Importer | BJ54: Member | BK54: =IF(M54=2,10,5)+IF(Q54="ICM",10,5)+IF(X54="Y",10,5) -> 20
A55: 54 | B55: 4758 | C55: 70058 | D55: 3177 | E55: 3602 | F55: =IF(A55<300,"Active","Retired") -> Active | G55: Front Range Energy LLC | H55: =VLOOKUP(E55,'[1]EPA Ethanol Capacity 2024'!$B$5:$C$235,2,FALSE) -> Front Range Energy LLC | I55: CO | J55: Windsor | K55: 80550 | L55: Weld | M55: 4 | N55: 40.45746 | O55: -104.85621 | P55: 2006 | Q55: ICM | R55: =COUNTIF(G:G,"="&G55) -> 1 | X55: White Fox | AB55: Corn | AC55: D6/D5 | AD55: Website | AE55: =IF(BK55=1,"Low","High") -> High | AJ55: =VLOOKUP(E55,'[1]Ethanol Plant Listing 2025'!$B$3:$E$220,4,FALSE) -> 46 | AK55: =+AJ55*[1]Yield!$K$4 -> 43.7 | AL55: =AK55/VLOOKUP(Q55,[1]Yield!$E$5:$F$14,2,FALSE) -> 14.813559 | AO55: =ROUND((+AL55*13.1*1000000)/2000,-3) -> 97000 | AP55: Rotary Dryer | AQ55: =IF(G55="POET Biorefining",G55,IF(T55="FQPT HI Pro",T55,IF(Z55="ICM FOT",Z55,IF(Q55="ICM",Q55,IF(Q55="ADM",Q55,"None"))))) -> ICM | AR55: =VLOOKUP(AQ55,[1]Yield!$A$5:$B$10,2,FALSE) -> 0.9 | AS55: =(AL55)*AR55 -> 13.332203 | AT55: Likely | AX55: =IFERROR(VLOOKUP(E55,[1]Sheet3!$C$2:$E$68,2,FALSE),"None") -> None | AY55: =IFERROR(VLOOKUP(AX55,[1]Sheet3!$H$3:$I$5,2,FALSE),0) -> 0 | AZ55: =AJ55 -> 46 | BA55: =+AJ55*6.85*0.48/2 -> 75.624 | BD55: https://www.frontrangeenergy.com/ | BE55: UP/BNSF | BF55: No | BK55: =IF(M55=2,10,5)+IF(Q55="ICM",10,5)+IF(X55="Y",10,5) -> 20
A56: 55 | B56: 4764 | C56: 70221 | D56: 2900 | E56: 3604 | F56: =IF(A56<300,"Active","Retired") -> Active | G56: Glacial Lakes Cooperative | H56: =VLOOKUP(E56,'[1]EPA Ethanol Capacity 2024'!$B$5:$C$235,2,FALSE) -> Hub City Energy LLC | I56: SD | J56: Aberdeen | K56: 57401 | L56: Brown | M56: 2 | N56: 45.459444 | O56: -98.542789 | P56: 2007 | Q56: ICM | R56: =COUNTIF(G:G,"="&G56) -> 4 | S56: EP3 | AB56: Corn | AC56: D6 | AD56: Website | AE56: =IF(BK56=1,"Low","High") -> High | AJ56: =VLOOKUP(E56,'[1]Ethanol Plant Listing 2025'!$B$3:$E$220,4,FALSE) -> 70 | AK56: =+AJ56*[1]Yield!$K$4 -> 66.5 | AL56: =AK56/VLOOKUP(Q56,[1]Yield!$E$5:$F$14,2,FALSE) -> 22.542373 | AO56: =ROUND((+AL56*13.1*1000000)/2000,-3) -> 148000 | AP56: Rotary Dryer | AQ56: =IF(G56="POET Biorefining",G56,IF(T56="FQPT HI Pro",T56,IF(Z56="ICM FOT",Z56,IF(Q56="ICM",Q56,IF(Q56="ADM",Q56,"None"))))) -> ICM | AR56: =VLOOKUP(AQ56,[1]Yield!$A$5:$B$10,2,FALSE) -> 0.9 | AS56: =(AL56)*AR56 -> 20.288136 | AT56: Y | AX56: =IFERROR(VLOOKUP(E56,[1]Sheet3!$C$2:$E$68,2,FALSE),"None") -> None | AY56: =IFERROR(VLOOKUP(AX56,[1]Sheet3!$H$3:$I$5,2,FALSE),0) -> 0 | AZ56: =AJ56 -> 70 | BA56: =+AJ56*6.85*0.48/2 -> 115.08 | BC56: Y | BD56: http://www.glaciallakesenergy.com/index.htm | BE56: BNSF | BF56: No | BG56: Yes | BI56: Importer | BK56: =IF(M56=2,10,5)+IF(Q56="ICM",10,5)+IF(X56="Y",10,5) -> 25
A57: 56 | B57: 4764 | C57: 70722 | D57: 2901 | E57: 3605 | F57: =IF(A57<300,"Active","Retired") -> Active | G57: Glacial Lakes Cooperative | H57: =VLOOKUP(E57,'[1]EPA Ethanol Capacity 2024'!$B$5:$C$235,2,FALSE) -> Huron Energy LLC | I57: SD | J57: Huron | K57: 57350 | L57: Beadle | M57: 2 | N57: 44.374508 | O57: -98.253288 | P57: 1998 | Q57: ICM | R57: =COUNTIF(G:G,"="&G57) -> 4 | S57: EP3 | AB57: Corn | AC57: D6 | AD57: Website | AE57: =IF(BK57=1,"Low","High") -> High | AJ57: =VLOOKUP(E57,'[1]Ethanol Plant Listing 2025'!$B$3:$E$220,4,FALSE) -> 60 | AK57: =+AJ57*[1]Yield!$K$4 -> 57 | AL57: =AK57/VLOOKUP(Q57,[1]Yield!$E$5:$F$14,2,FALSE) -> 19.322034 | AO57: =ROUND((+AL57*13.1*1000000)/2000,-3) -> 127000 | AP57: Rotary Dryer | AQ57: =IF(G57="POET Biorefining",G57,IF(T57="FQPT HI Pro",T57,IF(Z57="ICM FOT",Z57,IF(Q57="ICM",Q57,IF(Q57="ADM",Q57,"None"))))) -> ICM | AR57: =VLOOKUP(AQ57,[1]Yield!$A$5:$B$10,2,FALSE) -> 0.9 | AS57: =(AL57)*AR57 -> 17.389831 | AT57: Y | AX57: =IFERROR(VLOOKUP(E57,[1]Sheet3!$C$2:$E$68,2,FALSE),"None") -> None | AY57: =IFERROR(VLOOKUP(AX57,[1]Sheet3!$H$3:$I$5,2,FALSE),0) -> 0 | AZ57: =AJ57 -> 60 | BA57: =+AJ57*6.85*0.48/2 -> 98.64 | BC57: Y | BD57: http://www.glaciallakesenergy.com/index.htm | BE57: RCPE/BNSF/CP | BF57: No | BK57: =IF(M57=2,10,5)+IF(Q57="ICM",10,5)+IF(X57="Y",10,5) -> 25 | BL57: 12/2019 GLE purchases from Advance Bio for $47.5M
A58: 57 | B58: 4764 | C58: 70799 | D58: 3179 | E58: 3606 | F58: =IF(A58<300,"Active","Retired") -> Active | G58: Glacial Lakes Cooperative | H58: =VLOOKUP(E58,'[1]EPA Ethanol Capacity 2024'!$B$5:$C$235,2,FALSE) -> Glacial Lakes Energy | I58: SD | J58: Mina | K58: 57451 | L58: Edmunds | M58: 2 | N58: 45.442417 | O58: -98.787139 | P58: 2008 | Q58: ICM | R58: =COUNTIF(G:G,"="&G58) -> 4 | X58: White Fox ICE | AB58: Corn | AC58: D6 | AD58: Website | AE58: =IF(BK58=1,"Low","High") -> High | AJ58: =VLOOKUP(E58,'[1]Ethanol Plant Listing 2025'!$B$3:$E$220,4,FALSE) -> 162 | AK58: =+AJ58*[1]Yield!$K$4 -> 153.9 | AL58: =AK58/VLOOKUP(Q58,[1]Yield!$E$5:$F$14,2,FALSE) -> 52.169492 | AO58: =ROUND((+AL58*13.1*1000000)/2000,-3) -> 342000 | AP58: Rotary Dryer | AQ58: =IF(G58="POET Biorefining",G58,IF(T58="FQPT HI Pro",T58,IF(Z58="ICM FOT",Z58,IF(Q58="ICM",Q58,IF(Q58="ADM",Q58,"None"))))) -> ICM | AR58: =VLOOKUP(AQ58,[1]Yield!$A$5:$B$10,2,FALSE) -> 0.9 | AS58: =(AL58)*AR58 -> 46.952542 | AT58: Y | AX58: =IFERROR(VLOOKUP(E58,[1]Sheet3!$C$2:$E$68,2,FALSE),"None") -> None | AY58: =IFERROR(VLOOKUP(AX58,[1]Sheet3!$H$3:$I$5,2,FALSE),0) -> 0 | AZ58: =AJ58 -> 162 | BA58: =+AJ58*6.85*0.48/2 -> 266.328 | BC58: Y | BD58: http://www.glaciallakesenergy.com/index.htm | BE58: BNSF | BF58: Yes | BK58: =IF(M58=2,10,5)+IF(Q58="ICM",10,5)+IF(X58="Y",10,5) -> 25 | BL58: 12/2019 GLE purchases from Advance Bio for $47.5M
A59: 58 | B59: 4764 | C59: 70064 | D59: 3180 | E59: 3607 | F59: =IF(A59<300,"Active","Retired") -> Active | G59: Glacial Lakes Cooperative | H59: =VLOOKUP(E59,'[1]EPA Ethanol Capacity 2024'!$B$5:$C$235,2,FALSE) -> Glacial Lakes Energy | I59: SD | J59: Watertown | K59: 57201 | L59: Codington | M59: 2 | N59: 44.87624 | O59: -97.11367 | P59: 2002 | Q59: ICM | R59: =COUNTIF(G:G,"="&G59) -> 4 | S59: EP3 | AB59: Corn | AC59: D6 | AD59: Website | AE59: =IF(BK59=1,"Low","High") -> High | AJ59: =VLOOKUP(E59,'[1]Ethanol Plant Listing 2025'!$B$3:$E$220,4,FALSE) -> 148 | AK59: =+AJ59*[1]Yield!$K$4 -> 140.6 | AL59: =AK59/VLOOKUP(Q59,[1]Yield!$E$5:$F$14,2,FALSE) -> 47.661017 | AO59: =ROUND((+AL59*13.1*1000000)/2000,-3) -> 312000 | AP59: Rotary Dryer | AQ59: =IF(G59="POET Biorefining",G59,IF(T59="FQPT HI Pro",T59,IF(Z59="ICM FOT",Z59,IF(Q59="ICM",Q59,IF(Q59="ADM",Q59,"None"))))) -> ICM | AR59: =VLOOKUP(AQ59,[1]Yield!$A$5:$B$10,2,FALSE) -> 0.9 | AS59: =(AL59)*AR59 -> 42.894915 | AT59: Y | AX59: =IFERROR(VLOOKUP(E59,[1]Sheet3!$C$2:$E$68,2,FALSE),"None") -> None | AY59: =IFERROR(VLOOKUP(AX59,[1]Sheet3!$H$3:$I$5,2,FALSE),0) -> 0 | AZ59: =AJ59 -> 148 | BA59: =+AJ59*6.85*0.48/2 -> 243.312 | BC59: Y | BD59: http://www.glaciallakesenergy.com/index.htm | BE59: BNSF | BF59: Yes | BK59: =IF(M59=2,10,5)+IF(Q59="ICM",10,5)+IF(X59="Y",10,5) -> 25
A60: 59 | B60: 4829 | C60: 70691 | D60: 3181 | E60: 3608 | F60: =IF(A60<300,"Active","Retired") -> Active | G60: Golden Grain Energy | H60: =VLOOKUP(E60,'[1]EPA Ethanol Capacity 2024'!$B$5:$C$235,2,FALSE) -> Golden Grain Energy LLC | I60: IA | J60: Mason City | K60: 50401 | L60: Cerro Gordo | M60: 2 | N60: 43.11204 | O60: -93.23104 | P60: 2004 | Q60: ICM | R60: =COUNTIF(G:G,"="&G60) -> 1 | T60: ICM HI PRO | X60: White Fox ICE | AB60: Corn | AC60: D6 | AD60: Website | AE60: =IF(BK60=1,"Low","High") -> High | AJ60: =VLOOKUP(E60,'[1]Ethanol Plant Listing 2025'!$B$3:$E$220,4,FALSE) -> 140 | AK60: =+AJ60*[1]Yield!$K$4 -> 133 | AL60: =AK60/VLOOKUP(Q60,[1]Yield!$E$5:$F$14,2,FALSE) -> 45.084746 | AO60: =ROUND((+AL60*13.1*1000000)/2000,-3) -> 295000 | AP60: Rotary Dryer | AQ60: =IF(G60="POET Biorefining",G60,IF(T60="FQPT HI Pro",T60,IF(Z60="ICM FOT",Z60,IF(Q60="ICM",Q60,IF(Q60="ADM",Q60,"None"))))) -> ICM | AR60: =VLOOKUP(AQ60,[1]Yield!$A$5:$B$10,2,FALSE) -> 0.9 | AS60: =(AL60)*AR60 -> 40.576271 | AT60: Y | AV60: SCS | AX60: =IFERROR(VLOOKUP(E60,[1]Sheet3!$C$2:$E$68,2,FALSE),"None") -> Summit Carbon Solutions | AY60: =IFERROR(VLOOKUP(AX60,[1]Sheet3!$H$3:$I$5,2,FALSE),0) -> 31 | AZ60: =AJ60 -> 140 | BA60: =+AJ60*6.85*0.48/2 -> 230.16 | BB60: =SUMIFS('[1]Corn 2023'!V:V,'[1]Corn 2023'!B:B,"=2023",'[1]Corn 2023'!L:L,"="&'Corn Processors'!L60) -> 0 | BD60: https://ggecorn.com/ | BE60: UP | BF60: Yes | BI60: Importer | BJ60: Member | BK60: =IF(M60=2,10,5)+IF(Q60="ICM",10,5)+IF(X60="Y",10,5) -> 25
A61: 60 | D61: 3182 | E61: 3609 | F61: =IF(A61<300,"Active","Retired") -> Active | G61: Grain Processing Corp | H61: =VLOOKUP(E61,'[1]EPA Ethanol Capacity 2024'!$B$5:$C$235,2,FALSE) -> Grain Processing Corp | I61: IA | J61: Muscatine | K61: 52761 | L61: Muscatine | M61: 2 | N61: 41.400401 | O61: -91.062989 | P61: 0 | Q61: Wet Mill | R61: =COUNTIF(G:G,"="&G61) -> 2 | X61: White Fox ICE | AB61: Corn | AC61: D6 | AD61: Website | AE61: =IF(BK61=1,"Low","High") -> High | AF61: 157.5 | AG61: 150 | AH61: 03-A-607 | AJ61: =VLOOKUP(E61,'[1]Ethanol Plant Listing 2025'!$B$3:$E$220,4,FALSE) -> 82.5 | AK61: =+AJ61*[1]Yield!$K$4 -> 78.375 | AL61: =AK61/VLOOKUP(Q61,[1]Yield!$E$5:$F$14,2,FALSE) -> 28.5 | AO61: =ROUND((+AL61*13.1*1000000)/2000,-3) -> 187000 | AQ61: =IF(G61="POET Biorefining",G61,IF(T61="FQPT HI Pro",T61,IF(Z61="ICM FOT",Z61,IF(Q61="ICM",Q61,IF(Q61="ADM",Q61,"None"))))) -> None | AR61: =VLOOKUP(AQ61,[1]Yield!$A$5:$B$10,2,FALSE) -> 0.815 | AS61: =(AL61)*AR61 -> 23.2275 | AT61: Likely | AX61: =IFERROR(VLOOKUP(E61,[1]Sheet3!$C$2:$E$68,2,FALSE),"None") -> None | AY61: =IFERROR(VLOOKUP(AX61,[1]Sheet3!$H$3:$I$5,2,FALSE),0) -> 0 | AZ61: =AJ61 -> 82.5 | BA61: =+AJ61*6.85*0.48/2 -> 135.63 | BB61: =SUMIFS('[1]Corn 2023'!V:V,'[1]Corn 2023'!B:B,"=2023",'[1]Corn 2023'!L:L,"="&'Corn Processors'!L61) -> 88700 | BD61: https://www.grainprocessing.com/ | BE61: CP | BF61: Yes | BJ61: Member | BK61: =IF(M61=2,10,5)+IF(Q61="ICM",10,5)+IF(X61="Y",10,5) -> 20
A62: 61 | D62: 3183 | E62: 3610 | F62: =IF(A62<300,"Active","Retired") -> Active | G62: Grain Processing Corp | H62: =VLOOKUP(E62,'[1]EPA Ethanol Capacity 2024'!$B$5:$C$235,2,FALSE) -> Grain Processing Corp | I62: IN | J62: Washington | K62: 47501 | L62: Daviess | M62: 2 | N62: 38.635926 | O62: -87.224466 | P62: 0 | Q62: Wet Mill | R62: =COUNTIF(G:G,"="&G62) -> 2 | AB62: Corn | AC62: D6 | AD62: Website | AE62: =IF(BK62=1,"Low","High") -> High | AJ62: =VLOOKUP(E62,'[1]Ethanol Plant Listing 2025'!$B$3:$E$220,4,FALSE) -> 36.72 | AK62: =+AJ62*[1]Yield!$K$4 -> 34.884 | AL62: =AK62/VLOOKUP(Q62,[1]Yield!$E$5:$F$14,2,FALSE) -> 12.685091 | AO62: =ROUND((+AL62*13.1*1000000)/2000,-3) -> 83000 | AQ62: =IF(G62="POET Biorefining",G62,IF(T62="FQPT HI Pro",T62,IF(Z62="ICM FOT",Z62,IF(Q62="ICM",Q62,IF(Q62="ADM",Q62,"None"))))) -> None | AR62: =VLOOKUP(AQ62,[1]Yield!$A$5:$B$10,2,FALSE) -> 0.815 | AS62: =(AL62)*AR62 -> 10.338349 | AT62: Likely | AX62: =IFERROR(VLOOKUP(E62,[1]Sheet3!$C$2:$E$68,2,FALSE),"None") -> None | AY62: =IFERROR(VLOOKUP(AX62,[1]Sheet3!$H$3:$I$5,2,FALSE),0) -> 0 | AZ62: =AJ62 -> 36.72 | BA62: =+AJ62*6.85*0.48/2 -> 60.36768 | BD62: https://www.grainprocessing.com/ | BE62: CSX | BF62: Yes | BJ62: Member | BK62: =IF(M62=2,10,5)+IF(Q62="ICM",10,5)+IF(X62="Y",10,5) -> 20
A63: 62 | C63: 70071 | D63: 3184 | E63: 3611 | F63: =IF(A63<300,"Active","Retired") -> Active | G63: Granite Falls Energy | H63: =VLOOKUP(E63,'[1]EPA Ethanol Capacity 2024'!$B$5:$C$235,2,FALSE) -> Granite Falls Energy LLC | I63: MN | J63: Granite Falls | K63: 56241 | L63: Yellow Medicine | M63: 2 | N63: 44.7999 | O63: -95.4869 | P63: 2005 | Q63: ICM | R63: =COUNTIF(G:G,"="&G63) -> 2 | S63: EP3 | AB63: Corn | AC63: D6 | AD63: Website | AE63: =IF(BK63=1,"Low","High") -> High | AJ63: =VLOOKUP(E63,'[1]Ethanol Plant Listing 2025'!$B$3:$E$220,4,FALSE) -> 63 | AK63: =+AJ63*[1]Yield!$K$4 -> 59.85 | AL63: =AK63/VLOOKUP(Q63,[1]Yield!$E$5:$F$14,2,FALSE) -> 20.288136 | AO63: =ROUND((+AL63*13.1*1000000)/2000,-3) -> 133000 | AP63: Rotary Dryer | AQ63: =IF(G63="POET Biorefining",G63,IF(T63="FQPT HI Pro",T63,IF(Z63="ICM FOT",Z63,IF(Q63="ICM",Q63,IF(Q63="ADM",Q63,"None"))))) -> ICM | AR63: =VLOOKUP(AQ63,[1]Yield!$A$5:$B$10,2,FALSE) -> 0.9 | AS63: =(AL63)*AR63 -> 18.259322 | AT63: Y | AX63: =IFERROR(VLOOKUP(E63,[1]Sheet3!$C$2:$E$68,2,FALSE),"None") -> Summit Carbon Solutions | AY63: =IFERROR(VLOOKUP(AX63,[1]Sheet3!$H$3:$I$5,2,FALSE),0) -> 31 | AZ63: =AJ63 -> 63 | BA63: =+AJ63*6.85*0.48/2 -> 103.572 | BD63: http://www.granitefallsenergy.com/ | BE63: TC&W/BNSF/CP/UP/CN | BF63: Yes | BJ63: Member | BK63: =IF(M63=2,10,5)+IF(Q63="ICM",10,5)+IF(X63="Y",10,5) -> 25
A64: 63 | C64: 73561 | D64: 3186 | E64: 3613 | F64: =IF(A64<300,"Active","Retired") -> Active | G64: Husker Ag | H64: =VLOOKUP(E64,'[1]EPA Ethanol Capacity 2024'!$B$5:$C$235,2,FALSE) -> Sandhills Renewable Energy LLC | I64: NE | J64: Atkinson | K64: 68713 | L64: Holt | M64: 2 | N64: 42.51899 | O64: -98.9596 | P64: 2008 | Q64: Delta-T | R64: =COUNTIF(G:G,"="&G64) -> 2 | S64: EP3 | AA64: ICM P10 | AB64: Corn | AC64: D6 | AD64: Website | AE64: =IF(BK64=1,"Low","High") -> High | AJ64: =VLOOKUP(E64,'[1]Ethanol Plant Listing 2025'!$B$3:$E$220,4,FALSE) -> 52.5 | AK64: =+AJ64*[1]Yield!$K$4 -> 49.875 | AL64: =AK64/VLOOKUP(Q64,[1]Yield!$E$5:$F$14,2,FALSE) -> 17.317708 | AM64: 5109 | AN64: =+AM64/(AL64*2.85714285714286) -> 103.25558 | AO64: =ROUND((+AL64*13.1*1000000)/2000,-3) -> 113000 | AP64: Ring Dryer | AQ64: =IF(G64="POET Biorefining",G64,IF(T64="FQPT HI Pro",T64,IF(Z64="ICM FOT",Z64,IF(Q64="ICM",Q64,IF(Q64="ADM",Q64,"None"))))) -> None | AR64: =VLOOKUP(AQ64,[1]Yield!$A$5:$B$10,2,FALSE) -> 0.815 | AS64: =(AL64)*AR64 -> 14.113932 | AT64: Y | AX64: =IFERROR(VLOOKUP(E64,[1]Sheet3!$C$2:$E$68,2,FALSE),"None") -> None | AY64: =IFERROR(VLOOKUP(AX64,[1]Sheet3!$H$3:$I$5,2,FALSE),0) -> 0 | AZ64: =AJ64 -> 52.5 | BA64: =+AJ64*6.85*0.48/2 -> 86.31 | BC64: Y | BD64: https://gpreinc.com/ | BE64: BNSF | BF64: No | BJ64: Member | BK64: =IF(M64=2,10,5)+IF(Q64="ICM",10,5)+IF(X64="Y",10,5) -> 20
A65: 64 | B65: 3368 | C65: 70141 | D65: 3187 | E65: 3614 | F65: =IF(A65<300,"Active","Retired") -> Active | G65: Green Plains | H65: =VLOOKUP(E65,'[1]EPA Ethanol Capacity 2024'!$B$5:$C$235,2,FALSE) -> Green Plains Central City LLC | I65: NE | J65: Central City | K65: 68826 | L65: Merrick | M65: 2 | N65: 41.1111 | O65: -97.9727 | P65: 2004 | Q65: ICM | R65: =COUNTIF(G:G,"="&G65) -> 11 | S65: EP3 | T65: FQPT HI PRO | Z65: =+T65 -> FQPT HI PRO | AB65: Corn | AC65: D6 | AD65: Website | AE65: =IF(BK65=1,"Low","High") -> High | AF65: 52.5 | AG65: 52.5 | AH65: AIR>CONSTRUCTION | AI65: 86416 | AJ65: =VLOOKUP(E65,'[1]Ethanol Plant Listing 2025'!$B$3:$E$220,4,FALSE) -> 135 | AK65: =+AJ65*[1]Yield!$K$4 -> 128.25 | AL65: =AK65/VLOOKUP(Q65,[1]Yield!$E$5:$F$14,2,FALSE) -> 43.474576 | AM65: 1400 | AN65: =+AM65/(AL65*2.85714285714286) -> 11.270955 | AO65: =ROUND((+AL65*13.1*1000000)/2000,-3) -> 285000 | AP65: Rotary Dryer | AQ65: =IF(G65="POET Biorefining",G65,IF(T65="FQPT HI Pro",T65,IF(Z65="ICM FOT",Z65,IF(Q65="ICM",Q65,IF(Q65="ADM",Q65,"None"))))) -> FQPT HI PRO | AR65: =VLOOKUP(AQ65,[1]Yield!$A$5:$B$10,2,FALSE) -> 1.05 | AS65: =(AL65)*AR65 -> 45.648305 | AT65: Y | AV65: =+AX65 -> Tall Grass | AX65: =IFERROR(VLOOKUP(E65,[1]Sheet3!$C$2:$E$68,2,FALSE),"None") -> Tall Grass | AY65: =IFERROR(VLOOKUP(AX65,[1]Sheet3!$H$3:$I$5,2,FALSE),0) -> 30 | AZ65: =AJ65 -> 135 | BA65: =+AJ65*6.85*0.48/2 -> 221.94 | BC65: Y | BD65: https://gpreinc.com/ | BE65: UP | BF65: Yes | BK65: =IF(M65=2,10,5)+IF(Q65="ICM",10,5)+IF(X65="Y",10,5) -> 25
A66: 65 | D66: 3188 | E66: 3615 | F66: =IF(A66<300,"Active","Retired") -> Active | G66: Green Plains | H66: =VLOOKUP(E66,'[1]EPA Ethanol Capacity 2024'!$B$5:$C$235,2,FALSE) -> Green Plains Fairmont LLC | I66: MN | J66: Fairmont | K66: 56031 | L66: Martin | M66: 2 | N66: 43.664021 | O66: -94.492559 | P66: 2008 | Q66: Delta-T | R66: =COUNTIF(G:G,"="&G66) -> 11 | AA66: ICM P10 | AB66: Corn | AC66: D6 | AD66: Website | AE66: =IF(BK66=1,"Low","High") -> High | AF66: 135 | AG66: 100 | AH66: AIR>CONSTRUCTION | AI66: 82836 | AJ66: =VLOOKUP(E66,'[1]Ethanol Plant Listing 2025'!$B$3:$E$220,4,FALSE) -> 122.9 | AK66: =+AJ66*[1]Yield!$K$4 -> 116.755 | AL66: =AK66/VLOOKUP(Q66,[1]Yield!$E$5:$F$14,2,FALSE) -> 40.539931 | AM66: 1611 | AN66: =+AM66/(AL66*2.85714285714286) -> 13.908509 | AO66: =ROUND((+AL66*13.1*1000000)/2000,-3) -> 266000 | AP66: Ring Dryer | AQ66: =IF(G66="POET Biorefining",G66,IF(T66="FQPT HI Pro",T66,IF(Z66="ICM FOT",Z66,IF(Q66="ICM",Q66,IF(Q66="ADM",Q66,"None"))))) -> None | AR66: =VLOOKUP(AQ66,[1]Yield!$A$5:$B$10,2,FALSE) -> 0.815 | AS66: =(AL66)*AR66 -> 33.040043 | AT66: Y | AX66: =IFERROR(VLOOKUP(E66,[1]Sheet3!$C$2:$E$68,2,FALSE),"None") -> Summit Carbon Solutions | AY66: =IFERROR(VLOOKUP(AX66,[1]Sheet3!$H$3:$I$5,2,FALSE),0) -> 31 | AZ66: =AJ66 -> 122.9 | BA66: =+AJ66*6.85*0.48/2 -> 202.0476 | BC66: Y | BD66: https://gpreinc.com/ | BE66: UP | BF66: Yes | BK66: =IF(M66=2,10,5)+IF(Q66="ICM",10,5)+IF(X66="Y",10,5) -> 20
A67: 66 | D67: 3189 | E67: 3616 | F67: =IF(A67<300,"Active","Retired") -> Active | G67: Green Plains | H67: =VLOOKUP(E67,'[1]EPA Ethanol Capacity 2024'!$B$5:$C$235,2,FALSE) -> Green Plains Madison LLC | I67: IL | J67: Madison | K67: 62060 | L67: Madison | M67: 2 | N67: 38.67995 | O67: -90.17185 | P67: 2009 | Q67: Vogelbusch | R67: =COUNTIF(G:G,"="&G67) -> 11 | S67: EP3 | AA67: ICM P10 | AB67: Corn | AC67: D6 | AD67: https://grain.gpreinc.com/index.cfm?show=11&mid=3&theLocation=17&layout=19 | AE67: =IF(BK67=1,"Low","High") -> High | AG67: 122.9 | AJ67: =VLOOKUP(E67,'[1]Ethanol Plant Listing 2025'!$B$3:$E$220,4,FALSE) -> 100 | AK67: =+AJ67*[1]Yield!$K$4 -> 95 | AL67: =AK67/VLOOKUP(Q67,[1]Yield!$E$5:$F$14,2,FALSE) -> 32.758621 | AM67: 1015 | AN67: =+AM67/(AL67*2.85714285714286) -> 10.844474 | AO67: =ROUND((+AL67*13.1*1000000)/2000,-3) -> 215000 | AP67: Rotary Dryer | AQ67: =IF(G67="POET Biorefining",G67,IF(T67="FQPT HI Pro",T67,IF(Z67="ICM FOT",Z67,IF(Q67="ICM",Q67,IF(Q67="ADM",Q67,"None"))))) -> None | AR67: =VLOOKUP(AQ67,[1]Yield!$A$5:$B$10,2,FALSE) -> 0.815 | AS67: =(AL67)*AR67 -> 26.698276 | AT67: Likely | AX67: =IFERROR(VLOOKUP(E67,[1]Sheet3!$C$2:$E$68,2,FALSE),"None") -> None | AY67: =IFERROR(VLOOKUP(AX67,[1]Sheet3!$H$3:$I$5,2,FALSE),0) -> 0 | AZ67: =AJ67 -> 100 | BA67: =+AJ67*6.85*0.48/2 -> 164.4 | BC67: Y | BD67: https://gpreinc.com/ | BE67: PH/BNSF/UP/CN/NS | BF67: Yes | BK67: =IF(M67=2,10,5)+IF(Q67="ICM",10,5)+IF(X67="Y",10,5) -> 20
A68: 67 | D68: 3190 | E68: 3617 | F68: =IF(A68<300,"Active","Retired") -> Active | G68: Green Plains | H68: =VLOOKUP(E68,'[1]EPA Ethanol Capacity 2024'!$B$5:$C$235,2,FALSE) -> Green Plains Mount Vernon LLC | I68: IN | J68: Mount Vernon | K68: 47620 | L68: Posey | M68: 2 | N68: 37.9082 | O68: -87.7257 | P68: 2009 | Q68: Vogelbusch | R68: =COUNTIF(G:G,"="&G68) -> 11 | T68: FQPT HI PRO | Z68: =+T68 -> FQPT HI PRO | AA68: ICM P10 | AB68: Corn | AC68: D6 | AD68: Website | AE68: =IF(BK68=1,"Low","High") -> High | AG68: 110 | AJ68: =VLOOKUP(E68,'[1]Ethanol Plant Listing 2025'!$B$3:$E$220,4,FALSE) -> 135 | AK68: =+AJ68*[1]Yield!$K$4 -> 128.25 | AL68: =AK68/VLOOKUP(Q68,[1]Yield!$E$5:$F$14,2,FALSE) -> 44.224138 | AM68: 1034 | AN68: =+AM68/(AL68*2.85714285714286) -> 8.1833138 | AO68: =ROUND((+AL68*13.1*1000000)/2000,-3) -> 290000 | AQ68: =IF(G68="POET Biorefining",G68,IF(T68="FQPT HI Pro",T68,IF(Z68="ICM FOT",Z68,IF(Q68="ICM",Q68,IF(Q68="ADM",Q68,"None"))))) -> FQPT HI PRO | AR68: =VLOOKUP(AQ68,[1]Yield!$A$5:$B$10,2,FALSE) -> 1.05 | AS68: =(AL68)*AR68 -> 46.435345 | AT68: Likely | AX68: =IFERROR(VLOOKUP(E68,[1]Sheet3!$C$2:$E$68,2,FALSE),"None") -> None | AY68: =IFERROR(VLOOKUP(AX68,[1]Sheet3!$H$3:$I$5,2,FALSE),0) -> 0 | AZ68: =AJ68 -> 135 | BA68: =+AJ68*6.85*0.48/2 -> 221.94 | BC68: Y | BD68: https://gpreinc.com/ | BE68: CSX | BF68: Yes | BH68: Barge | BK68: =IF(M68=2,10,5)+IF(Q68="ICM",10,5)+IF(X68="Y",10,5) -> 20 | BL68: 9/26/16 GP purchases from Abengoa for $237M
A69: 68 | D69: 3191 | E69: 3618 | F69: =IF(A69<300,"Active","Retired") -> Active | G69: Green Plains | H69: Poet Biorefining-Obion LLC | I69: TN | J69: Rives | K69: 38253 | L69: Obion | M69: 2 | N69: 36.28305 | O69: -89.147607 | P69: 2008 | Q69: ICM | R69: =COUNTIF(G:G,"="&G69) -> 11 | S69: EP3 | T69: FQPT HI PRO | Z69: =+T69 -> FQPT HI PRO | AB69: Corn | AC69: D6 | AD69: Website | AE69: =IF(BK69=1,"Low","High") -> High | AG69: 110 | AJ69: =VLOOKUP(E69,'[1]Ethanol Plant Listing 2025'!$B$3:$E$220,4,FALSE) -> 135 | AK69: =+AJ69*[1]Yield!$K$4 -> 128.25 | AL69: =AK69/VLOOKUP(Q69,[1]Yield!$E$5:$F$14,2,FALSE) -> 43.474576 | AM69: 8168 | AN69: =+AM69/(AL69*2.85714285714286) -> 65.757973 | AO69: =ROUND((+AL69*13.1*1000000)/2000,-3) -> 285000 | AP69: Rotary Dryer | AQ69: =IF(G69="POET Biorefining",G69,IF(T69="FQPT HI Pro",T69,IF(Z69="ICM FOT",Z69,IF(Q69="ICM",Q69,IF(Q69="ADM",Q69,"None"))))) -> FQPT HI PRO | AR69: =VLOOKUP(AQ69,[1]Yield!$A$5:$B$10,2,FALSE) -> 1.05 | AS69: =(AL69)*AR69 -> 45.648305 | AT69: Likely | AX69: =IFERROR(VLOOKUP(E69,[1]Sheet3!$C$2:$E$68,2,FALSE),"None") -> None | AY69: =IFERROR(VLOOKUP(AX69,[1]Sheet3!$H$3:$I$5,2,FALSE),0) -> 0 | AZ69: =AJ69 -> 135 | BA69: =+AJ69*6.85*0.48/2 -> 221.94 | BC69: Y | BD69: https://gpreinc.com/ | BE69: CN | BF69: Yes | BK69: =IF(M69=2,10,5)+IF(Q69="ICM",10,5)+IF(X69="Y",10,5) -> 25 | BL69: 9/26/16 GP purchases from Abengoa for $237M
A70: 69 | C70: 70110 | D70: 3192 | E70: 3619 | F70: =IF(A70<300,"Active","Retired") -> Active | G70: Green Plains | H70: =VLOOKUP(E70,'[1]EPA Ethanol Capacity 2024'!$B$5:$C$235,2,FALSE) -> Green Plains Otter Tail LLC | I70: MN | J70: Otter Tail | K70: 56537 | L70: Otter Tail | M70: 2 | N70: 46.3125 | O70: -96.1337 | P70: 2008 | Q70: Delta-T | R70: =COUNTIF(G:G,"="&G70) -> 11 | AA70: ICM P10 | AB70: Corn | AC70: D6 | AD70: Website | AE70: =IF(BK70=1,"Low","High") -> High | AF70: EP3 | AG70: EP3 | AJ70: =VLOOKUP(E70,'[1]Ethanol Plant Listing 2025'!$B$3:$E$220,4,FALSE) -> 66.6 | AK70: =+AJ70*[1]Yield!$K$4 -> 63.27 | AL70: =AK70/VLOOKUP(Q70,[1]Yield!$E$5:$F$14,2,FALSE) -> 21.96875 | AM70: 628 | AN70: =+AM70/(AL70*2.85714285714286) -> 10.005121 | AO70: =ROUND((+AL70*13.1*1000000)/2000,-3) -> 144000 | AP70: Ring Dryer | AQ70: =IF(G70="POET Biorefining",G70,IF(T70="FQPT HI Pro",T70,IF(Z70="ICM FOT",Z70,IF(Q70="ICM",Q70,IF(Q70="ADM",Q70,"None"))))) -> None | AR70: =VLOOKUP(AQ70,[1]Yield!$A$5:$B$10,2,FALSE) -> 0.815 | AS70: =(AL70)*AR70 -> 17.904531 | AT70: Y | AX70: =IFERROR(VLOOKUP(E70,[1]Sheet3!$C$2:$E$68,2,FALSE),"None") -> Summit Carbon Solutions | AY70: =IFERROR(VLOOKUP(AX70,[1]Sheet3!$H$3:$I$5,2,FALSE),0) -> 31 | AZ70: =AJ70 -> 66.6 | BA70: =+AJ70*6.85*0.48/2 -> 109.4904 | BC70: Y | BD70: https://gpreinc.com/ | BE70: BNSF | BF70: Yes | BK70: =IF(M70=2,10,5)+IF(Q70="ICM",10,5)+IF(X70="Y",10,5) -> 20
A71: 70 | D71: 3193 | E71: 3620 | F71: =IF(A71<300,"Active","Retired") -> Active | G71: Green Plains | H71: =VLOOKUP(E71,'[1]EPA Ethanol Capacity 2024'!$B$5:$C$235,2,FALSE) -> Green Plains Shenandoah LLC | I71: IA | J71: Shenandoah | K71: 51601 | L71: Page | M71: 2 | N71: 40.7549 | O71: -95.3953 | P71: 2007 | Q71: ICM | R71: =COUNTIF(G:G,"="&G71) -> 11 | S71: EP3 | T71: FQPT HI PRO | Z71: =+T71 -> FQPT HI PRO | AB71: Corn | AC71: D6 | AD71: Website | AE71: =IF(BK71=1,"Low","High") -> High | AG71: 65 | AJ71: =VLOOKUP(E71,'[1]Ethanol Plant Listing 2025'!$B$3:$E$220,4,FALSE) -> 100 | AK71: =+AJ71*[1]Yield!$K$4 -> 95 | AL71: =AK71/VLOOKUP(Q71,[1]Yield!$E$5:$F$14,2,FALSE) -> 32.20339 | AM71: 886 | AN71: =+AM71/(AL71*2.85714285714286) -> 9.6294211 | AO71: =ROUND((+AL71*13.1*1000000)/2000,-3) -> 211000 | AP71: Rotary Dryer | AQ71: =IF(G71="POET Biorefining",G71,IF(T71="FQPT HI Pro",T71,IF(Z71="ICM FOT",Z71,IF(Q71="ICM",Q71,IF(Q71="ADM",Q71,"None"))))) -> FQPT HI PRO | AR71: =VLOOKUP(AQ71,[1]Yield!$A$5:$B$10,2,FALSE) -> 1.05 | AS71: =(AL71)*AR71 -> 33.813559 | AT71: Y | AX71: =IFERROR(VLOOKUP(E71,[1]Sheet3!$C$2:$E$68,2,FALSE),"None") -> None | AY71: =IFERROR(VLOOKUP(AX71,[1]Sheet3!$H$3:$I$5,2,FALSE),0) -> 0 | AZ71: =AJ71 -> 100 | BA71: =+AJ71*6.85*0.48/2 -> 164.4 | BB71: =SUMIFS('[1]Corn 2023'!V:V,'[1]Corn 2023'!B:B,"=2023",'[1]Corn 2023'!L:L,"="&'Corn Processors'!L71) -> 112000 | BC71: Y | BD71: https://gpreinc.com/ | BE71: BNSF | BF71: No | BK71: =IF(M71=2,10,5)+IF(Q71="ICM",10,5)+IF(X71="Y",10,5) -> 25
A72: 71 | B72: 5861 | C72: 70304 | D72: 3194 | E72: 3621 | F72: =IF(A72<300,"Active","Retired") -> Active | G72: Green Plains | H72: =VLOOKUP(E72,'[1]EPA Ethanol Capacity 2024'!$B$5:$C$235,2,FALSE) -> Green Plains Superior | I72: IA | J72: Superior | K72: 51363 | L72: Dickinson | M72: 2 | N72: 43.431367 | O72: -94.95422 | P72: 2007 | Q72: Delta-T | R72: =COUNTIF(G:G,"="&G72) -> 11 | S72: EP3 | AA72: ICM P10 | AB72: Corn | AC72: D6 | AD72: Website | AE72: =IF(BK72=1,"Low","High") -> High | AF72: 100 | AG72: 63 | AH72: 06-A-346 | AJ72: =VLOOKUP(E72,'[1]Ethanol Plant Listing 2025'!$B$3:$E$220,4,FALSE) -> 68.5 | AK72: =+AJ72*[1]Yield!$K$4 -> 65.075 | AL72: =AK72/VLOOKUP(Q72,[1]Yield!$E$5:$F$14,2,FALSE) -> 22.595486 | AM72: 1770 | AN72: =+AM72/(AL72*2.85714285714286) -> 27.41698 | AO72: =ROUND((+AL72*13.1*1000000)/2000,-3) -> 148000 | AP72: Ring Dryer | AQ72: =IF(G72="POET Biorefining",G72,IF(T72="FQPT HI Pro",T72,IF(Z72="ICM FOT",Z72,IF(Q72="ICM",Q72,IF(Q72="ADM",Q72,"None"))))) -> None | AR72: =VLOOKUP(AQ72,[1]Yield!$A$5:$B$10,2,FALSE) -> 0.815 | AS72: =(AL72)*AR72 -> 18.415321 | AT72: Y | AV72: SCS | AX72: =IFERROR(VLOOKUP(E72,[1]Sheet3!$C$2:$E$68,2,FALSE),"None") -> Summit Carbon Solutions | AY72: =IFERROR(VLOOKUP(AX72,[1]Sheet3!$H$3:$I$5,2,FALSE),0) -> 31 | AZ72: =AJ72 -> 68.5 | BA72: =+AJ72*6.85*0.48/2 -> 112.614 | BB72: =SUMIFS('[1]Corn 2023'!V:V,'[1]Corn 2023'!B:B,"=2023",'[1]Corn 2023'!L:L,"="&'Corn Processors'!L72) -> 92500 | BC72: Y | BD72: https://gpreinc.com/ | BE72: UP | BF72: Yes | BK72: =IF(M72=2,10,5)+IF(Q72="ICM",10,5)+IF(X72="Y",10,5) -> 20
A73: 72 | B73: 6162 | C73: 70249 | D73: 3195 | E73: 3622 | F73: =IF(A73<300,"Active","Retired") -> Active | G73: Green Plains | H73: =VLOOKUP(E73,'[1]EPA Ethanol Capacity 2024'!$B$5:$C$235,2,FALSE) -> Green Plains Wood River LLC | I73: NE | J73: Wood River | K73: 68883 | L73: Hall | M73: 2 | N73: 40.81577 | O73: -98.60739 | P73: 2008 | Q73: Delta-T | R73: =COUNTIF(G:G,"="&G73) -> 11 | T73: FQPT HI PRO | Z73: =+T73 -> FQPT HI PRO | AA73: ICM P10 | AB73: Corn | AC73: D6 | AD73: Website | AE73: =IF(BK73=1,"Low","High") -> High | AF73: 63 | AG73: 63 | AH73: 11-A-707 | AJ73: =VLOOKUP(E73,'[1]Ethanol Plant Listing 2025'!$B$3:$E$220,4,FALSE) -> 123.9 | AK73: =+AJ73*[1]Yield!$K$4 -> 117.705 | AL73: =AK73/VLOOKUP(Q73,[1]Yield!$E$5:$F$14,2,FALSE) -> 40.869792 | AM73: 3293 | AN73: =+AM73/(AL73*2.85714285714286) -> 28.200535 | AO73: =ROUND((+AL73*13.1*1000000)/2000,-3) -> 268000 | AP73: Ring Dryer | AQ73: =IF(G73="POET Biorefining",G73,IF(T73="FQPT HI Pro",T73,IF(Z73="ICM FOT",Z73,IF(Q73="ICM",Q73,IF(Q73="ADM",Q73,"None"))))) -> FQPT HI PRO | AR73: =VLOOKUP(AQ73,[1]Yield!$A$5:$B$10,2,FALSE) -> 1.05 | AS73: =(AL73)*AR73 -> 42.913281 | AT73: Y | AV73: =+AX73 -> Tall Grass | AX73: =IFERROR(VLOOKUP(E73,[1]Sheet3!$C$2:$E$68,2,FALSE),"None") -> Tall Grass | AY73: =IFERROR(VLOOKUP(AX73,[1]Sheet3!$H$3:$I$5,2,FALSE),0) -> 30 | AZ73: =AJ73 -> 123.9 | BA73: =+AJ73*6.85*0.48/2 -> 203.6916 | BC73: Y | BD73: https://gpreinc.com/ | BE73: UP | BF73: Yes | BK73: =IF(M73=2,10,5)+IF(Q73="ICM",10,5)+IF(X73="Y",10,5) -> 20
A74: 73 | D74: 3196 | E74: 3623 | F74: =IF(A74<300,"Active","Retired") -> Active | G74: Green Plains | H74: =VLOOKUP(E74,'[1]EPA Ethanol Capacity 2024'!$B$5:$C$235,2,FALSE) -> Green Plains York LLC | I74: NE | J74: York | K74: 68467 | L74: York | M74: 2 | N74: 40.69874 | O74: -97.567402 | P74: 1994 | Q74: Katzen | R74: =COUNTIF(G:G,"="&G74) -> 11 | AB74: Corn | AC74: D6 | AD74: Website | AE74: =IF(BK74=1,"Low","High") -> High | AF74: 123.9 | AG74: 100 | AH74: AIR>CONSTRUCTION | AI74: 86000 | AJ74: =VLOOKUP(E74,'[1]Ethanol Plant Listing 2025'!$B$3:$E$220,4,FALSE) -> 60 | AK74: =+AJ74*[1]Yield!$K$4 -> 57 | AL74: =AK74/VLOOKUP(Q74,[1]Yield!$E$5:$F$14,2,FALSE) -> 19.860627 | AM74: 365 | AN74: =+AM74/(AL74*2.85714285714286) -> 6.4323246 | AO74: =ROUND((+AL74*13.1*1000000)/2000,-3) -> 130000 | AQ74: =IF(G74="POET Biorefining",G74,IF(T74="FQPT HI Pro",T74,IF(Z74="ICM FOT",Z74,IF(Q74="ICM",Q74,IF(Q74="ADM",Q74,"None"))))) -> None | AR74: =VLOOKUP(AQ74,[1]Yield!$A$5:$B$10,2,FALSE) -> 0.815 | AS74: =(AL74)*AR74 -> 16.186411 | AT74: Y | AV74: =+AX74 -> Tall Grass | AX74: =IFERROR(VLOOKUP(E74,[1]Sheet3!$C$2:$E$68,2,FALSE),"None") -> Tall Grass | AY74: =IFERROR(VLOOKUP(AX74,[1]Sheet3!$H$3:$I$5,2,FALSE),0) -> 30 | AZ74: =AJ74 -> 60 | BA74: =+AJ74*6.85*0.48/2 -> 98.64 | BC74: Y | BD74: https://gpreinc.com/ | BE74: BNSF | BF74: Yes | BK74: =IF(M74=2,10,5)+IF(Q74="ICM",10,5)+IF(X74="Y",10,5) -> 20
A75: 74 | B75: 1481 | C75: 71641 | D75: 3185 | E75: 3612 | F75: =IF(A75<300,"Active","Retired") -> Active | G75: GreenAmerica | H75: =VLOOKUP(E75,'[1]EPA Ethanol Capacity 2024'!$B$5:$C$235,2,FALSE) -> Green America Biofuels Ord LLC | I75: NE | J75: Ord | K75: 68862 | L75: Valley | M75: 2 | N75: 41.5701 | O75: -98.821 | P75: 2007 | Q75: ICM | R75: =COUNTIF(G:G,"="&G75) -> 1 | S75: EP3 | AB75: Corn | AC75: D6 | AD75: Website | AE75: =IF(BK75=1,"Low","High") -> High | AF75: 60 | AG75: 50 | AH75: AIR>CONSTRUCTION | AI75: 59094 | AJ75: =VLOOKUP(E75,'[1]Ethanol Plant Listing 2025'!$B$3:$E$220,4,FALSE) -> 68 | AK75: =+AJ75*[1]Yield!$K$4 -> 64.6 | AL75: =AK75/VLOOKUP(Q75,[1]Yield!$E$5:$F$14,2,FALSE) -> 21.898305 | AO75: =ROUND((+AL75*13.1*1000000)/2000,-3) -> 143000 | AP75: Rotary Dryer | AQ75: =IF(G75="POET Biorefining",G75,IF(T75="FQPT HI Pro",T75,IF(Z75="ICM FOT",Z75,IF(Q75="ICM",Q75,IF(Q75="ADM",Q75,"None"))))) -> ICM | AR75: =VLOOKUP(AQ75,[1]Yield!$A$5:$B$10,2,FALSE) -> 0.9 | AS75: =(AL75)*AR75 -> 19.708475 | AT75: Likely | AX75: =IFERROR(VLOOKUP(E75,[1]Sheet3!$C$2:$E$68,2,FALSE),"None") -> None | AY75: =IFERROR(VLOOKUP(AX75,[1]Sheet3!$H$3:$I$5,2,FALSE),0) -> 0 | AZ75: =AJ75 -> 68 | BA75: =+AJ75*6.85*0.48/2 -> 111.792 | BD75: https://www.greenamericabiofuels.com/ | BE75: BNSF | BF75: Yes | BJ75: Member | BK75: =IF(M75=2,10,5)+IF(Q75="ICM",10,5)+IF(X75="Y",10,5) -> 25 | BL75: 9/26/16 GP purchases from Abengoa for $237M
A76: 75 | D76: 3197 | E76: 3624 | F76: =IF(A76<300,"Active","Retired") -> Active | G76: Greenfield Global | H76: =VLOOKUP(E76,'[1]EPA Ethanol Capacity 2024'!$B$5:$C$235,2,FALSE) -> Greenfield Global Corn Plus LLC | I76: MN | J76: Winnebago | K76: 56098 | L76: Faribault | M76: 2 | N76: 43.760415 | O76: -94.149858 | P76: 1994 | Q76: Delta-T | R76: =COUNTIF(G:G,"="&G76) -> 1 | S76: EP3 | AB76: Corn | AC76: D6 | AD76: Website | AE76: =IF(BK76=1,"Low","High") -> High | AF76: 75 | AG76: 55 | AH76: AIR>CONSTRUCTION | AI76: 85861 | AJ76: =VLOOKUP(E76,'[1]Ethanol Plant Listing 2025'!$B$3:$E$220,4,FALSE) -> 43 | AK76: =+AJ76*[1]Yield!$K$4 -> 40.85 | AL76: =AK76/VLOOKUP(Q76,[1]Yield!$E$5:$F$14,2,FALSE) -> 14.184028 | AO76: =ROUND((+AL76*13.1*1000000)/2000,-3) -> 93000 | AP76: Ring Dryer | AQ76: =IF(G76="POET Biorefining",G76,IF(T76="FQPT HI Pro",T76,IF(Z76="ICM FOT",Z76,IF(Q76="ICM",Q76,IF(Q76="ADM",Q76,"None"))))) -> None | AR76: =VLOOKUP(AQ76,[1]Yield!$A$5:$B$10,2,FALSE) -> 0.815 | AS76: =(AL76)*AR76 -> 11.559983 | AT76: Likely | AX76: =IFERROR(VLOOKUP(E76,[1]Sheet3!$C$2:$E$68,2,FALSE),"None") -> None | AY76: =IFERROR(VLOOKUP(AX76,[1]Sheet3!$H$3:$I$5,2,FALSE),0) -> 0 | AZ76: =AJ76 -> 43 | BA76: =+AJ76*6.85*0.48/2 -> 70.692 | BD76: https://greenfield.com/ | BE76: CP | BF76: No | BK76: =IF(M76=2,10,5)+IF(Q76="ICM",10,5)+IF(X76="Y",10,5) -> 20 | BL76: 1/27/2021 GAB purchase from GP for $64M | 3/17/09 AgStar Financial purcahses US BioEnergy assets out of bancruptcy for $??M
A77: 76 | B77: 3383 | C77: 70289 | D77: 3198 | E77: 3625 | F77: =IF(A77<300,"Active","Retired") -> Active | G77: Guardian Energy, LLC | H77: =VLOOKUP(E77,'[1]EPA Ethanol Capacity 2024'!$B$5:$C$235,2,FALSE) -> Guardian Energy LLC | I77: MN | J77: Janesville | K77: 56048 | L77: Waseca | M77: 2 | N77: 44.111944 | O77: -93.678611 | P77: 2009 | Q77: ICM | R77: =COUNTIF(G:G,"="&G77) -> 3 | S77: EP3 | AB77: Corn | AC77: D6 | AD77: Website | AE77: =IF(BK77=1,"Low","High") -> High | AJ77: =VLOOKUP(E77,'[1]Ethanol Plant Listing 2025'!$B$3:$E$220,4,FALSE) -> 164 | AK77: =+AJ77*[1]Yield!$K$4 -> 155.8 | AL77: =AK77/VLOOKUP(Q77,[1]Yield!$E$5:$F$14,2,FALSE) -> 52.813559 | AO77: =ROUND((+AL77*13.1*1000000)/2000,-3) -> 346000 | AP77: Rotary Dryer | AQ77: =IF(G77="POET Biorefining",G77,IF(T77="FQPT HI Pro",T77,IF(Z77="ICM FOT",Z77,IF(Q77="ICM",Q77,IF(Q77="ADM",Q77,"None"))))) -> ICM | AR77: =VLOOKUP(AQ77,[1]Yield!$A$5:$B$10,2,FALSE) -> 0.9 | AS77: =(AL77)*AR77 -> 47.532203 | AT77: Likely | AX77: =IFERROR(VLOOKUP(E77,[1]Sheet3!$C$2:$E$68,2,FALSE),"None") -> None | AY77: =IFERROR(VLOOKUP(AX77,[1]Sheet3!$H$3:$I$5,2,FALSE),0) -> 0 | AZ77: =AJ77 -> 164 | BA77: =+AJ77*6.85*0.48/2 -> 269.616 | BD77: https://www.hankinsonre.com/janesville | BE77: CP | BF77: Yes | BJ77: Member | BK77: =IF(M77=2,10,5)+IF(Q77="ICM",10,5)+IF(X77="Y",10,5) -> 25 | BL77: 10/20 Greenfield purchases shuttered Corn Plus out of recievership
A78: 77 | B78: 6169 | C78: 70288 | D78: 3199 | E78: 3626 | F78: =IF(A78<300,"Active","Retired") -> Active | G78: Guardian Energy, LLC | H78: =VLOOKUP(E78,'[1]EPA Ethanol Capacity 2024'!$B$5:$C$235,2,FALSE) -> Hankinson Renewable Energy LLC | I78: ND | J78: Hankinson | K78: 58041 | L78: Richland | M78: 2 | N78: 46.073186 | O78: -96.886775 | P78: 2008 | Q78: ICM | R78: =COUNTIF(G:G,"="&G78) -> 3 | S78: EP3 | AB78: Corn | AC78: D6 | AD78: Website | AE78: =IF(BK78=1,"Low","High") -> High | AJ78: =VLOOKUP(E78,'[1]Ethanol Plant Listing 2025'!$B$3:$E$220,4,FALSE) -> 157.4 | AK78: =+AJ78*[1]Yield!$K$4 -> 149.53 | AL78: =AK78/VLOOKUP(Q78,[1]Yield!$E$5:$F$14,2,FALSE) -> 50.688136 | AO78: =ROUND((+AL78*13.1*1000000)/2000,-3) -> 332000 | AP78: Rotary Dryer | AQ78: =IF(G78="POET Biorefining",G78,IF(T78="FQPT HI Pro",T78,IF(Z78="ICM FOT",Z78,IF(Q78="ICM",Q78,IF(Q78="ADM",Q78,"None"))))) -> ICM | AR78: =VLOOKUP(AQ78,[1]Yield!$A$5:$B$10,2,FALSE) -> 0.9 | AS78: =(AL78)*AR78 -> 45.619322 | AT78: Likely | AX78: =IFERROR(VLOOKUP(E78,[1]Sheet3!$C$2:$E$68,2,FALSE),"None") -> None | AY78: =IFERROR(VLOOKUP(AX78,[1]Sheet3!$H$3:$I$5,2,FALSE),0) -> 0 | AZ78: =AJ78 -> 157.4 | BA78: =+AJ78*6.85*0.48/2 -> 258.7656 | BD78: https://www.hankinsonre.com/ | BE78: CP | BF78: Yes | BJ78: Member | BK78: =IF(M78=2,10,5)+IF(Q78="ICM",10,5)+IF(X78="Y",10,5) -> 25 | BL78: 8/4/09 GE purcahses from AgStar Financials re VeraSun bancruptcy
A79: 78 | D79: 3200 | E79: 3627 | F79: =IF(A79<300,"Active","Retired") -> Active | G79: Guardian Energy, LLC | H79: =VLOOKUP(E79,'[1]EPA Ethanol Capacity 2024'!$B$5:$C$235,2,FALSE) -> Guardian Lima LLC | I79: OH | J79: Lima | K79: 45804 | L79: Allen | M79: 2 | N79: 40.70588 | O79: -84.08007 | P79: 2005 | Q79: ICM | R79: =COUNTIF(G:G,"="&G79) -> 3 | S79: EP3 | AB79: Corn | AC79: D6 | AD79: Website | AE79: =IF(BK79=1,"Low","High") -> High | AJ79: =VLOOKUP(E79,'[1]Ethanol Plant Listing 2025'!$B$3:$E$220,4,FALSE) -> 84 | AK79: =+AJ79*[1]Yield!$K$4 -> 79.8 | AL79: =AK79/VLOOKUP(Q79,[1]Yield!$E$5:$F$14,2,FALSE) -> 27.050847 | AO79: =ROUND((+AL79*13.1*1000000)/2000,-3) -> 177000 | AP79: Rotary Dryer | AQ79: =IF(G79="POET Biorefining",G79,IF(T79="FQPT HI Pro",T79,IF(Z79="ICM FOT",Z79,IF(Q79="ICM",Q79,IF(Q79="ADM",Q79,"None"))))) -> ICM | AR79: =VLOOKUP(AQ79,[1]Yield!$A$5:$B$10,2,FALSE) -> 0.9 | AS79: =(AL79)*AR79 -> 24.345763 | AT79: Likely | AX79: =IFERROR(VLOOKUP(E79,[1]Sheet3!$C$2:$E$68,2,FALSE),"None") -> None | AY79: =IFERROR(VLOOKUP(AX79,[1]Sheet3!$H$3:$I$5,2,FALSE),0) -> 0 | AZ79: =AJ79 -> 84 | BA79: =+AJ79*6.85*0.48/2 -> 138.096 | BD79: https://www.guardianlima.com/lima | BE79: IORY//CSX/NS | BF79: Yes | BK79: =IF(M79=2,10,5)+IF(Q79="ICM",10,5)+IF(X79="Y",10,5) -> 25 | BL79: 3/17/09 AgStar Financial purcahses US BioEnergy assets out of bancruptcy for $??M
A80: 79 | B80: 4827 | C80: 70089 | D80: 2496 | E80: 3628 | F80: =IF(A80<300,"Active","Retired") -> Active | G80: Heartland Corn Products | H80: =VLOOKUP(E80,'[1]EPA Ethanol Capacity 2024'!$B$5:$C$235,2,FALSE) -> Heartland Corn Products | I80: MN | J80: Winthrop | K80: 55396 | L80: Sibley | M80: 2 | N80: 44.541944 | O80: -94.341667 | P80: 1995 | Q80: ICM | R80: =COUNTIF(G:G,"="&G80) -> 1 | S80: EP3 | AB80: Corn | AC80: D6 | AD80: Website | AE80: =IF(BK80=1,"Low","High") -> High | AJ80: =VLOOKUP(E80,'[1]Ethanol Plant Listing 2025'!$B$3:$E$220,4,FALSE) -> 151 | AK80: =+AJ80*[1]Yield!$K$4 -> 143.45 | AL80: =AK80/VLOOKUP(Q80,[1]Yield!$E$5:$F$14,2,FALSE) -> 48.627119 | AO80: =ROUND((+AL80*13.1*1000000)/2000,-3) -> 319000 | AP80: Rotary Dryer | AQ80: =IF(G80="POET Biorefining",G80,IF(T80="FQPT HI Pro",T80,IF(Z80="ICM FOT",Z80,IF(Q80="ICM",Q80,IF(Q80="ADM",Q80,"None"))))) -> ICM | AR80: =VLOOKUP(AQ80,[1]Yield!$A$5:$B$10,2,FALSE) -> 0.9 | AS80: =(AL80)*AR80 -> 43.764407 | AT80: Likely | AX80: =IFERROR(VLOOKUP(E80,[1]Sheet3!$C$2:$E$68,2,FALSE),"None") -> Summit Carbon Solutions | AY80: =IFERROR(VLOOKUP(AX80,[1]Sheet3!$H$3:$I$5,2,FALSE),0) -> 31 | AZ80: =AJ80 -> 151 | BA80: =+AJ80*6.85*0.48/2 -> 248.244 | BD80: https://www.heartlandcorn.com/ | BE80: TC&W/BNSF/UP/CP/CN | BF80: No | BJ80: Member | BK80: =IF(M80=2,10,5)+IF(Q80="ICM",10,5)+IF(X80="Y",10,5) -> 25
A81: 80 | C81: 21601 | D81: 3068 | E81: 3629 | F81: =IF(A81<300,"Active","Retired") -> Active | G81: Hereford Ethanol Partners | H81: =VLOOKUP(E81,'[1]EPA Ethanol Capacity 2024'!$B$5:$C$235,2,FALSE) -> Hereford Ethanol Partners LP | I81: TX | J81: Hereford | K81: 79045 | L81: Deaf Smith | M81: 3 | N81: 34.84998 | O81: -102.28679 | P81: 2007 | Q81: Lurgi | R81: =COUNTIF(G:G,"="&G81) -> 1 | AB81: Corn | AC81: D6 | AD81: Website | AE81: =IF(BK81=1,"Low","High") -> High | AJ81: =VLOOKUP(E81,'[1]Ethanol Plant Listing 2025'!$B$3:$E$220,4,FALSE) -> 120 | AK81: =+AJ81*[1]Yield!$K$4 -> 114 | AL81: =AK81/VLOOKUP(Q81,[1]Yield!$E$5:$F$14,2,FALSE) -> 40 | AO81: =ROUND((+AL81*13.1*1000000)/2000,-3) -> 262000 | AP81: Rotary Dryer | AQ81: =IF(G81="POET Biorefining",G81,IF(T81="FQPT HI Pro",T81,IF(Z81="ICM FOT",Z81,IF(Q81="ICM",Q81,IF(Q81="ADM",Q81,"None"))))) -> None | AR81: =VLOOKUP(AQ81,[1]Yield!$A$5:$B$10,2,FALSE) -> 0.815 | AS81: =(AL81)*AR81 -> 32.6 | AT81: Likely | AX81: =IFERROR(VLOOKUP(E81,[1]Sheet3!$C$2:$E$68,2,FALSE),"None") -> None | AY81: =IFERROR(VLOOKUP(AX81,[1]Sheet3!$H$3:$I$5,2,FALSE),0) -> 0 | AZ81: =AJ81 -> 120 | BA81: =+AJ81*6.85*0.48/2 -> 197.28 | BD81: https://www.herefordethanol.com/hereford-ethanol-plant/ | BE81: BNSF | BF81: Yes | BK81: =IF(M81=2,10,5)+IF(Q81="ICM",10,5)+IF(X81="Y",10,5) -> 15
A82: 81 | C82: 70097 | D82: 3201 | E82: 3630 | F82: =IF(A82<300,"Active","Retired") -> Active | G82: Granite Falls Energy | H82: =VLOOKUP(E82,'[1]EPA Ethanol Capacity 2024'!$B$5:$C$235,2,FALSE) -> Heron Lake Bioenergy LLC | I82: MN | J82: Heron Lake | K82: 56137 | L82: Jackson | M82: 2 | N82: 43.862199 | O82: -95.300983 | P82: 2007 | Q82: ICM | R82: =COUNTIF(G:G,"="&G82) -> 2 | S82: EP3 | AB82: Corn | AC82: D6 | AD82: Website | AE82: =IF(BK82=1,"Low","High") -> High | AJ82: =VLOOKUP(E82,'[1]Ethanol Plant Listing 2025'!$B$3:$E$220,4,FALSE) -> 70 | AK82: =+AJ82*[1]Yield!$K$4 -> 66.5 | AL82: =AK82/VLOOKUP(Q82,[1]Yield!$E$5:$F$14,2,FALSE) -> 22.542373 | AO82: =ROUND((+AL82*13.1*1000000)/2000,-3) -> 148000 | AP82: Rotary Dryer | AQ82: =IF(G82="POET Biorefining",G82,IF(T82="FQPT HI Pro",T82,IF(Z82="ICM FOT",Z82,IF(Q82="ICM",Q82,IF(Q82="ADM",Q82,"None"))))) -> ICM | AR82: =VLOOKUP(AQ82,[1]Yield!$A$5:$B$10,2,FALSE) -> 0.9 | AS82: =(AL82)*AR82 -> 20.288136 | AT82: Y | AX82: =IFERROR(VLOOKUP(E82,[1]Sheet3!$C$2:$E$68,2,FALSE),"None") -> Summit Carbon Solutions | AY82: =IFERROR(VLOOKUP(AX82,[1]Sheet3!$H$3:$I$5,2,FALSE),0) -> 31 | AZ82: =AJ82 -> 70 | BA82: =+AJ82*6.85*0.48/2 -> 115.08 | BD82: http://www.heronlakebioenergy.com/ | BE82: UP | BF82: Yes | BI82: Importer | BK82: =IF(M82=2,10,5)+IF(Q82="ICM",10,5)+IF(X82="Y",10,5) -> 25
A83: 82 | B83: 3303 | C83: 70235 | D83: 3202 | E83: 3631 | F83: =IF(A83<300,"Active","Retired") -> Active | G83: High Water Ethanol | H83: =VLOOKUP(E83,'[1]EPA Ethanol Capacity 2024'!$B$5:$C$235,2,FALSE) -> Highwater Ethanol LLC | I83: MN | J83: Lamberton | K83: 56152 | L83: Redwood | M83: 2 | N83: 44.23202 | O83: -95.30027 | P83: 2009 | Q83: ICM | R83: =COUNTIF(G:G,"="&G83) -> 1 | S83: EP3 | AB83: Corn | AC83: D6 | AD83: Website | AE83: =IF(BK83=1,"Low","High") -> High | AJ83: =VLOOKUP(E83,'[1]Ethanol Plant Listing 2025'!$B$3:$E$220,4,FALSE) -> 72 | AK83: =+AJ83*[1]Yield!$K$4 -> 68.4 | AL83: =AK83/VLOOKUP(Q83,[1]Yield!$E$5:$F$14,2,FALSE) -> 23.186441 | AO83: =ROUND((+AL83*13.1*1000000)/2000,-3) -> 152000 | AP83: Rotary Dryer | AQ83: =IF(G83="POET Biorefining",G83,IF(T83="FQPT HI Pro",T83,IF(Z83="ICM FOT",Z83,IF(Q83="ICM",Q83,IF(Q83="ADM",Q83,"None"))))) -> ICM | AR83: =VLOOKUP(AQ83,[1]Yield!$A$5:$B$10,2,FALSE) -> 0.9 | AS83: =(AL83)*AR83 -> 20.867797 | AT83: Y | AX83: =IFERROR(VLOOKUP(E83,[1]Sheet3!$C$2:$E$68,2,FALSE),"None") -> None | AY83: =IFERROR(VLOOKUP(AX83,[1]Sheet3!$H$3:$I$5,2,FALSE),0) -> 0 | AZ83: =AJ83 -> 72 | BA83: =+AJ83*6.85*0.48/2 -> 118.368 | BD83: http://www.highwaterethanol.com/ | BE83: CP | BF83: Yes | BJ83: Member | BK83: =IF(M83=2,10,5)+IF(Q83="ICM",10,5)+IF(X83="Y",10,5) -> 25 | BL83: 3/2021 GF purchases HL for $14M (saved plant from bancruptcy)
A84: 83 | B84: 3220 | C84: 70188 | D84: 3203 | E84: 3632 | F84: =IF(A84<300,"Active","Retired") -> Active | G84: Homeland Energy Solutions | H84: =VLOOKUP(E84,'[1]EPA Ethanol Capacity 2024'!$B$5:$C$235,2,FALSE) -> Homeland Energy Solutions LLC | I84: IA | J84: Lawler | K84: 52154 | L84: Chickasaw | M84: 2 | N84: 43.070207 | O84: -92.205 | P84: 2007 | Q84: ICM | R84: =COUNTIF(G:G,"="&G84) -> 1 | S84: EP3 | AB84: Corn | AC84: D6 | AD84: Website | AE84: =IF(BK84=1,"Low","High") -> High | AJ84: =VLOOKUP(E84,'[1]Ethanol Plant Listing 2025'!$B$3:$E$220,4,FALSE) -> 207 | AK84: =+AJ84*[1]Yield!$K$4 -> 196.65 | AL84: =AK84/VLOOKUP(Q84,[1]Yield!$E$5:$F$14,2,FALSE) -> 66.661017 | AO84: =ROUND((+AL84*13.1*1000000)/2000,-3) -> 437000 | AP84: Rotary Dryer | AQ84: =IF(G84="POET Biorefining",G84,IF(T84="FQPT HI Pro",T84,IF(Z84="ICM FOT",Z84,IF(Q84="ICM",Q84,IF(Q84="ADM",Q84,"None"))))) -> ICM | AR84: =VLOOKUP(AQ84,[1]Yield!$A$5:$B$10,2,FALSE) -> 0.9 | AS84: =(AL84)*AR84 -> 59.994915 | AT84: Y | AV84: SCS | AX84: =IFERROR(VLOOKUP(E84,[1]Sheet3!$C$2:$E$68,2,FALSE),"None") -> Summit Carbon Solutions | AY84: =IFERROR(VLOOKUP(AX84,[1]Sheet3!$H$3:$I$5,2,FALSE),0) -> 31 | AZ84: =AJ84 -> 207 | BA84: =+AJ84*6.85*0.48/2 -> 340.308 | BB84: =SUMIFS('[1]Corn 2023'!V:V,'[1]Corn 2023'!B:B,"=2023",'[1]Corn 2023'!L:L,"="&'Corn Processors'!L84) -> 147000 | BD84: https://www.homelandenergysolutions.com/ | BE84: CP | BF84: Yes | BK84: =IF(M84=2,10,5)+IF(Q84="ICM",10,5)+IF(X84="Y",10,5) -> 25
A85: 84 | B85: 5078 | C85: 70151 | D85: 3204 | E85: 3633 | F85: =IF(A85<300,"Active","Retired") -> Active | G85: Husker Ag | H85: =VLOOKUP(E85,'[1]EPA Ethanol Capacity 2024'!$B$5:$C$235,2,FALSE) -> Husker Ag LLC | I85: NE | J85: Plainview | K85: 68769 | L85: Pierce | M85: 2 | N85: 42.35066 | O85: -97.708 | P85: 2003 | Q85: ICM | R85: =COUNTIF(G:G,"="&G85) -> 2 | S85: EP3 | AB85: Corn | AC85: D6 | AD85: Website | AE85: =IF(BK85=1,"Low","High") -> High | AF85: 208.5 | AG85: 170 | AH85: 07-A-965 | AJ85: =VLOOKUP(E85,'[1]Ethanol Plant Listing 2025'!$B$3:$E$220,4,FALSE) -> 109 | AK85: =+AJ85*[1]Yield!$K$4 -> 103.55 | AL85: =AK85/VLOOKUP(Q85,[1]Yield!$E$5:$F$14,2,FALSE) -> 35.101695 | AO85: =ROUND((+AL85*13.1*1000000)/2000,-3) -> 230000 | AP85: Rotary Dryer | AQ85: =IF(G85="POET Biorefining",G85,IF(T85="FQPT HI Pro",T85,IF(Z85="ICM FOT",Z85,IF(Q85="ICM",Q85,IF(Q85="ADM",Q85,"None"))))) -> ICM | AR85: =VLOOKUP(AQ85,[1]Yield!$A$5:$B$10,2,FALSE) -> 0.9 | AS85: =(AL85)*AR85 -> 31.591525 | AT85: Y | AX85: =IFERROR(VLOOKUP(E85,[1]Sheet3!$C$2:$E$68,2,FALSE),"None") -> None | AY85: =IFERROR(VLOOKUP(AX85,[1]Sheet3!$H$3:$I$5,2,FALSE),0) -> 0 | AZ85: =AJ85 -> 109 | BA85: =+AJ85*6.85*0.48/2 -> 179.196 | BD85: https://huskerag.com/ | BE85: BNSF | BF85: No | BJ85: Member | BK85: =IF(M85=2,10,5)+IF(Q85="ICM",10,5)+IF(X85="Y",10,5) -> 25
A86: 85 | D86: 3205 | E86: 3634 | F86: =IF(A86<300,"Active","Retired") -> Active | G86: ICM | H86: =VLOOKUP(E86,'[1]EPA Ethanol Capacity 2024'!$B$5:$C$235,2,FALSE) -> ICM Biofuels LLC | I86: MO | J86: St Joseph | K86: 67030 | L86: Sedgwick | M86: 2 | N86: 39.74025 | O86: -94.8468 | P86: Unknown | Q86: ICM | R86: =COUNTIF(G:G,"="&G86) -> 1 | AB86: Corn | AC86: D6 | AD86: Website | AE86: =IF(BK86=1,"Low","High") -> High | AF86: =106.4*1.0249 -> 109.04936 | AG86: 76 | AH86: AIR>CONSTRUCTION | AI86: 73356 | AJ86: =VLOOKUP(E86,'[1]Ethanol Plant Listing 2025'!$B$3:$E$220,4,FALSE) -> 50 | AK86: =+AJ86*[1]Yield!$K$4 -> 47.5 | AL86: =AK86/VLOOKUP(Q86,[1]Yield!$E$5:$F$14,2,FALSE) -> 16.101695 | AO86: =ROUND((+AL86*13.1*1000000)/2000,-3) -> 105000 | AP86: Rotary Dryer | AQ86: =IF(G86="POET Biorefining",G86,IF(T86="FQPT HI Pro",T86,IF(Z86="ICM FOT",Z86,IF(Q86="ICM",Q86,IF(Q86="ADM",Q86,"None"))))) -> ICM | AR86: =VLOOKUP(AQ86,[1]Yield!$A$5:$B$10,2,FALSE) -> 0.9 | AS86: =(AL86)*AR86 -> 14.491525 | AT86: Unlikely | AX86: =IFERROR(VLOOKUP(E86,[1]Sheet3!$C$2:$E$68,2,FALSE),"None") -> None | AY86: =IFERROR(VLOOKUP(AX86,[1]Sheet3!$H$3:$I$5,2,FALSE),0) -> 0 | AZ86: =AJ86 -> 50 | BA86: =+AJ86*6.85*0.48/2 -> 82.2 | BD86: https://www.icmbiofuels.com/ | BE86: BNSF | BF86: No | BJ86: Member | BK86: =IF(M86=2,10,5)+IF(Q86="ICM",10,5)+IF(X86="Y",10,5) -> 25
A87: 86 | D87: 3206 | E87: 3635 | F87: =IF(A87<300,"Active","Retired") -> Active | G87: Harvestone | H87: =VLOOKUP(E87,'[1]EPA Ethanol Capacity 2024'!$B$5:$C$235,2,FALSE) -> Iroquois Bio-Energy Co LLC | I87: IN | J87: Rensselaer | K87: 47978 | L87: Jasper | M87: 2 | N87: 40.933056 | O87: -87.067222 | P87: 2006 | Q87: ICM | R87: =COUNTIF(G:G,"="&G87) -> 3 | S87: EP3 | AB87: Corn | AC87: D6 | AD87: Website | AE87: =IF(BK87=1,"Low","High") -> High | AJ87: =VLOOKUP(E87,'[1]Ethanol Plant Listing 2025'!$B$3:$E$220,4,FALSE) -> 65 | AK87: =+AJ87*[1]Yield!$K$4 -> 61.75 | AL87: =AK87/VLOOKUP(Q87,[1]Yield!$E$5:$F$14,2,FALSE) -> 20.932203 | AO87: =ROUND((+AL87*13.1*1000000)/2000,-3) -> 137000 | AP87: Rotary Dryer | AQ87: =IF(G87="POET Biorefining",G87,IF(T87="FQPT HI Pro",T87,IF(Z87="ICM FOT",Z87,IF(Q87="ICM",Q87,IF(Q87="ADM",Q87,"None"))))) -> ICM | AR87: =VLOOKUP(AQ87,[1]Yield!$A$5:$B$10,2,FALSE) -> 0.9 | AS87: =(AL87)*AR87 -> 18.838983 | AT87: Likely | AU87: Direct | AX87: =IFERROR(VLOOKUP(E87,[1]Sheet3!$C$2:$E$68,2,FALSE),"None") -> Direct Inject | AY87: =IFERROR(VLOOKUP(AX87,[1]Sheet3!$H$3:$I$5,2,FALSE),0) -> 32 | AZ87: =AJ87 -> 65 | BA87: =+AJ87*6.85*0.48/2 -> 106.86 | BD87: http://www.ibecethanol.com/ | BE87: CSX | BF87: Yes | BK87: =IF(M87=2,10,5)+IF(Q87="ICM",10,5)+IF(X87="Y",10,5) -> 25 | BL87: 9/7/16 ICM pruchases from Abengoa out of bancruptcy for $3.1M
A88: 87 | B88: 4805 | C88: 70079 | D88: 3207 | E88: 3636 | F88: =IF(A88<300,"Active","Retired") -> Active | G88: KAAPA Ethanol & Grain, LLC. | H88: =VLOOKUP(E88,'[1]EPA Ethanol Capacity 2024'!$B$5:$C$235,2,FALSE) -> Kappa Ethanol LLC | I88: NE | J88: Minden | K88: 68959 | L88: Kearney | M88: 2 | N88: 40.48343 | O88: -99.0733 | P88: 2003 | Q88: ICM | R88: =COUNTIF(G:G,"="&G88) -> 3 | AB88: Corn | AC88: D6 | AD88: Website | AE88: =IF(BK88=1,"Low","High") -> High | AJ88: =VLOOKUP(E88,'[1]Ethanol Plant Listing 2025'!$B$3:$E$220,4,FALSE) -> 87 | AK88: =+AJ88*[1]Yield!$K$4 -> 82.65 | AL88: =AK88/VLOOKUP(Q88,[1]Yield!$E$5:$F$14,2,FALSE) -> 28.016949 | AO88: =ROUND((+AL88*13.1*1000000)/2000,-3) -> 184000 | AP88: Rotary Dryer | AQ88: =IF(G88="POET Biorefining",G88,IF(T88="FQPT HI Pro",T88,IF(Z88="ICM FOT",Z88,IF(Q88="ICM",Q88,IF(Q88="ADM",Q88,"None"))))) -> ICM | AR88: =VLOOKUP(AQ88,[1]Yield!$A$5:$B$10,2,FALSE) -> 0.9 | AS88: =(AL88)*AR88 -> 25.215254 | AT88: Likely | AX88: =IFERROR(VLOOKUP(E88,[1]Sheet3!$C$2:$E$68,2,FALSE),"None") -> None | AY88: =IFERROR(VLOOKUP(AX88,[1]Sheet3!$H$3:$I$5,2,FALSE),0) -> 0 | AZ88: =AJ88 -> 87 | BA88: =+AJ88*6.85*0.48/2 -> 143.028 | BD88: https://kaapaethanolcommodities.com/ | BE88: BNSF | BF88: Yes | BJ88: Member | BK88: =IF(M88=2,10,5)+IF(Q88="ICM",10,5)+IF(X88="Y",10,5) -> 25
A89: 88 | C89: 70098 | D89: 3208 | E89: 3637 | F89: =IF(A89<300,"Active","Retired") -> Active | G89: KAAPA Ethanol & Grain, LLC. | H89: =VLOOKUP(E89,'[1]EPA Ethanol Capacity 2024'!$B$5:$C$235,2,FALSE) -> Kappa Ethanol Ravenna LLC | I89: NE | J89: Ravenna | K89: 68869 | L89: Buffalo | M89: 2 | N89: 41.023749 | O89: -98.87511 | P89: 2007 | Q89: Vogelbusch | R89: =COUNTIF(G:G,"="&G89) -> 3 | AB89: Corn | AC89: D6 | AD89: Website | AE89: =IF(BK89=1,"Low","High") -> High | AF89: =95.46*1.0245 -> 97.79877 | AG89: 60 | AH89: AIR>CONSTRUCTION | AI89: 75073 | AJ89: =VLOOKUP(E89,'[1]Ethanol Plant Listing 2025'!$B$3:$E$220,4,FALSE) -> 138 | AK89: =+AJ89*[1]Yield!$K$4 -> 131.1 | AL89: =AK89/VLOOKUP(Q89,[1]Yield!$E$5:$F$14,2,FALSE) -> 45.206897 | AO89: =ROUND((+AL89*13.1*1000000)/2000,-3) -> 296000 | AQ89: =IF(G89="POET Biorefining",G89,IF(T89="FQPT HI Pro",T89,IF(Z89="ICM FOT",Z89,IF(Q89="ICM",Q89,IF(Q89="ADM",Q89,"None"))))) -> None | AR89: =VLOOKUP(AQ89,[1]Yield!$A$5:$B$10,2,FALSE) -> 0.815 | AS89: =(AL89)*AR89 -> 36.843621 | AT89: Likely | AX89: =IFERROR(VLOOKUP(E89,[1]Sheet3!$C$2:$E$68,2,FALSE),"None") -> None | AY89: =IFERROR(VLOOKUP(AX89,[1]Sheet3!$H$3:$I$5,2,FALSE),0) -> 0 | AZ89: =AJ89 -> 138 | BA89: =+AJ89*6.85*0.48/2 -> 226.872 | BD89: https://kaapaethanolcommodities.com/ | BE89: BNSF | BF89: Yes | BJ89: Member | BK89: =IF(M89=2,10,5)+IF(Q89="ICM",10,5)+IF(X89="Y",10,5) -> 20
A90: 89 | C90: 72943 | D90: 3152 | E90: 3638 | F90: =IF(A90<300,"Active","Retired") -> Active | G90: KAAPA Ethanol & Grain, LLC. | H90: =VLOOKUP(E90,'[1]EPA Ethanol Capacity 2024'!$B$5:$C$235,2,FALSE) -> Kappa Partners Aurora LLC | I90: NE | J90: Aurora | K90: 68818 | L90: Hamilton | M90: 2 | N90: 40.86801 | O90: -98.0364 | P90: 2012 | Q90: Delta-T | R90: =COUNTIF(G:G,"="&G90) -> 3 | AA90: ICM P10 | AB90: Corn | AC90: D6 | AD90: Website | AE90: =IF(BK90=1,"Low","High") -> High | AF90: =110.51*1.05 -> 116.0355 | AH90: AIR>CONSTRUCTION | AI90: 87072 | AJ90: =VLOOKUP(E90,'[1]Ethanol Plant Listing 2025'!$B$3:$E$220,4,FALSE) -> 109.5 | AK90: =+AJ90*[1]Yield!$K$4 -> 104.025 | AL90: =AK90/VLOOKUP(Q90,[1]Yield!$E$5:$F$14,2,FALSE) -> 36.119792 | AO90: =ROUND((+AL90*13.1*1000000)/2000,-3) -> 237000 | AP90: Ring Dryer | AQ90: =IF(G90="POET Biorefining",G90,IF(T90="FQPT HI Pro",T90,IF(Z90="ICM FOT",Z90,IF(Q90="ICM",Q90,IF(Q90="ADM",Q90,"None"))))) -> None | AR90: =VLOOKUP(AQ90,[1]Yield!$A$5:$B$10,2,FALSE) -> 0.815 | AS90: =(AL90)*AR90 -> 29.43763 | AT90: Likely | AV90: =+AX90 -> Tall Grass | AX90: =IFERROR(VLOOKUP(E90,[1]Sheet3!$C$2:$E$68,2,FALSE),"None") -> Tall Grass | AY90: =IFERROR(VLOOKUP(AX90,[1]Sheet3!$H$3:$I$5,2,FALSE),0) -> 30 | AZ90: =AJ90 -> 109.5 | BA90: =+AJ90*6.85*0.48/2 -> 180.018 | BD90: https://auroracoop.com/ | BE90: BNSF | BF90: Yes | BJ90: Member | BK90: =IF(M90=2,10,5)+IF(Q90="ICM",10,5)+IF(X90="Y",10,5) -> 20 | BL90: 4/20 PEIX sells to Aurora for $52.8M | 12/2014 PEIX purchases Aventine for $380M (315M gals)
A91: 90 | B91: 5810 | C91: 70279 | D91: 3209 | E91: 3639 | F91: =IF(A91<300,"Active","Retired") -> Active | G91: Kansas Ethanol | H91: =VLOOKUP(E91,'[1]EPA Ethanol Capacity 2024'!$B$5:$C$235,2,FALSE) -> Kansas Ethanol LLC | I91: KS | J91: Lyons | K91: 67554 | L91: Rice | M91: 2 | N91: 38.28959 | O91: -98.19522 | P91: 2005 | Q91: ICM | R91: =COUNTIF(G:G,"="&G91) -> 1 | S91: EP3 | X91: White Fox ICE Flex | AB91: Corn/Milo | AC91: D6 | AD91: Website | AE91: =IF(BK91=1,"Low","High") -> High | AF91: 148 | AG91: 100 | AH91: AIR>CONSTRUCTION | AI91: 77854 | AJ91: =VLOOKUP(E91,'[1]Ethanol Plant Listing 2025'!$B$3:$E$220,4,FALSE) -> 80 | AK91: =+AJ91*[1]Yield!$K$4 -> 76 | AL91: =AK91/VLOOKUP(Q91,[1]Yield!$E$5:$F$14,2,FALSE) -> 25.762712 | AO91: =ROUND((+AL91*13.1*1000000)/2000,-3) -> 169000 | AP91: Rotary Dryer | AQ91: =IF(G91="POET Biorefining",G91,IF(T91="FQPT HI Pro",T91,IF(Z91="ICM FOT",Z91,IF(Q91="ICM",Q91,IF(Q91="ADM",Q91,"None"))))) -> ICM | AR91: =VLOOKUP(AQ91,[1]Yield!$A$5:$B$10,2,FALSE) -> 0.9 | AS91: =(AL91)*AR91 -> 23.186441 | AT91: Likely | AY91: =IFERROR(VLOOKUP(AX91,[1]Sheet3!$H$3:$I$5,2,FALSE),0) -> 0 | AZ91: =AJ91 -> 80 | BA91: =+AJ91*6.85*0.48/2 -> 131.52 | BD91: http://www.kansasethanol.net/ | BE91: UP | BF91: No | BK91: =IF(M91=2,10,5)+IF(Q91="ICM",10,5)+IF(X91="Y",10,5) -> 25 | BL91: 9/30/16 KAPPA purchases from Abengoa out of bancruptcy for $115M
A92: 91 | D92: 3210 | E92: 3640 | F92: =IF(A92<300,"Active","Retired") -> Active | G92: Lincolnland Agri Energy, LLC | H92: =VLOOKUP(E92,'[1]EPA Ethanol Capacity 2024'!$B$5:$C$235,2,FALSE) -> Lincolnland Agri-Energy LLC | I92: IL | J92: Palestine | K92: 62451 | L92: Crawford | M92: 2 | N92: 39.004293 | O92: -87.631325 | P92: 2004 | Q92: ICM | R92: =COUNTIF(G:G,"="&G92) -> 1 | T92: ICM HI PRO | U92: CHP | X92: White Fox | AB92: Corn | AC92: D6 | AD92: https://www.lincolnlandagrienergy.com/pages/custom.php?id=5427 | AE92: =IF(BK92=1,"Low","High") -> High | AJ92: =VLOOKUP(E92,'[1]Ethanol Plant Listing 2025'!$B$3:$E$220,4,FALSE) -> 68 | AK92: =+AJ92*[1]Yield!$K$4 -> 64.6 | AL92: =AK92/VLOOKUP(Q92,[1]Yield!$E$5:$F$14,2,FALSE) -> 21.898305 | AO92: =ROUND((+AL92*13.1*1000000)/2000,-3) -> 143000 | AP92: Rotary Dryer | AQ92: =IF(G92="POET Biorefining",G92,IF(T92="FQPT HI Pro",T92,IF(Z92="ICM FOT",Z92,IF(Q92="ICM",Q92,IF(Q92="ADM",Q92,"None"))))) -> ICM | AR92: =VLOOKUP(AQ92,[1]Yield!$A$5:$B$10,2,FALSE) -> 0.9 | AS92: =(AL92)*AR92 -> 19.708475 | AT92: Likely | AX92: =IFERROR(VLOOKUP(E92,[1]Sheet3!$C$2:$E$68,2,FALSE),"None") -> None | AY92: =IFERROR(VLOOKUP(AX92,[1]Sheet3!$H$3:$I$5,2,FALSE),0) -> 0 | AZ92: =AJ92 -> 68 | BA92: =+AJ92*6.85*0.48/2 -> 111.792 | BD92: https://www.lincolnlandagrienergy.com/ | BE92: CSX | BF92: No | BJ92: Member | BK92: =IF(M92=2,10,5)+IF(Q92="ICM",10,5)+IF(X92="Y",10,5) -> 25
A93: 92 | B93: 4830 | C93: 70092 | D93: 3211 | E93: 3641 | F93: =IF(A93<300,"Active","Retired") -> Active | G93: Lincolnway Energy LLC | H93: =VLOOKUP(E93,'[1]EPA Ethanol Capacity 2024'!$B$5:$C$235,2,FALSE) -> Lincolnway Energy LLC | I93: IA | J93: Nevada | K93: 50201 | L93: Story | M93: 2 | N93: 42.024869 | O93: -93.510114 | P93: 2006 | Q93: ICM | R93: =COUNTIF(G:G,"="&G93) -> 1 | S93: EP3 | X93: White Fox ICE | AB93: Corn | AC93: D6 | AD93: Website | AE93: =IF(BK93=1,"Low","High") -> High | AJ93: =VLOOKUP(E93,'[1]Ethanol Plant Listing 2025'!$B$3:$E$220,4,FALSE) -> 90 | AK93: =+AJ93*[1]Yield!$K$4 -> 85.5 | AL93: =AK93/VLOOKUP(Q93,[1]Yield!$E$5:$F$14,2,FALSE) -> 28.983051 | AM93: =500+720 -> 1220 | AN93: =+AM93/(AL93*2.85714285714286) -> 14.732749 | AO93: =ROUND((+AL93*13.1*1000000)/2000,-3) -> 190000 | AP93: Steam Tube Dryer | AQ93: =IF(G93="POET Biorefining",G93,IF(T93="FQPT HI Pro",T93,IF(Z93="ICM FOT",Z93,IF(Q93="ICM",Q93,IF(Q93="ADM",Q93,"None"))))) -> ICM | AR93: =VLOOKUP(AQ93,[1]Yield!$A$5:$B$10,2,FALSE) -> 0.9 | AS93: =(AL93)*AR93 -> 26.084746 | AT93: Y | AV93: SCS | AX93: =IFERROR(VLOOKUP(E93,[1]Sheet3!$C$2:$E$68,2,FALSE),"None") -> Summit Carbon Solutions | AY93: =IFERROR(VLOOKUP(AX93,[1]Sheet3!$H$3:$I$5,2,FALSE),0) -> 31 | AZ93: =AJ93 -> 90 | BA93: =+AJ93*6.85*0.48/2 -> 147.96 | BB93: =SUMIFS('[1]Corn 2023'!V:V,'[1]Corn 2023'!B:B,"=2023",'[1]Corn 2023'!L:L,"="&'Corn Processors'!L93) -> 152500 | BD93: https://lincolnwayenergy.com/ | BE93: UP | BF93: Yes | BJ93: Member | BK93: =IF(M93=2,10,5)+IF(Q93="ICM",10,5)+IF(X93="Y",10,5) -> 25
A94: 93 | B94: 4728 | C94: 70015 | D94: 2517 | E94: 3642 | F94: =IF(A94<300,"Active","Retired") -> Active | G94: Little Sioux Corn Processors | H94: =VLOOKUP(E94,'[1]EPA Ethanol Capacity 2024'!$B$5:$C$235,2,FALSE) -> Little Sioux Corn Processors LLLP | I94: IA | J94: Marcus | K94: 51035 | L94: Cherokee | M94: 2 | N94: 42.82085 | O94: -95.7609 | P94: 2003 | Q94: ICM | R94: =COUNTIF(G:G,"="&G94) -> 1 | S94: EP3 | T94: FQPT HI PRO | Z94: =+T94 -> FQPT HI PRO | AB94: Corn | AC94: D6/D3 | AD94: Website | AE94: =IF(BK94=1,"Low","High") -> High | AF94: 75 | AG94: 55 | AH94: 05-A-085 | AJ94: =VLOOKUP(E94,'[1]Ethanol Plant Listing 2025'!$B$3:$E$220,4,FALSE) -> 165 | AK94: =+AJ94*[1]Yield!$K$4 -> 156.75 | AL94: =AK94/VLOOKUP(Q94,[1]Yield!$E$5:$F$14,2,FALSE) -> 53.135593 | AM94: 1200 | AN94: =+AM94/(AL94*2.85714285714286) -> 7.9043062 | AO94: =ROUND((+AL94*13.1*1000000)/2000,-3) -> 348000 | AP94: Rotary Dryer | AQ94: =IF(G94="POET Biorefining",G94,IF(T94="FQPT HI Pro",T94,IF(Z94="ICM FOT",Z94,IF(Q94="ICM",Q94,IF(Q94="ADM",Q94,"None"))))) -> FQPT HI PRO | AR94: =VLOOKUP(AQ94,[1]Yield!$A$5:$B$10,2,FALSE) -> 1.05 | AS94: =(AL94)*AR94 -> 55.792373 | AT94: Y | AV94: SCS | AX94: =IFERROR(VLOOKUP(E94,[1]Sheet3!$C$2:$E$68,2,FALSE),"None") -> Summit Carbon Solutions | AY94: =IFERROR(VLOOKUP(AX94,[1]Sheet3!$H$3:$I$5,2,FALSE),0) -> 31 | AZ94: =AJ94 -> 165 | BA94: =+AJ94*6.85*0.48/2 -> 271.26 | BB94: =SUMIFS('[1]Corn 2023'!V:V,'[1]Corn 2023'!B:B,"=2023",'[1]Corn 2023'!L:L,"="&'Corn Processors'!L94) -> 148500 | BD94: https://www.littlesiouxcornprocessors.com/ | BE94: CN | BF94: Yes | BK94: =IF(M94=2,10,5)+IF(Q94="ICM",10,5)+IF(X94="Y",10,5) -> 25 | BL94: 1/20 Husker Ag takes operating control with $6.7M purchase of shares
A95: 94 | C95: 70139 | D95: 3212 | E95: 3643 | F95: =IF(A95<300,"Active","Retired") -> Active | G95: Louis Dreyfus | H95: =VLOOKUP(E95,'[1]EPA Ethanol Capacity 2024'!$B$5:$C$235,2,FALSE) -> Louis Dreyfus Co | I95: IA | J95: Grand Junction | K95: 50107 | L95: Greene | M95: 2 | N95: 42.05199 | O95: -94.24234 | P95: 2007 | Q95: ICM | R95: =COUNTIF(G:G,"="&G95) -> 1 | S95: EP3 | AB95: Corn | AC95: D6 | AD95: Website | AE95: =IF(BK95=1,"Low","High") -> High | AF95: 185 | AG95: 120 | AH95: 03-A-541 | AJ95: =VLOOKUP(E95,'[1]Ethanol Plant Listing 2025'!$B$3:$E$220,4,FALSE) -> 121.6 | AK95: =+AJ95*[1]Yield!$K$4 -> 115.52 | AL95: =AK95/VLOOKUP(Q95,[1]Yield!$E$5:$F$14,2,FALSE) -> 39.159322 | AO95: =ROUND((+AL95*13.1*1000000)/2000,-3) -> 256000 | AP95: Rotary Dryer | AQ95: =IF(G95="POET Biorefining",G95,IF(T95="FQPT HI Pro",T95,IF(Z95="ICM FOT",Z95,IF(Q95="ICM",Q95,IF(Q95="ADM",Q95,"None"))))) -> ICM | AR95: =VLOOKUP(AQ95,[1]Yield!$A$5:$B$10,2,FALSE) -> 0.9 | AS95: =(AL95)*AR95 -> 35.24339 | AT95: Y | AV95: SCS | AX95: =IFERROR(VLOOKUP(E95,[1]Sheet3!$C$2:$E$68,2,FALSE),"None") -> Summit Carbon Solutions | AY95: =IFERROR(VLOOKUP(AX95,[1]Sheet3!$H$3:$I$5,2,FALSE),0) -> 31 | AZ95: =AJ95 -> 121.6 | BA95: =+AJ95*6.85*0.48/2 -> 199.9104 | BB95: =SUMIFS('[1]Corn 2023'!V:V,'[1]Corn 2023'!B:B,"=2023",'[1]Corn 2023'!L:L,"="&'Corn Processors'!L95) -> 163500 | BD95: https://www.ldc.com/us/en/our-facilities/grand-junction-ia/ | BE95: UP | BF95: Yes | BK95: =IF(M95=2,10,5)+IF(Q95="ICM",10,5)+IF(X95="Y",10,5) -> 25
A96: 95 | B96: 5750 | C96: 70269 | D96: 3215 | E96: 3645 | F96: =IF(A96<300,"Active","Retired") -> Active | G96: United Cooperative | H96: United Energy Necadah | I96: WI | J96: Necedah | K96: 54646 | L96: Juneau | M96: 2 | N96: 43.99187 | O96: -90.07219 | P96: 0 | Q96: ICM | R96: =COUNTIF(G:G,"="&G96) -> 2 | S96: EP3 | AB96: Corn | AC96: D6 | AD96: Website | AE96: =IF(BK96=1,"Low","High") -> High | AJ96: =VLOOKUP(E96,'[1]Ethanol Plant Listing 2025'!$B$3:$E$220,4,FALSE) -> 106 | AK96: =+AJ96*[1]Yield!$K$4 -> 100.7 | AL96: =AK96/VLOOKUP(Q96,[1]Yield!$E$5:$F$14,2,FALSE) -> 34.135593 | AO96: =ROUND((+AL96*13.1*1000000)/2000,-3) -> 224000 | AP96: Rotary Dryer | AQ96: =IF(G96="POET Biorefining",G96,IF(T96="FQPT HI Pro",T96,IF(Z96="ICM FOT",Z96,IF(Q96="ICM",Q96,IF(Q96="ADM",Q96,"None"))))) -> ICM | AR96: =VLOOKUP(AQ96,[1]Yield!$A$5:$B$10,2,FALSE) -> 0.9 | AS96: =(AL96)*AR96 -> 30.722034 | AT96: Unlikely | AX96: =IFERROR(VLOOKUP(E96,[1]Sheet3!$C$2:$E$68,2,FALSE),"None") -> None | AY96: =IFERROR(VLOOKUP(AX96,[1]Sheet3!$H$3:$I$5,2,FALSE),0) -> 0 | AZ96: =AJ96 -> 106 | BA96: =+AJ96*6.85*0.48/2 -> 174.264 | BD96: http://www.marquisgrain.com/index.cfm?show=10&mid=3 | BE96: CN | BF96: Yes | BI96: Importer | BK96: =IF(M96=2,10,5)+IF(Q96="ICM",10,5)+IF(X96="Y",10,5) -> 25
A97: 96 | D97: 3212 | E97: 3644 | F97: =IF(A97<300,"Active","Retired") -> Active | G97: Marquis Energy | H97: =VLOOKUP(E97,'[1]EPA Ethanol Capacity 2024'!$B$5:$C$235,2,FALSE) -> Marquis Energy LLC | I97: IL | J97: Hennepin | K97: 61327 | L97: Putnam | M97: 2 | N97: 41.276711 | O97: -89.319504 | P97: 2007 | Q97: ICM | R97: =COUNTIF(G:G,"="&G97) -> 1 | S97: EP3 | T97: Marquis HI PRO | AB97: Corn | AC97: D6 | AD97: https://www.rivervalleycoop.com/products-services/grain#grain-bids | AE97: =IF(BK97=1,"Low","High") -> High | AJ97: =VLOOKUP(E97,'[1]Ethanol Plant Listing 2025'!$B$3:$E$220,4,FALSE) -> 400 | AK97: =+AJ97*[1]Yield!$K$4 -> 380 | AL97: =AK97/VLOOKUP(Q97,[1]Yield!$E$5:$F$14,2,FALSE) -> 128.81356 | AO97: =ROUND((+AL97*13.1*1000000)/2000,-3) -> 844000 | AP97: Steam Tube Dryer | AQ97: =IF(G97="POET Biorefining",G97,IF(T97="FQPT HI Pro",T97,IF(Z97="ICM FOT",Z97,IF(Q97="ICM",Q97,IF(Q97="ADM",Q97,"None"))))) -> ICM | AR97: =VLOOKUP(AQ97,[1]Yield!$A$5:$B$10,2,FALSE) -> 0.9 | AS97: =(AL97)*AR97 -> 115.9322 | AT97: Y | AU97: Direct | AX97: =IFERROR(VLOOKUP(E97,[1]Sheet3!$C$2:$E$68,2,FALSE),"None") -> Direct Inject | AY97: =IFERROR(VLOOKUP(AX97,[1]Sheet3!$H$3:$I$5,2,FALSE),0) -> 32 | AZ97: =AJ97 -> 400 | BA97: =+AJ97*6.85*0.48/2 -> 657.6 | BD97: http://www.marquisgrain.com/index.cfm?show=10&mid=3 | BE97: NS | BF97: Yes | BH97: Barge | BK97: =IF(M97=2,10,5)+IF(Q97="ICM",10,5)+IF(X97="Y",10,5) -> 25
A98: 97 | D98: 3216 | E98: 3646 | F98: =IF(A98<300,"Active","Retired") -> Active | G98: DCP Midstream | H98: =VLOOKUP(E98,'[1]EPA Ethanol Capacity 2024'!$B$5:$C$235,2,FALSE) -> Marysville Ethanol LLC | I98: MI | J98: Marysville | K98: 48040 | L98: St. Clair | M98: 2 | N98: 42.88335 | O98: -82.491547 | P98: 2007 | Q98: ICM | R98: =COUNTIF(G:G,"="&G98) -> 1 | AB98: Corn | AC98: D6 | AD98: Website | AE98: =IF(BK98=1,"Low","High") -> High | AJ98: =VLOOKUP(E98,'[1]Ethanol Plant Listing 2025'!$B$3:$E$220,4,FALSE) -> 60 | AK98: =+AJ98*[1]Yield!$K$4 -> 57 | AL98: =AK98/VLOOKUP(Q98,[1]Yield!$E$5:$F$14,2,FALSE) -> 19.322034 | AO98: =ROUND((+AL98*13.1*1000000)/2000,-3) -> 127000 | AP98: Rotary Dryer | AQ98: =IF(G98="POET Biorefining",G98,IF(T98="FQPT HI Pro",T98,IF(Z98="ICM FOT",Z98,IF(Q98="ICM",Q98,IF(Q98="ADM",Q98,"None"))))) -> ICM | AR98: =VLOOKUP(AQ98,[1]Yield!$A$5:$B$10,2,FALSE) -> 0.9 | AS98: =(AL98)*AR98 -> 17.389831 | AT98: Likely | AX98: =IFERROR(VLOOKUP(E98,[1]Sheet3!$C$2:$E$68,2,FALSE),"None") -> None | AY98: =IFERROR(VLOOKUP(AX98,[1]Sheet3!$H$3:$I$5,2,FALSE),0) -> 0 | AZ98: =AJ98 -> 60 | BA98: =+AJ98*6.85*0.48/2 -> 98.64 | BD98: NA | BE98: CSX/CN | BF98: No | BK98: =IF(M98=2,10,5)+IF(Q98="ICM",10,5)+IF(X98="Y",10,5) -> 25
A99: 98 | D99: 2524 | E99: 3647 | F99: =IF(A99<300,"Active","Retired") -> Active | G99: MGP | H99: =VLOOKUP(E99,'[1]EPA Ethanol Capacity 2024'!$B$5:$C$235,2,FALSE) -> MGP | I99: IN | J99: Lawrenceburg | K99: 47025 | L99: Dearborn | M99: 2 | N99: 39.098994 | O99: -84.861089 | P99: 0 | Q99: Wet Mill | R99: =COUNTIF(G:G,"="&G99) -> 1 | AB99: Corn | AC99: D6 | AD99: Website | AE99: =IF(BK99=1,"Low","High") -> High | AJ99: =VLOOKUP(E99,'[1]Ethanol Plant Listing 2025'!$B$3:$E$220,4,FALSE) -> #N/A | AK99: =+AJ99*[1]Yield!$K$4 -> #N/A | AL99: =AK99/VLOOKUP(Q99,[1]Yield!$E$5:$F$14,2,FALSE) -> #N/A | AO99: =ROUND((+AL99*13.1*1000000)/2000,-3) -> #N/A | AQ99: =IF(G99="POET Biorefining",G99,IF(T99="FQPT HI Pro",T99,IF(Z99="ICM FOT",Z99,IF(Q99="ICM",Q99,IF(Q99="ADM",Q99,"None"))))) -> None | AR99: =VLOOKUP(AQ99,[1]Yield!$A$5:$B$10,2,FALSE) -> 0.815 | AS99: =(AL99)*AR99 -> #N/A | AT99: Likely | AX99: =IFERROR(VLOOKUP(E99,[1]Sheet3!$C$2:$E$68,2,FALSE),"None") -> None | AY99: =IFERROR(VLOOKUP(AX99,[1]Sheet3!$H$3:$I$5,2,FALSE),0) -> 0 | AZ99: =AJ99 -> #N/A | BA99: =+AJ99*6.85*0.48/2 -> #N/A | BD99: https://www.mgpingredients.com/ | BE99: CSX | BF99: No | BK99: =IF(M99=2,10,5)+IF(Q99="ICM",10,5)+IF(X99="Y",10,5) -> 20
A100: 99 | B100: 5059 | C100: 70153 | D100: 3217 | E100: 3648 | F100: =IF(A100<300,"Active","Retired") -> Active | G100: Standard Ethanol | H100: =VLOOKUP(E100,'[1]EPA Ethanol Capacity 2024'!$B$5:$C$235,2,FALSE) -> Mid America Agri Products LLC | I100: NE | J100: Madrid | K100: 69150 | L100: Perkins | M100: 2 | N100: 40.85401 | O100: -101.54 | P100: 2007 | Q100: Delta-T | R100: =COUNTIF(G:G,"="&G100) -> 1 | AB100: Corn | AC100: D6/D3 | AD100: Website | AE100: =IF(BK100=1,"Low","High") -> High | AF100: 55 | AG100: 44 | AH100: AIR>CONSTRUCTION | AI100: 84220 | AJ100: =VLOOKUP(E100,'[1]Ethanol Plant Listing 2025'!$B$3:$E$220,4,FALSE) -> 50 | AK100: =+AJ100*[1]Yield!$K$4 -> 47.5 | AL100: =AK100/VLOOKUP(Q100,[1]Yield!$E$5:$F$14,2,FALSE) -> 16.493056 | AO100: =ROUND((+AL100*13.1*1000000)/2000,-3) -> 108000 | AP100: Ring Dryer | AQ100: =IF(G100="POET Biorefining",G100,IF(T100="FQPT HI Pro",T100,IF(Z100="ICM FOT",Z100,IF(Q100="ICM",Q100,IF(Q100="ADM",Q100,"None"))))) -> None | AR100: =VLOOKUP(AQ100,[1]Yield!$A$5:$B$10,2,FALSE) -> 0.815 | AS100: =(AL100)*AR100 -> 13.44184 | AT100: Y | AV100: =+AX100 -> Tall Grass | AX100: Tall Grass | AY100: =IFERROR(VLOOKUP(AX100,[1]Sheet3!$H$3:$I$5,2,FALSE),0) -> 30 | AZ100: =AJ100 -> 50 | BA100: =+AJ100*6.85*0.48/2 -> 82.2 | BD100: NA | BE100: BNSF | BF100: No | BJ100: Member | BK100: =IF(M100=2,10,5)+IF(Q100="ICM",10,5)+IF(X100="Y",10,5) -> 20
...

Sheet Summary
A1: fiber_technology | B1: count_rows | C1: count_plants | D1: min_ci | E1: max_ci | F1: avg_ci | G1: median_ci | H1: std_ci
A2: EDENIQ | B2: 35 | C2: 35 | D2: 21.93 | E2: 40.14 | F2: 27.122571 | G2: 26.38 | H2: 4.1116623
A3: BPX | B3: 28 | C3: 28 | D3: 23.48 | E3: 30.39 | F3: 26.903571 | G3: 26.955 | H3: 1.6786441
A4: SOLITON | B4: 13 | C4: 13 | D4: 23 | E4: 30.3 | F4: 25.860769 | G4: 25.28 | H4: 1.7794543
A5: Proprietary Process | B5: 4 | C5: 4 | D5: 25.94 | E5: 31.05 | F5: 27.975 | G5: 27.455 | H5: 2.2803289
A6: POET | B6: 2 | C6: 2 | D6: 25.25 | E6: 30.1 | F6: 27.675 | G6: 27.675 | H6: 3.4294679

Sheet Fiber Rows
A1: facility_id | B1: plant_name | C1: ownership | D1: state | E1: city | F1: feedstock | G1: pathway_type | H1: fiber_technology_raw | I1: fiber_technology | J1: ci_score | K1: coproduct_type | L1: gas_supply | M1: electricity_type | N1: detail_date | O1: program
A2: 70144 | B2: Absolute Energy | C2: Absolute Energy | D2: IA | E2: St. Ansgar | F2: Corn Fiber (012) | G2: Fiber | H2: EDENIQ | I2: EDENIQ | J2: 29.68 | L2: Natural Gas | M2: Grid Electricity | N2: 2026-02-11 | O2: CA
A3: 70087 | B3: Al-Corn Clean Fuel | C3: Al–Corn Clean Fuel | D3: MN | E3: Claremont | F3: Corn Fiber (012) | G3: Fiber | H3: EDENIQ | I3: EDENIQ | J3: 26.86 | L3: Natural Gas | M3: Grid Electricity | N3: 2026-02-11 | O3: CA
A4: 70247 | B4: Arkalon Ethanol LLC | C4: Conestoga Energy | D4: KS | E4: Liberal | F4: Corn Fiber (012) | G4: Fiber | H4: EDENIQ | I4: EDENIQ | J4: 24.39 | L4: Natural Gas | M4: Grid Electricity | N4: 2026-02-11 | O4: CA
A5: 70130 | B5: Badger State Ethanol LLC | C5: Badger State Ethanol | D5: WI | E5: Monroe | F5: Corn Fiber (012) | G5: Fiber | H5: EDENIQ | I5: EDENIQ | J5: 27.22 | L5: Natural Gas | M5: Grid Electricity | N5: 2026-02-11 | O5: CA
A6: 70117 | B6: Bonanza Bioenergy LLC | C6: Conestoga Energy | D6: KS | E6: Garden City | F6: Corn Fiber (012) | G6: Fiber | H6: EDENIQ | I6: EDENIQ | J6: 24.44 | L6: Natural Gas | M6: Grid Electricity | N6: 2026-02-11 | O6: CA
A7: 70150 | B7: Chief Ethanol Fuels Inc | C7: Chief Industries | D7: NE | E7: Hastings | F7: Corn Fiber (012) | G7: Fiber | H7: EDENIQ | I7: EDENIQ | J7: 40.14 | L7: Natural Gas | M7: Grid Electricity | N7: 2026-02-11 | O7: CA
A8: 70241 | B8: Chief Ethanol Fuels Inc | C8: Chief Industries | D8: NE | E8: Lexington | F8: Corn Fiber (012) | G8: Fiber | H8: EDENIQ | I8: EDENIQ | J8: 36.17 | L8: Natural Gas | M8: Grid Electricity | N8: 2026-02-11 | O8: CA
A9: 70078 | B9: Chippewa Valley Ethanol Co LLLP | C9: Chippewa Valley Ethanol Co. | D9: MN | E9: Benson | F9: Corn Fiber (012) | G9: Fiber | H9: EDENIQ | I9: EDENIQ | J9: 29 | L9: Natural Gas | M9: Grid Electricity | N9: 2026-02-11 | O9: CA
A10: 70082 | B10: Denco II LLC | C10: DENCO II | D10: MN | E10: Morris | F10: Corn Fiber (012) | G10: Fiber | H10: SOLITON | I10: SOLITON | J10: 30.3 | L10: Natural Gas | M10: Grid Electricity | N10: 2026-02-11 | O10: CA
A11: 70093 | B11: E Energy Adams LLC | C11: E Energy Adams, LLC | D11: NE | E11: Adams | F11: Corn Fiber (012) | G11: Fiber | H11: EDENIQ | I11: EDENIQ | J11: 30.47 | L11: Natural Gas | M11: Grid Electricity | N11: 2026-02-11 | O11: CA
A12: 71287 | B12: Elite Octane LLC | C12: Elite Octane | D12: IA | E12: Atlantic | F12: Corn Fiber (012) | G12: Fiber | H12: EDENIQ | I12: EDENIQ | J12: 28.35 | L12: Natural Gas | M12: Grid Electricity | N12: 2026-02-11 | O12: CA
A13: 70722 | B13: Huron Energy LLC | C13: Glacial Lakes Cooperative | D13: SD | E13: Huron | F13: Corn Fiber (012) | G13: Fiber | H13: EDENIQ | I13: EDENIQ | J13: 29.31 | L13: Natural Gas | M13: Grid Electricity | N13: 2026-02-11 | O13: CA
... A21: 70089 | B21: Heartland Corn Products | C21: Heartland Corn Products | D21: MN | E21: Winthrop | F21: Corn Fiber (012) | G21: Fiber | H21: EDENIQ | I21: EDENIQ | J21: 24 | L21: Natural Gas | M21: Grid Electricity | N21: 2026-02-11 | O21: CA
A22: 21601 | B22: Hereford Ethanol Partners LP | C22: Hereford Ethanol Partners | D22: TX | E22: Hereford | F22: Corn Fiber (012) | G22: Fiber | H22: EDENIQ | I22: EDENIQ | J22: 27 | K22: WDGS | L22: Natural Gas | M22: Grid Electricity | N22: 2026-02-11 | O22: CA
A23: 70097 | B23: Heron Lake Bioenergy LLC | C23: Granite Falls Energy | D23: MN | E23: Heron Lake | F23: Corn Fiber (012) | G23: Fiber | H23: EDENIQ | I23: EDENIQ | J23: 24.83 | L23: Natural Gas | M23: Grid Electricity | N23: 2026-02-11 | O23: CA
A24: 70235 | B24: Highwater Ethanol LLC | C24: High Water Ethanol | D24: MN | E24: Lamberton | F24: Corn Fiber (012) | G24: Fiber | H24: SOLITON | I24: SOLITON | J24: 25.13 | L24: Natural Gas | M24: Grid Electricity | N24: 2026-02-11 | O24: CA
A25: 70188 | B25: Homeland Energy Solutions LLC | C25: Homeland Energy Solutions | D25: IA | E25: Lawler | F25: Corn Fiber (012) | G25: Fiber | H25: EDENIQ | I25: EDENIQ | J25: 24.68 | L25: Natural Gas | M25: Grid Electricity | N25: 2026-02-11 | O25: CA
A26: 70151 | B26: Husker Ag LLC | C26: Husker Ag | D26: NE | E26: Plainview | F26: Corn Fiber (012) | G26: Fiber | H26: EDENIQ | I26: EDENIQ | J26: 25.83 | L26: Natural Gas | M26: Grid Electricity | N26: 2026-02-11 | O26: CA
A27: 70079 | B27: Kappa Ethanol LLC | C27: KAAPA Ethanol & Grain, LLC. | D27: NE | E27: Minden | F27: Corn Fiber (012) | G27: Fiber | H27: SOLITON | I27: SOLITON | J27: 23 | L27: Natural Gas | M27: Grid Electricity | N27: 2026-02-11 | O27: CA
A28: 70098 | B28: Kappa Ethanol Ravenna LLC | C28: KAAPA Ethanol & Grain, LLC. | D28: NE | E28: Ravenna | F28: Corn Fiber (012) | G28: Fiber | H28: SOLITON | I28: SOLITON | J28: 25.15 | L28: Natural Gas | M28: Grid Electricity | N28: 2026-02-11 | O28: CA
A29: 72943 | B29: Kappa Partners Aurora LLC | C29: KAAPA Ethanol & Grain, LLC. | D29: NE | E29: Aurora | F29: Corn Fiber (012) | G29: Fiber | H29: EDENIQ | I29: EDENIQ | J29: 27.39 | L29: Natural Gas | M29: Grid Electricity | N29: 2026-02-11 | O29: CA
A30: 70279 | B30: Kansas Ethanol LLC | C30: Kansas Ethanol | D30: KS | E30: Lyons | F30: Corn Fiber (012) | G30: Fiber | H30: EDENIQ | I30: EDENIQ | J30: 21.93 | L30: Natural Gas | M30: Grid Electricity | N30: 2026-02-11 | O30: CA
A31: 70092 | B31: Lincolnway Energy LLC | C31: Lincolnway Energy LLC | D31: IA | E31: Nevada | F31: Corn Fiber (012) | G31: Fiber | H31: EDENIQ | I31: EDENIQ | J31: 23.7 | L31: Natural Gas | M31: Grid Electricity | N31: 2026-02-11 | O31: CA
A32: 70015 | B32: Little Sioux Corn Processors LLLP | C32: Little Sioux Corn Processors | D32: IA | E32: Marcus | F32: Corn Fiber (012) | G32: Fiber | H32: EDENIQ | I32: EDENIQ | J32: 26 | L32: Natural Gas | M32: Grid Electricity | N32: 2026-02-11 | O32: CA
A33: 70139 | B33: Louis Dreyfus Co | C33: Louis Dreyfus | D33: IA | E33: Grand Junction | F33: Corn Fiber (012) | G33: Fiber | H33: EDENIQ | I33: EDENIQ | J33: 24.19 | L33: Natural Gas | M33: Grid Electricity | N33: 2026-02-11 | O33: CA
A34: 70153 | B34: Mid America Agri Products LLC | C34: Standard Ethanol | D34: NE | E34: Madrid | F34: Corn Fiber (012) | G34: Fiber | H34: SOLITON | I34: SOLITON | J34: 27.99 | L34: Natural Gas | M34: Grid Electricity | N34: 2026-02-11 | O34: CA
... A38: 70025 | B38: Poet Biorefining- Big Stone LLC | C38: POET Biorefining | D38: SD | E38: Big Stone City | F38: Corn Fiber (012) | G38: Fiber | H38: BPX | I38: BPX | J38: 28.31 | L38: Natural Gas | M38: Grid Electricity | N38: 2026-02-11 | O38: CA
A39: 70026 | B39: Poet Biorefining-Bingham Lake LLC | C39: POET Biorefining | D39: MN | E39: Bingham Lake | F39: Corn Fiber (012) | G39: Fiber | H39: BPX | I39: BPX | J39: 30 | K39: DDGS + WDGS | L39: Natural Gas | M39: Grid Electricity | N39: 2026-02-11 | O39: CA
A40: 70028 | B40: Poet Biorefinning-Caro | C40: POET Biorefining | D40: MI | E40: Caro | F40: Corn Fiber (012) | G40: Fiber | H40: BPX | I40: BPX | J40: 28.59 | L40: Natural Gas | M40: Grid Electricity | N40: 2026-02-11 | O40: CA
A41: 70012 | B41: Poet Biorefining- Chancellor LLC | C41: POET Biorefining | D41: SD | E41: Chancellor | F41: Corn Fiber (012) | G41: Fiber | H41: BPX | I41: BPX | J41: 23.48 | L41: Biogas | M41: Grid Electricity | N41: 2026-02-11 | O41: CA
A42: 70485 | B42: Poet Biorefining-Cloverdale | C42: POET Biorefining | D42: IN | E42: Cloverdale | F42: Corn Fiber (012) | G42: Fiber | H42: Proprietary Process | I42: Proprietary Process | J42: 31.05 | L42: Natural Gas | M42: Grid Electricity | N42: 2026-02-11 | O42: CA
A43: 70031 | B43: Poet Biorefinning-Coon Rapids | C43: POET Biorefining | D43: IA | E43: Coon Rapids | F43: Corn Fiber (012) | G43: Fiber | H43: BPX | I43: BPX | J43: 26.63 | K43: DDGS + WDGS | L43: Natural Gas | M43: Grid Electricity | N43: 2026-02-11 | O43: CA
A44: 70143 | B44: Poet Biorefinning-Corning LLC | C44: POET Biorefining | D44: IA | E44: Corning | F44: Corn Fiber (012) | G44: Fiber | H44: BPX | I44: BPX | J44: 26.96 | K44: DDGS + WDGS | L44: Natural Gas | M44: Grid Electricity | N44: 2026-02-11 | O44: CA
A45: 71683 | B45: Poet Biorefinning-Fairbank | C45: POET Biorefining | D45: IA | E45: Fairbank | F45: Corn Fiber (012) | G45: Fiber | H45: Proprietary Process | I45: Proprietary Process | J45: 25.94 | L45: Natural Gas | M45: Grid Electricity | N45: 2026-02-11 | O45: CA
A46: 71681 | B46: Poet Biorefining-Fairmont | C46: POET Biorefining | D46: NE | E46: Fairmont | F46: Corn Fiber (012) | G46: Fiber | H46: POET | I46: POET | J46: 30.1 | L46: Natural Gas | M46: Grid Electricity | N46: 2026-02-11 | O46: CA
A47: 70323 | B47: Poet Biorefining-Fostoria LLC | C47: POET Biorefining | D47: OH | E47: Fostoria | F47: Corn Fiber (012) | G47: Fiber | H47: BPX | I47: BPX | J47: 26.96 | L47: Natural Gas | M47: Grid Electricity | N47: 2026-02-11 | O47: CA
A48: 70020 | B48: Poet Biorefining--Glenville LLC | C48: POET Biorefining | D48: MN | E48: Albert Lea | F48: Corn Fiber (012) | G48: Fiber | H48: BPX | I48: BPX | J48: 30.39 | K48: WDGS | L48: Natural Gas | M48: Grid Electricity | N48: 2026-02-11 | O48: CA
A49: 70033 | B49: Poet Biorefinning-Gowrie LLC | C49: POET Biorefining | D49: IA | E49: Gowrie | F49: Corn Fiber (012) | G49: Fiber | H49: BPX | I49: BPX | J49: 24.96 | K49: DDGS + WDGS + MDGS | L49: Natural Gas | M49: Grid Electricity | N49: 2026-02-11 | O49: CA
A50: 70013 | B50: Poet Biorefining- Groton LLC | C50: POET Biorefining | D50: SD | E50: Groton | F50: Corn Fiber (012) | G50: Fiber | H50: BPX | I50: BPX | J50: 28.95 | K50: DDGS + WDGS | L50: Natural Gas | M50: Grid Electricity | N50: 2026-02-11 | O50: CA
A51: 70010 | B51: Poet Biorefinning-Hanlontown LLC | C51: POET Biorefining | D51: IA | E51: Hanlontown | F51: Corn Fiber (012) | G51: Fiber | H51: BPX | I51: BPX | J51: 27.88 | K51: DDGS + WDGS | L51: Natural Gas | M51: Grid Electricity | N51: 2026-02-11 | O51: CA
A52: 70022 | B52: Poet Biorefining- Hudson | C52: POET Biorefining | D52: SD | E52: Hudson | F52: Corn Fiber (012) | G52: Fiber | H52: BPX | I52: BPX | J52: 26.85 | K52: DDGS + WDGS | L52: Natural Gas | M52: Grid Electricity | N52: 2026-02-11 | O52: CA
A53: 71684 | B53: Poet Biorefinning-Iowa Falls LLC | C53: POET Biorefining | D53: IA | E53: Iowa Falls | F53: Corn Fiber (012) | G53: Fiber | H53: POET | I53: POET | J53: 25.25 | L53: Natural Gas | M53: Grid Electricity | N53: 2026-02-11 | O53: CA
A54: 70014 | B54: Poet Biorefinning-Jewell LLC | C54: POET Biorefining | D54: IA | E54: Jewell | F54: Corn Fiber (012) | G54: Fiber | H54: BPX | I54: BPX | J54: 27.18 | K54: DDGS + WDGS | L54: Natural Gas | M54: Grid Electricity | N54: 2026-02-11 | O54: CA
A55: 70023 | B55: Poet Biorefining-Laddonia LLC | C55: POET Biorefining | D55: MO | E55: Laddonia | F55: Corn Fiber (012) | G55: Fiber | H55: BPX | I55: BPX | J55: 24.02 | K55: DDGS + WDGS | L55: Natural Gas | M55: Cogeneration | N55: 2026-02-11 | O55: CA
A56: 70072 | B56: Poet Biorefining--Lake Crystal LLC | C56: POET Biorefining | D56: MN | E56: Lake Crystal | F56: Corn Fiber (012) | G56: Fiber | H56: BPX | I56: BPX | J56: 28.01 | L56: Natural Gas | M56: Grid Electricity | N56: 2026-02-11 | O56: CA
A57: 70265 | B57: Poet Biorefining-Leipsic LLC | C57: POET Biorefining | D57: OH | E57: Leipsic | F57: Corn Fiber (012) | G57: Fiber | H57: BPX | I57: BPX | J57: 28.07 | L57: Natural Gas | M57: Grid Electricity | N57: 2026-02-11 | O57: CA
A58: 70017 | B58: Poet Biorefining-Macon LLC | C58: POET Biorefining | D58: MO | E58: Macon | F58: Corn Fiber (012) | G58: Fiber | H58: BPX | I58: BPX | J58: 25.11 | L58: Natural Gas | M58: Grid Electricity | N58: 2026-02-11 | O58: CA
A59: 70327 | B59: Poet Biorefining-Marion | C59: POET Biorefining | D59: OH | E59: Marion | F59: Corn Fiber (012) | G59: Fiber | H59: BPX | I59: BPX | J59: 27.76 | L59: Natural Gas | M59: Grid Electricity | N59: 2026-02-11 | O59: CA
A60: 71685 | B60: Poet Biorefinning-Menlo | C60: POET Biorefining | D60: IA | E60: Menlo | F60: Corn Fiber (012) | G60: Fiber | H60: Proprietary Process | I60: Proprietary Process | J60: 26.6 | L60: Natural Gas | M60: Grid Electricity | N60: 2026-02-11 | O60: CA
A61: 70016 | B61: Poet Biorefining- Mitchell LLC | C61: POET Biorefining | D61: SD | E61: Mitchell | F61: Corn Fiber (012) | G61: Fiber | H61: BPX | I61: BPX | J61: 26.48 | K61: DDGS + WDGS | L61: Natural Gas | M61: Grid Electricity | N61: 2026-02-11 | O61: CA
A62: 70322 | B62: Poet Biorefining-North Manchester | C62: POET Biorefining | D62: IN | E62: North Manchester | F62: Corn Fiber (012) | G62: Fiber | H62: BPX | I62: BPX | J62: 25.32 | L62: Natural Gas | M62: Grid Electricity | N62: 2026-02-11 | O62: CA
A63: 70108 | B63: Poet Biorefining-Portland LLC | C63: POET Biorefining | D63: IN | E63: Portland | F63: Corn Fiber (012) | G63: Fiber | H63: BPX | I63: BPX | J63: 26.78 | L63: Natural Gas | M63: Grid Electricity | N63: 2026-02-11 | O63: CA
A64: 70056 | B64: Poet Biorefining--Preston LLC | C64: POET Biorefining | D64: MN | E64: Preston | F64: Corn Fiber (012) | G64: Fiber | H64: BPX | I64: BPX | J64: 27.92 | L64: Natural Gas | M64: Grid Electricity | N64: 2026-02-11 | O64: CA
A65: 20621 | B65: Poet Biorefining-Portland LLC | C65: POET Biorefining | D65: IN | E65: Shelbyville | F65: Corn Fiber (012) | G65: Fiber | H65: BPX | I65: BPX | J65: 24.91 | L65: Natural Gas | M65: Grid Electricity | N65: 2026-02-11 | O65: CA
A66: 71686 | B66: Poet Biorefinning-Shell Rock LLC | C66: POET Biorefining | D66: IA | E66: Shell Rock | F66: Corn Fiber (012) | G66: Fiber | H66: Proprietary Process | I66: Proprietary Process | J66: 28.31 | L66: Natural Gas | M66: Grid Electricity | N66: 2026-02-11 | O66: CA
A67: 70158 | B67: Pratt Energy LLC | C67: Pratt Energy (Scoular / Pratt JV) | D67: KS | E67: Pratt | F67: Corn Fiber (012) | G67: Fiber | H67: EDENIQ | I67: EDENIQ | J67: 23.25 | L67: Natural Gas | M67: Grid Electricity | N67: 2026-02-11 | O67: CA
A68: 70111 | B68: Redfield Energy LLC | C68: Redfield Energy | D68: SD | E68: Redfield | F68: Corn Fiber (012) | G68: Fiber | H68: EDENIQ | I68: EDENIQ | J68: 29.06 | L68: Natural Gas | M68: Grid Electricity | N68: 2026-02-11 | O68: CA
A69: 70112 | B69: Siouxland Energy Cooperative | C69: Sioux Center | D69: IA | E69: Sioux Center | F69: Corn Fiber (012) | G69: Fiber | H69: EDENIQ | I69: EDENIQ | J69: 22.23 | L69: Natural Gas | M69: Grid Electricity | N69: 2026-02-11 | O69: CA
A70: 70134 | B70: Siouxland Ethnaol LLC | C70: Siouxland Ethanol | D70: NE | E70: Jackson | F70: Corn Fiber (012) | G70: Fiber | H70: EDENIQ | I70: EDENIQ | J70: 25 | L70: Biogas | M70: Grid Electricity | N70: 2026-02-11 | O70: CA
A71: 70326 | B71: Sothwest Iowa Renewable | C71: SIRE | D71: IA | E71: Council Bluffs | F71: Corn Fiber (012) | G71: Fiber | H71: EDENIQ | I71: EDENIQ | J71: 23.33 | L71: Natural Gas | M71: Grid Electricity | N71: 2026-02-11 | O71: CA
A72: 70884 | B72: The Andersons Marathon Holdings LLC | C72: The Andersons | D72: IA | E72: Denison | F72: Any Cellulosic Biomass (041) | G72: Fiber | H72: EDENIQ | I72: EDENIQ | J72: 26.38 | L72: Natural Gas | M72: Grid Electricity | N72: 2026-02-11 | O72: CA
A73: 70053 | B73: Trenton Agri Products LLC | C73: Trenton Agri Products | D73: NE | E73: Trenton | F73: Corn Fiber (012) | G73: Fiber | H73: EDENIQ | I73: EDENIQ | J73: 26.52 | L73: Natural Gas | M73: Grid Electricity | N73: 2026-02-11 | O73: CA
A74: 70142 | B74: Valero Renewable Fuels LLC | C74: Valero Renewables | D74: IA | E74: Albert City | F74: Corn Fiber (012) | G74: Fiber | H74: BPX | I74: BPX | J74: 25.01 | K74: MDGS | L74: Natural Gas | M74: Grid Electricity | N74: 2026-02-11 | O74: CA
A75: 70283 | B75: Valero Renewable Fuels | C75: Valero Renewables | D75: NE | E75: Albion | F75: Corn Fiber (012) | G75: Fiber | H75: SOLITON | I75: SOLITON | J75: 25.29 | L75: Natural Gas | M75: Grid Electricity | N75: 2026-02-11 | O75: CA
A76: 70042 | B76: Valero Renewable Fuels LLC | C76: Valero Renewables | D76: IA | E76: Charles City | F76: Corn Fiber (012) | G76: Fiber | H76: SOLITON | I76: SOLITON | J76: 25.25 | L76: Natural Gas | M76: Grid Electricity | N76: 2026-02-11 | O76: CA
A77: 70043 | B77: Valero Renewable Fuels LLC | C77: Valero Renewables | D77: IA | E77: Ft. Dodge | F77: Corn Fiber (012) | G77: Fiber | H77: SOLITON | I77: SOLITON | J77: 26.8 | L77: Natural Gas | M77: Grid Electricity | N77: 2026-02-11 | O77: CA
A78: 70275 | B78: Valero Renewable Fuels LLC | C78: Valero Renewables | D78: IA | E78: Hartley | F78: Corn Fiber (012) | G78: Fiber | H78: SOLITON | I78: SOLITON | J78: 25.15 | L78: Natural Gas | M78: Grid Electricity | N78: 2026-02-11 | O78: CA
A79: 70196 | B79: Valero Renewable Fuels LLC | C79: Valero Renewables | D79: IN | E79: Linden | F79: Corn Fiber (012) | G79: Fiber | H79: SOLITON | I79: SOLITON | J79: 26.35 | L79: Natural Gas | M79: Grid Electricity | N79: 2026-02-11 | O79: CA
A80: 70276 | B80: Valero Renewable Fuels LLC | C80: Valero Renewables | D80: MN | E80: Welcome | F80: Corn Fiber (012) | G80: Fiber | H80: SOLITON | I80: SOLITON | J80: 25.28 | L80: Natural Gas | M80: Grid Electricity | N80: 2026-02-11 | O80: CA
A81: 70030 | B81: Western Plains Energy LLC | C81: Western Plains Energy | D81: KS | E81: Oakley | F81: Corn Fiber (012) | G81: Fiber | H81: EDENIQ | I81: EDENIQ | J81: 24.36 | L81: Natural Gas | M81: Grid Electricity | N81: 2026-02-11 | O81: CA
A82: 70039 | B82: Plainview Bioenergy LLC | C82: White Energy | D82: TX | E82: Plainview | F82: Corn Fiber (012) | G82: Fiber | H82: EDENIQ | I82: EDENIQ | J82: 24.89 | L82: Natural Gas | M82: Grid Electricity | N82: 2026-02-11 | O82: CA
A83: 70021 | B83: Poet Biorefinning-Emmetsburg LLC | C83: POET Biorefining | D83: IA | E83: Emmetsburg | F83: Corn Fiber (012) | G83: Fiber | H83: BPX | I83: BPX | J83: 27.51 | K83: DDGS + WDGS | L83: Natural Gas | M83: Grid Electricity | N83: 2026-02-11 | O83: CA

Sheet By Plant
A1: fiber_technology | B1: facility_id | C1: plant_name | D1: ownership | E1: state | F1: city | G1: Plant Technology | H1: rows | I1: min_ci | J1: max_ci | K1: avg_ci
A2: EDENIQ | B2: 70279 | C2: Kansas Ethanol LLC | D2: Kansas Ethanol | E2: KS | F2: Lyons | G2: =OFFSET('Corn Processors'!Q2,MATCH('By Plant'!B2,'Corn Processors'!C:C,0),) -> ICM | H2: 1 | I2: 21.93 | J2: 21.93 | K2: 21.93
A3: EDENIQ | B3: 70112 | C3: Siouxland Energy Cooperative | D3: Sioux Center | E3: IA | F3: Sioux Center | G3: =OFFSET('Corn Processors'!Q3,MATCH('By Plant'!B3,'Corn Processors'!C:C,0),) -> ICM | H3: 1 | I3: 22.23 | J3: 22.23 | K3: 22.23
A4: SOLITON | B4: 70079 | C4: Kappa Ethanol LLC | D4: KAAPA Ethanol & Grain, LLC. | E4: NE | F4: Minden | G4: =OFFSET('Corn Processors'!Q4,MATCH('By Plant'!B4,'Corn Processors'!C:C,0),) -> ICM | H4: 1 | I4: 23 | J4: 23 | K4: 23
A5: EDENIQ | B5: 70071 | C5: Granite Falls Energy LLC | D5: Granite Falls Energy | E5: MN | F5: Granite Falls | G5: =OFFSET('Corn Processors'!Q5,MATCH('By Plant'!B5,'Corn Processors'!C:C,0),) -> Vogelbusch | H5: 1 | I5: 23.22 | J5: 23.22 | K5: 23.22
A6: EDENIQ | B6: 70158 | C6: Pratt Energy LLC | D6: Pratt Energy (Scoular / Pratt JV) | E6: KS | F6: Pratt | G6: =OFFSET('Corn Processors'!Q6,MATCH('By Plant'!B6,'Corn Processors'!C:C,0),) -> Katzen | H6: 1 | I6: 23.25 | J6: 23.25 | K6: 23.25
A7: EDENIQ | B7: 70326 | C7: Sothwest Iowa Renewable | D7: SIRE | E7: IA | F7: Council Bluffs | G7: =OFFSET('Corn Processors'!Q7,MATCH('By Plant'!B7,'Corn Processors'!C:C,0),) -> ICM | H7: 1 | I7: 23.33 | J7: 23.33 | K7: 23.33
A8: BPX | B8: 70012 | C8: Poet Biorefining- Chancellor LLC | D8: POET Biorefining | E8: SD | F8: Chancellor | G8: =OFFSET('Corn Processors'!Q8,MATCH('By Plant'!B8,'Corn Processors'!C:C,0),) -> Poet | H8: 1 | I8: 23.48 | J8: 23.48 | K8: 23.48
A9: EDENIQ | B9: 70092 | C9: Lincolnway Energy LLC | D9: Lincolnway Energy LLC | E9: IA | F9: Nevada | G9: =OFFSET('Corn Processors'!Q9,MATCH('By Plant'!B9,'Corn Processors'!C:C,0),) -> Lurgi | H9: 1 | I9: 23.7 | J9: 23.7 | K9: 23.7
A10: EDENIQ | B10: 70089 | C10: Heartland Corn Products | D10: Heartland Corn Products | E10: MN | F10: Winthrop | G10: =OFFSET('Corn Processors'!Q10,MATCH('By Plant'!B10,'Corn Processors'!C:C,0),) -> Delta-T | H10: 1 | I10: 24 | J10: 24 | K10: 24
A11: BPX | B11: 70023 | C11: Poet Biorefining-Laddonia LLC | D11: POET Biorefining | E11: MO | F11: Laddonia | G11: =OFFSET('Corn Processors'!Q11,MATCH('By Plant'!B11,'Corn Processors'!C:C,0),) -> Poet | H11: 1 | I11: 24.02 | J11: 24.02 | K11: 24.02
A12: EDENIQ | B12: 70139 | C12: Louis Dreyfus Co | D12: Louis Dreyfus | E12: IA | F12: Grand Junction | G12: =OFFSET('Corn Processors'!Q12,MATCH('By Plant'!B12,'Corn Processors'!C:C,0),) -> Waste Stream | H12: 1 | I12: 24.19 | J12: 24.19 | K12: 24.19
A13: EDENIQ | B13: 70030 | C13: Western Plains Energy LLC | D13: Western Plains Energy | E13: KS | F13: Oakley | G13: =OFFSET('Corn Processors'!Q13,MATCH('By Plant'!B13,'Corn Processors'!C:C,0),) -> Unknown | H13: 1 | I13: 24.36 | J13: 24.36 | K13: 24.36
... A83: EDENIQ | B83: 70150 | C83: Chief Ethanol Fuels Inc | D83: Chief Industries | E83: NE | F83: Hastings | G83: =OFFSET('Corn Processors'!Q83,MATCH('By Plant'!B83,'Corn Processors'!C:C,0),) -> Poet | H83: 1 | I83: 40.14 | J83: 40.14 | K83: 40.14

Sheet Raw Label Check
A1: fiber_technology_raw | B1: fiber_technology | C1: count
A2: BPX | B2: BPX | C2: 28
A3: EDENIQ | B3: EDENIQ | C3: 35
A4: POET | B4: POET | C4: 2
A5: Proprietary Process | B5: Proprietary Process | C5: 4
A6: SOLITON | B6: SOLITON | C6: 13
